Workbook

Sheet assumptions
A1: MFR Analytics
A2: Financial Planning & Analysis Model
A3: 2024-2026
A6: Revenue Assumptions | B6: 2024 | C6: 2025 | D6: 2026
A7: Subscription Revenue | B7: 36000000 | C7: 41400000 | D7: =C7*(1+D10) -> 47610000
A8: Professional Services Revenue | B8: 4000000 | C8: =B8*(1+B10) -> 4600000 | D8: =C8*(1+D10) -> 5290000
A9: Total Revenue | B9: =SUM(B7:B8) -> 40000000 | C9: =SUM(C7:C8) -> 46000000 | D9: =SUM(D7:D8) -> 52900000
A10: Revenue Growth | B10: 0.15 | C10: 0.15 | D10: 0.15
A13: Department | B13: 2024 Headcount | C13: 2025 Headcount | D13: Proposed 2026 Headcount
A14: Engineering | B14: 70 | C14: 76 | D14: 82
A15: Sales | B15: 50 | C15: 55 | D15: 60
A16: Customer Success | B16: 30 | C16: 33 | D16: 36
A17: Marketing | B17: 20 | C17: 22 | D17: 24
A18: Product | B18: 15 | C18: 17 | D18: 19
A19: G&A | B19: 25 | C19: 26 | D19: 27
A20: Total | B20: =SUM(B14:B19) -> 210 | C20: =SUM(C14:C19) -> 229 | D20: =SUM(D14:D19) -> 248
A23: Department | B23: 2024 Avg. Salary | C23: 2025 Avg. Salary | D23: 2026 Avg. Salary
A24: Engineering | B24: 135000 | C24: =B24*(1+$B$34) -> 139050 | D24: =C24*(1+$C$34) -> 143221.5
A25: Sales | B25: 100000 | C25: =B25*(1+$B$34) -> 103000 | D25: =C25*(1+$C$34) -> 106090
A26: Customer Success | B26: 85000 | C26: =B26*(1+$B$34) -> 87550 | D26: =C26*(1+$C$34) -> 90176.5
A27: Marketing | B27: 95000 | C27: =B27*(1+$B$34) -> 97850 | D27: =C27*(1+$C$34) -> 100785.5
A28: Product | B28: 125000 | C28: =B28*(1+$B$34) -> 128750 | D28: =C28*(1+$C$34) -> 132612.5
A29: G&A | B29: 105000 | C29: =B29*(1+$B$34) -> 108150 | D29: =C29*(1+$C$34) -> 111394.5
A32: Assumption | B32: 2024 Value | C32: 2025 Value | D32: 2026 Value
A33: Benefits as % of Salary | B33: 0.2 | C33: 0.2 | D33: 0.2
A34: Annual Salary Increase | B34: 0.03 | C34: 0.03 | D34: 0.03
A35: Subscription Revenue % | B35: 0.9 | C35: 0.9 | D35: 0.9
A36: Professional Services Revenue % | B36: 0.1 | C36: 0.1 | D36: 0.1
A39: Operating Expense Assumptions | B39: 2024 | C39: 2025 | D39: 2026
A40: Sales Commission % of Subscription Revenue | B40: 0.05 | C40: 0.05 | D40: 0.05
A41: Software Cost per Employee | B41: 3000 | C41: 3000 | D41: 3000
A42: Sales Travel per Employee | B42: 4000 | C42: 4000 | D42: 4000
A43: Customer Success Travel Per Employee | B43: 2000 | C43: 2000 | D43: 2000
A44: Marketing Travel per Employee | B44: 2500 | C44: 2500 | D44: 2500
A45: Marketing & Advertising % of Revenue | B45: 0.06 | C45: 0.06 | D45: 0.06
A46: Engineering Cloud & Hosting % of Revenue | B46: 0.04 | C46: 0.04 | D46: 0.04
... A49: Rent & Facilities per Employee | B49: 6000 | C49: 6000 | D49: 6000
A52: Monthly Revenue Allocation | B52: Jan | C52: Feb | D52: Mar | E52: Apr | F52: May | G52: Jun | H52: Jul | I52: Aug | J52: Sep | K52: Oct | L52: Nov | M52: Dec | N52: Total
A53: % of Annual Revenue 2024 | B53: 0.07 | C53: 0.07 | D53: 0.08 | E53: 0.08 | F53: 0.08 | G53: 0.08 | H53: 0.08 | I53: 0.08 | J53: 0.09 | K53: 0.09 | L53: 0.09 | M53: 0.11 | N53: =SUM(B53:M53) -> 1
A54: % of Annual Revenue 2025 | B54: 0.07 | C54: 0.07 | D54: 0.08 | E54: 0.08 | F54: 0.08 | G54: 0.08 | H54: 0.08 | I54: 0.08 | J54: 0.09 | K54: 0.09 | L54: 0.09 | M54: 0.11 | N54: =SUM(B54:M54) -> 1

Sheet 2024_budget
A1: Revenue | B1: Jan | C1: Feb | D1: Mar | E1: Apr | F1: May | G1: Jun | H1: Jul | I1: Aug | J1: Sep | K1: Oct | L1: Nov | M1: Dec | N1: FY 2024
A2: Subscription Revenue | B2: =assumptions!$B$7*assumptions!B53 -> 2520000 | C2: =assumptions!$B$7*assumptions!C53 -> 2520000 | D2: =assumptions!$B$7*assumptions!D53 -> 2880000 | E2: =assumptions!$B$7*assumptions!E53 -> 2880000 | F2: =assumptions!$B$7*assumptions!F53 -> 2880000 | G2: =assumptions!$B$7*assumptions!G53 -> 2880000 | H2: =assumptions!$B$7*assumptions!H53 -> 2880000 | I2: =assumptions!$B$7*assumptions!I53 -> 2880000 | ... M2: =assumptions!$B$7*assumptions!M53 -> 3960000 | N2: =SUM(B2:M2) -> 36000000
A3: Professional Services | B3: =assumptions!$B$8*assumptions!B53 -> 280000 | C3: =assumptions!$B$8*assumptions!C53 -> 280000 | D3: =assumptions!$B$8*assumptions!D53 -> 320000 | E3: =assumptions!$B$8*assumptions!E53 -> 320000 | F3: =assumptions!$B$8*assumptions!F53 -> 320000 | G3: =assumptions!$B$8*assumptions!G53 -> 320000 | H3: =assumptions!$B$8*assumptions!H53 -> 320000 | I3: =assumptions!$B$8*assumptions!I53 -> 320000 | ... M3: =assumptions!$B$8*assumptions!M53 -> 440000 | N3: =SUM(B3:M3) -> 4000000
A4: Total Revenue | B4: =SUM(B2:B3) -> 2800000 | C4: =SUM(C2:C3) -> 2800000 | D4: =SUM(D2:D3) -> 3200000 | E4: =SUM(E2:E3) -> 3200000 | F4: =SUM(F2:F3) -> 3200000 | G4: =SUM(G2:G3) -> 3200000 | H4: =SUM(H2:H3) -> 3200000 | I4: =SUM(I2:I3) -> 3200000 | ... N4: =SUM(N2:N3) -> 40000000
A7: Sales | B7: Jan | C7: Feb | D7: Mar | E7: Apr | F7: May | G7: Jun | H7: Jul | I7: Aug | J7: Sep | K7: Oct | L7: Nov | M7: Dec | N7: FY 2024
A8: Salaries & Wages | B8: =assumptions!$B$15*assumptions!$B$25/12 -> 416666.67 | C8: =assumptions!$B$15*assumptions!$B$25/12 -> 416666.67 | D8: =assumptions!$B$15*assumptions!$B$25/12 -> 416666.67 | E8: =assumptions!$B$15*assumptions!$B$25/12 -> 416666.67 | F8: =assumptions!$B$15*assumptions!$B$25/12 -> 416666.67 | G8: =assumptions!$B$15*assumptions!$B$25/12 -> 416666.67 | H8: =assumptions!$B$15*assumptions!$B$25/12 -> 416666.67 | I8: =assumptions!$B$15*assumptions!$B$25/12 -> 416666.67 | ... M8: =assumptions!$B$15*assumptions!$B$25/12 -> 416666.67 | N8: =SUM(B8:M8) -> 5000000
A9: Employee Benefits | B9: =$B$8*assumptions!$B$33 -> 83333.333 | C9: =$B$8*assumptions!$B$33 -> 83333.333 | D9: =$B$8*assumptions!$B$33 -> 83333.333 | E9: =$B$8*assumptions!$B$33 -> 83333.333 | F9: =$B$8*assumptions!$B$33 -> 83333.333 | G9: =$B$8*assumptions!$B$33 -> 83333.333 | H9: =$B$8*assumptions!$B$33 -> 83333.333 | I9: =$B$8*assumptions!$B$33 -> 83333.333 | ... M9: =$B$8*assumptions!$B$33 -> 83333.333 | N9: =SUM(B9:M9) -> 1000000
A10: Sales Commissions | B10: =B2*assumptions!$B$40 -> 126000 | C10: =C2*assumptions!$B$40 -> 126000 | D10: =D2*assumptions!$B$40 -> 144000 | E10: =E2*assumptions!$B$40 -> 144000 | F10: =F2*assumptions!$B$40 -> 144000 | G10: =G2*assumptions!$B$40 -> 144000 | H10: =H2*assumptions!$B$40 -> 144000 | I10: =I2*assumptions!$B$40 -> 144000 | ... M10: =M2*assumptions!$B$40 -> 198000 | N10: =SUM(B10:M10) -> 1800000
A11: Software & Tools | B11: =(assumptions!$B$15*assumptions!$B$41)/12 -> 12500 | C11: =(assumptions!$B$15*assumptions!$B$41)/12 -> 12500 | D11: =(assumptions!$B$15*assumptions!$B$41)/12 -> 12500 | E11: =(assumptions!$B$15*assumptions!$B$41)/12 -> 12500 | F11: =(assumptions!$B$15*assumptions!$B$41)/12 -> 12500 | G11: =(assumptions!$B$15*assumptions!$B$41)/12 -> 12500 | H11: =(assumptions!$B$15*assumptions!$B$41)/12 -> 12500 | I11: =(assumptions!$B$15*assumptions!$B$41)/12 -> 12500 | ... M11: =(assumptions!$B$15*assumptions!$B$41)/12 -> 12500 | N11: =SUM(B11:M11) -> 150000
A12: Travel & Entertainment | B12: =(assumptions!$B$15*assumptions!$B$42)/12 -> 16666.667 | C12: =(assumptions!$B$15*assumptions!$B$42)/12 -> 16666.667 | D12: =(assumptions!$B$15*assumptions!$B$42)/12 -> 16666.667 | E12: =(assumptions!$B$15*assumptions!$B$42)/12 -> 16666.667 | F12: =(assumptions!$B$15*assumptions!$B$42)/12 -> 16666.667 | G12: =(assumptions!$B$15*assumptions!$B$42)/12 -> 16666.667 | H12: =(assumptions!$B$15*assumptions!$B$42)/12 -> 16666.667 | I12: =(assumptions!$B$15*assumptions!$B$42)/12 -> 16666.667 | ... M12: =(assumptions!$B$15*assumptions!$B$42)/12 -> 16666.667 | N12: =SUM(B12:M12) -> 200000
A13: Total Sales Expenses | B13: =SUM(B8:B12) -> 655166.67 | C13: =SUM(C8:C12) -> 655166.67 | D13: =SUM(D8:D12) -> 673166.67 | E13: =SUM(E8:E12) -> 673166.67 | F13: =SUM(F8:F12) -> 673166.67 | G13: =SUM(G8:G12) -> 673166.67 | H13: =SUM(H8:H12) -> 673166.67 | I13: =SUM(I8:I12) -> 673166.67 | ... N13: =SUM(N8:N12) -> 8150000
A16: Marketing | B16: Jan | C16: Feb | D16: Mar | E16: Apr | F16: May | G16: Jun | H16: Jul | I16: Aug | J16: Sep | K16: Oct | L16: Nov | M16: Dec | N16: FY 2024
A17: Salaries & Wages | B17: =(assumptions!$B$27*assumptions!$B$17)/12 -> 158333.33 | C17: =(assumptions!$B$27*assumptions!$B$17)/12 -> 158333.33 | D17: =(assumptions!$B$27*assumptions!$B$17)/12 -> 158333.33 | E17: =(assumptions!$B$27*assumptions!$B$17)/12 -> 158333.33 | F17: =(assumptions!$B$27*assumptions!$B$17)/12 -> 158333.33 | G17: =(assumptions!$B$27*assumptions!$B$17)/12 -> 158333.33 | H17: =(assumptions!$B$27*assumptions!$B$17)/12 -> 158333.33 | I17: =(assumptions!$B$27*assumptions!$B$17)/12 -> 158333.33 | ... M17: =(assumptions!$B$27*assumptions!$B$17)/12 -> 158333.33 | N17: =SUM(B17:M17) -> 1900000
A18: Employee Benefits | B18: =B17*assumptions!$B$33 -> 31666.667 | C18: =C17*assumptions!$B$33 -> 31666.667 | D18: =D17*assumptions!$B$33 -> 31666.667 | E18: =E17*assumptions!$B$33 -> 31666.667 | F18: =F17*assumptions!$B$33 -> 31666.667 | G18: =G17*assumptions!$B$33 -> 31666.667 | H18: =H17*assumptions!$B$33 -> 31666.667 | I18: =I17*assumptions!$B$33 -> 31666.667 | ... M18: =M17*assumptions!$B$33 -> 31666.667 | N18: =SUM(B18:M18) -> 380000
A19: Marketing & Advertising | B19: =B4*assumptions!$B$45 -> 168000 | C19: =C4*assumptions!$B$45 -> 168000 | D19: =D4*assumptions!$B$45 -> 192000 | E19: =E4*assumptions!$B$45 -> 192000 | F19: =F4*assumptions!$B$45 -> 192000 | G19: =G4*assumptions!$B$45 -> 192000 | H19: =H4*assumptions!$B$45 -> 192000 | I19: =I4*assumptions!$B$45 -> 192000 | ... M19: =M4*assumptions!$B$45 -> 264000 | N19: =SUM(B19:M19) -> 2400000
A20: Software & Tools | B20: =(assumptions!$B$17*assumptions!$B$41)/12 -> 5000 | C20: =(assumptions!$B$17*assumptions!$B$41)/12 -> 5000 | D20: =(assumptions!$B$17*assumptions!$B$41)/12 -> 5000 | E20: =(assumptions!$B$17*assumptions!$B$41)/12 -> 5000 | F20: =(assumptions!$B$17*assumptions!$B$41)/12 -> 5000 | G20: =(assumptions!$B$17*assumptions!$B$41)/12 -> 5000 | H20: =(assumptions!$B$17*assumptions!$B$41)/12 -> 5000 | I20: =(assumptions!$B$17*assumptions!$B$41)/12 -> 5000 | ... M20: =(assumptions!$B$17*assumptions!$B$41)/12 -> 5000 | N20: =SUM(B20:M20) -> 60000
A21: Travel & Entertainment | B21: =(assumptions!$B$44*assumptions!$B$17)/12 -> 4166.6667 | C21: =(assumptions!$B$44*assumptions!$B$17)/12 -> 4166.6667 | D21: =(assumptions!$B$44*assumptions!$B$17)/12 -> 4166.6667 | E21: =(assumptions!$B$44*assumptions!$B$17)/12 -> 4166.6667 | F21: =(assumptions!$B$44*assumptions!$B$17)/12 -> 4166.6667 | G21: =(assumptions!$B$44*assumptions!$B$17)/12 -> 4166.6667 | H21: =(assumptions!$B$44*assumptions!$B$17)/12 -> 4166.6667 | I21: =(assumptions!$B$44*assumptions!$B$17)/12 -> 4166.6667 | ... M21: =(assumptions!$B$44*assumptions!$B$17)/12 -> 4166.6667 | N21: =SUM(B21:M21) -> 50000
A22: Total Marketing Expenses | B22: =SUM(B$17:B$21) -> 367166.67 | C22: =SUM(C$17:C$21) -> 367166.67 | D22: =SUM(D$17:D$21) -> 391166.67 | E22: =SUM(E$17:E$21) -> 391166.67 | F22: =SUM(F$17:F$21) -> 391166.67 | G22: =SUM(G$17:G$21) -> 391166.67 | H22: =SUM(H$17:H$21) -> 391166.67 | I22: =SUM(I$17:I$21) -> 391166.67 | ... N22: =SUM(N$17:N$21) -> 4790000
A25: Engineering | B25: Jan | C25: Feb | D25: Mar | E25: Apr | F25: May | G25: Jun | H25: Jul | I25: Aug | J25: Sep | K25: Oct | L25: Nov | M25: Dec | N25: FY 2024
A26: Salaries & Wages | B26: =(assumptions!$B$24*assumptions!$B$14)/12 -> 787500 | C26: =(assumptions!$B$24*assumptions!$B$14)/12 -> 787500 | D26: =(assumptions!$B$24*assumptions!$B$14)/12 -> 787500 | E26: =(assumptions!$B$24*assumptions!$B$14)/12 -> 787500 | F26: =(assumptions!$B$24*assumptions!$B$14)/12 -> 787500 | G26: =(assumptions!$B$24*assumptions!$B$14)/12 -> 787500 | H26: =(assumptions!$B$24*assumptions!$B$14)/12 -> 787500 | I26: =(assumptions!$B$24*assumptions!$B$14)/12 -> 787500 | ... M26: =(assumptions!$B$24*assumptions!$B$14)/12 -> 787500 | N26: =SUM(B26:M26) -> 9450000
A27: Employee Benefits | B27: =assumptions!$B$33*B26 -> 157500 | C27: =assumptions!$B$33*C26 -> 157500 | D27: =assumptions!$B$33*D26 -> 157500 | E27: =assumptions!$B$33*E26 -> 157500 | F27: =assumptions!$B$33*F26 -> 157500 | G27: =assumptions!$B$33*G26 -> 157500 | H27: =assumptions!$B$33*H26 -> 157500 | I27: =assumptions!$B$33*I26 -> 157500 | ... M27: =assumptions!$B$33*M26 -> 157500 | N27: =SUM(B27:M27) -> 1890000
A28: Cloud & Hosting | B28: =assumptions!$B$46*B4 -> 112000 | C28: =assumptions!$B$46*C4 -> 112000 | D28: =assumptions!$B$46*D4 -> 128000 | E28: =assumptions!$B$46*E4 -> 128000 | F28: =assumptions!$B$46*F4 -> 128000 | G28: =assumptions!$B$46*G4 -> 128000 | H28: =assumptions!$B$46*H4 -> 128000 | I28: =assumptions!$B$46*I4 -> 128000 | ... M28: =assumptions!$B$46*M4 -> 176000 | N28: =SUM(B28:M28) -> 1600000
A29: Software & Tools | B29: =(assumptions!$B$14*assumptions!$B$41)/12 -> 17500 | C29: =(assumptions!$B$14*assumptions!$B$41)/12 -> 17500 | D29: =(assumptions!$B$14*assumptions!$B$41)/12 -> 17500 | E29: =(assumptions!$B$14*assumptions!$B$41)/12 -> 17500 | F29: =(assumptions!$B$14*assumptions!$B$41)/12 -> 17500 | G29: =(assumptions!$B$14*assumptions!$B$41)/12 -> 17500 | H29: =(assumptions!$B$14*assumptions!$B$41)/12 -> 17500 | I29: =(assumptions!$B$14*assumptions!$B$41)/12 -> 17500 | ... M29: =(assumptions!$B$14*assumptions!$B$41)/12 -> 17500 | N29: =SUM(B29:M29) -> 210000
A30: Total Engineering Expenses | B30: =SUM(B26:B29) -> 1074500 | C30: =SUM(C26:C29) -> 1074500 | D30: =SUM(D26:D29) -> 1090500 | E30: =SUM(E26:E29) -> 1090500 | F30: =SUM(F26:F29) -> 1090500 | G30: =SUM(G26:G29) -> 1090500 | H30: =SUM(H26:H29) -> 1090500 | I30: =SUM(I26:I29) -> 1090500 | ... N30: =SUM(N26:N29) -> 13150000
A33: Product | B33: Jan | C33: Feb | D33: Mar | E33: Apr | F33: May | G33: Jun | H33: Jul | I33: Aug | J33: Sep | K33: Oct | L33: Nov | M33: Dec | N33: FY 2024
A34: Salaries & Wages | B34: =(assumptions!$B$18*assumptions!$B$28)/12 -> 156250 | C34: =(assumptions!$B$18*assumptions!$B$28)/12 -> 156250 | D34: =(assumptions!$B$18*assumptions!$B$28)/12 -> 156250 | E34: =(assumptions!$B$18*assumptions!$B$28)/12 -> 156250 | F34: =(assumptions!$B$18*assumptions!$B$28)/12 -> 156250 | G34: =(assumptions!$B$18*assumptions!$B$28)/12 -> 156250 | H34: =(assumptions!$B$18*assumptions!$B$28)/12 -> 156250 | I34: =(assumptions!$B$18*assumptions!$B$28)/12 -> 156250 | ... M34: =(assumptions!$B$18*assumptions!$B$28)/12 -> 156250 | N34: =SUM(B34:M34) -> 1875000
A35: Employee Benefits | B35: =B34*assumptions!$B$33 -> 31250 | C35: =C34*assumptions!$B$33 -> 31250 | D35: =D34*assumptions!$B$33 -> 31250 | E35: =E34*assumptions!$B$33 -> 31250 | F35: =F34*assumptions!$B$33 -> 31250 | G35: =G34*assumptions!$B$33 -> 31250 | H35: =H34*assumptions!$B$33 -> 31250 | I35: =I34*assumptions!$B$33 -> 31250 | ... M35: =M34*assumptions!$B$33 -> 31250 | N35: =SUM(B35:M35) -> 375000
A36: Software & Tools | B36: =(assumptions!$B$18*assumptions!$B$41)/12 -> 3750 | C36: =(assumptions!$B$18*assumptions!$B$41)/12 -> 3750 | D36: =(assumptions!$B$18*assumptions!$B$41)/12 -> 3750 | E36: =(assumptions!$B$18*assumptions!$B$41)/12 -> 3750 | F36: =(assumptions!$B$18*assumptions!$B$41)/12 -> 3750 | G36: =(assumptions!$B$18*assumptions!$B$41)/12 -> 3750 | H36: =(assumptions!$B$18*assumptions!$B$41)/12 -> 3750 | I36: =(assumptions!$B$18*assumptions!$B$41)/12 -> 3750 | ... M36: =(assumptions!$B$18*assumptions!$B$41)/12 -> 3750 | N36: =SUM(B36:M36) -> 45000
A37: Professional Services | B37: =assumptions!$B$47/12 -> 20833.333 | C37: =assumptions!$B$47/12 -> 20833.333 | D37: =assumptions!$B$47/12 -> 20833.333 | E37: =assumptions!$B$47/12 -> 20833.333 | F37: =assumptions!$B$47/12 -> 20833.333 | G37: =assumptions!$B$47/12 -> 20833.333 | H37: =assumptions!$B$47/12 -> 20833.333 | I37: =assumptions!$B$47/12 -> 20833.333 | ... M37: =assumptions!$B$47/12 -> 20833.333 | N37: =SUM(B37:M37) -> 250000
A38: Total Product Expenses | B38: =SUM(B34:B37) -> 212083.33 | C38: =SUM(C34:C37) -> 212083.33 | D38: =SUM(D34:D37) -> 212083.33 | E38: =SUM(E34:E37) -> 212083.33 | F38: =SUM(F34:F37) -> 212083.33 | G38: =SUM(G34:G37) -> 212083.33 | H38: =SUM(H34:H37) -> 212083.33 | I38: =SUM(I34:I37) -> 212083.33 | ... N38: =SUM(N34:N37) -> 2545000
A41: Customer Success | B41: Jan | C41: Feb | D41: Mar | E41: Apr | F41: May | G41: Jun | H41: Jul | I41: Aug | J41: Sep | K41: Oct | L41: Nov | M41: Dec | N41: FY 2024
A42: Salaries & Wages | B42: =(assumptions!$B$26*assumptions!$B$16)/12 -> 212500 | C42: =(assumptions!$B$26*assumptions!$B$16)/12 -> 212500 | D42: =(assumptions!$B$26*assumptions!$B$16)/12 -> 212500 | E42: =(assumptions!$B$26*assumptions!$B$16)/12 -> 212500 | F42: =(assumptions!$B$26*assumptions!$B$16)/12 -> 212500 | G42: =(assumptions!$B$26*assumptions!$B$16)/12 -> 212500 | H42: =(assumptions!$B$26*assumptions!$B$16)/12 -> 212500 | I42: =(assumptions!$B$26*assumptions!$B$16)/12 -> 212500 | ... M42: =(assumptions!$B$26*assumptions!$B$16)/12 -> 212500 | N42: =SUM(B42:M42) -> 2550000
A43: Employee Benefits | B43: =B42*assumptions!$B$33 -> 42500 | C43: =C42*assumptions!$B$33 -> 42500 | D43: =D42*assumptions!$B$33 -> 42500 | E43: =E42*assumptions!$B$33 -> 42500 | F43: =F42*assumptions!$B$33 -> 42500 | G43: =G42*assumptions!$B$33 -> 42500 | H43: =H42*assumptions!$B$33 -> 42500 | I43: =I42*assumptions!$B$33 -> 42500 | ... M43: =M42*assumptions!$B$33 -> 42500 | N43: =SUM(B43:M43) -> 510000
A44: Software & Tools | B44: =(assumptions!$B$16*assumptions!$B$41)/12 -> 7500 | C44: =(assumptions!$B$16*assumptions!$B$41)/12 -> 7500 | D44: =(assumptions!$B$16*assumptions!$B$41)/12 -> 7500 | E44: =(assumptions!$B$16*assumptions!$B$41)/12 -> 7500 | F44: =(assumptions!$B$16*assumptions!$B$41)/12 -> 7500 | G44: =(assumptions!$B$16*assumptions!$B$41)/12 -> 7500 | H44: =(assumptions!$B$16*assumptions!$B$41)/12 -> 7500 | I44: =(assumptions!$B$16*assumptions!$B$41)/12 -> 7500 | ... M44: =(assumptions!$B$16*assumptions!$B$41)/12 -> 7500 | N44: =SUM(B44:M44) -> 90000
A45: Travel & Entertainment | B45: =(assumptions!$B$43*assumptions!$B$16)/12 -> 5000 | C45: =(assumptions!$B$43*assumptions!$B$16)/12 -> 5000 | D45: =(assumptions!$B$43*assumptions!$B$16)/12 -> 5000 | E45: =(assumptions!$B$43*assumptions!$B$16)/12 -> 5000 | F45: =(assumptions!$B$43*assumptions!$B$16)/12 -> 5000 | G45: =(assumptions!$B$43*assumptions!$B$16)/12 -> 5000 | H45: =(assumptions!$B$43*assumptions!$B$16)/12 -> 5000 | I45: =(assumptions!$B$43*assumptions!$B$16)/12 -> 5000 | ... M45: =(assumptions!$B$43*assumptions!$B$16)/12 -> 5000 | N45: =SUM(B45:M45) -> 60000
A46: Total Customer Success Expenses | B46: =SUM(B42:B45) -> 267500 | C46: =SUM(C42:C45) -> 267500 | D46: =SUM(D42:D45) -> 267500 | E46: =SUM(E42:E45) -> 267500 | F46: =SUM(F42:F45) -> 267500 | G46: =SUM(G42:G45) -> 267500 | H46: =SUM(H42:H45) -> 267500 | I46: =SUM(I42:I45) -> 267500 | ... M46: =SUM(M42:M45) -> 267500 | N46: =SUM(B46:M46) -> 3210000
A49: G&A | B49: Jan | C49: Feb | D49: Mar | E49: Apr | F49: May | G49: Jun | H49: Jul | I49: Aug | J49: Sep | K49: Oct | L49: Nov | M49: Dec | N49: FY 2024
A50: Salaries & Wages | B50: =(assumptions!$B$19*assumptions!$B$29)/12 -> 218750 | C50: =(assumptions!$B$19*assumptions!$B$29)/12 -> 218750 | D50: =(assumptions!$B$19*assumptions!$B$29)/12 -> 218750 | E50: =(assumptions!$B$19*assumptions!$B$29)/12 -> 218750 | F50: =(assumptions!$B$19*assumptions!$B$29)/12 -> 218750 | G50: =(assumptions!$B$19*assumptions!$B$29)/12 -> 218750 | H50: =(assumptions!$B$19*assumptions!$B$29)/12 -> 218750 | I50: =(assumptions!$B$19*assumptions!$B$29)/12 -> 218750 | ... N50: =(assumptions!$B$19*assumptions!$B$29)/12 -> 218750
A51: Employee Benefits | B51: =B50*assumptions!$B$33 -> 43750 | C51: =C50*assumptions!$B$33 -> 43750 | D51: =D50*assumptions!$B$33 -> 43750 | E51: =E50*assumptions!$B$33 -> 43750 | F51: =F50*assumptions!$B$33 -> 43750 | G51: =G50*assumptions!$B$33 -> 43750 | H51: =H50*assumptions!$B$33 -> 43750 | I51: =I50*assumptions!$B$33 -> 43750 | ... N51: =N50*assumptions!$B$33 -> 43750
A52: Software & Tools | B52: =(assumptions!$B$19*assumptions!$B$41)/12 -> 6250 | C52: =(assumptions!$B$19*assumptions!$B$41)/12 -> 6250 | D52: =(assumptions!$B$19*assumptions!$B$41)/12 -> 6250 | E52: =(assumptions!$B$19*assumptions!$B$41)/12 -> 6250 | F52: =(assumptions!$B$19*assumptions!$B$41)/12 -> 6250 | G52: =(assumptions!$B$19*assumptions!$B$41)/12 -> 6250 | H52: =(assumptions!$B$19*assumptions!$B$41)/12 -> 6250 | I52: =(assumptions!$B$19*assumptions!$B$41)/12 -> 6250 | ... N52: =(assumptions!$B$19*assumptions!$B$41)/12 -> 6250
A53: Consulting & Professional Fees | B53: =assumptions!$B$48/12 -> 33333.333 | C53: =assumptions!$B$48/12 -> 33333.333 | D53: =assumptions!$B$48/12 -> 33333.333 | E53: =assumptions!$B$48/12 -> 33333.333 | F53: =assumptions!$B$48/12 -> 33333.333 | G53: =assumptions!$B$48/12 -> 33333.333 | H53: =assumptions!$B$48/12 -> 33333.333 | I53: =assumptions!$B$48/12 -> 33333.333 | ... N53: =assumptions!$B$48/12 -> 33333.333
A54: Rent & Facilities | B54: =(assumptions!$B$49*assumptions!$B$19)/12 -> 12500 | C54: =(assumptions!$B$49*assumptions!$B$19)/12 -> 12500 | D54: =(assumptions!$B$49*assumptions!$B$19)/12 -> 12500 | E54: =(assumptions!$B$49*assumptions!$B$19)/12 -> 12500 | F54: =(assumptions!$B$49*assumptions!$B$19)/12 -> 12500 | G54: =(assumptions!$B$49*assumptions!$B$19)/12 -> 12500 | H54: =(assumptions!$B$49*assumptions!$B$19)/12 -> 12500 | I54: =(assumptions!$B$49*assumptions!$B$19)/12 -> 12500 | ... N54: =(assumptions!$B$49*assumptions!$B$19)/12 -> 12500
A55: Total G&A Expenses | B55: =SUM(B50:B54) -> 314583.33 | C55: =SUM(C50:C54) -> 314583.33 | D55: =SUM(D50:D54) -> 314583.33 | E55: =SUM(E50:E54) -> 314583.33 | F55: =SUM(F50:F54) -> 314583.33 | G55: =SUM(G50:G54) -> 314583.33 | H55: =SUM(H50:H54) -> 314583.33 | I55: =SUM(I50:I54) -> 314583.33 | ... M55: =SUM(M50:M54) -> 314583.33 | N55: =SUM(B55:M55) -> 3775000
A58: 2024 Budget Summary | B58: Jan | C58: Feb | D58: Mar | E58: Apr | F58: May | G58: Jun | H58: Jul | I58: Aug | J58: Sep | K58: Oct | L58: Nov | M58: Dec | N58: FY 2024
A59: Total Revenue | B59: =B4 -> 2800000 | C59: =C4 -> 2800000 | D59: =D4 -> 3200000 | E59: =E4 -> 3200000 | F59: =F4 -> 3200000 | G59: =G4 -> 3200000 | H59: =H4 -> 3200000 | I59: =I4 -> 3200000 | ... M59: =M4 -> 4400000 | N59: =SUM(B59:M59) -> 40000000
A61: Sales Expenses | B61: =B13 -> 655166.67 | C61: =C13 -> 655166.67 | D61: =D13 -> 673166.67 | E61: =E13 -> 673166.67 | F61: =F13 -> 673166.67 | G61: =G13 -> 673166.67 | H61: =H13 -> 673166.67 | I61: =I13 -> 673166.67 | ... M61: =M13 -> 727166.67 | N61: =SUM(B61:M61) -> 8150000
A62: Marketing Expenses | B62: =B22 -> 367166.67 | C62: =C22 -> 367166.67 | D62: =D22 -> 391166.67 | E62: =E22 -> 391166.67 | F62: =F22 -> 391166.67 | G62: =G22 -> 391166.67 | H62: =H22 -> 391166.67 | I62: =I22 -> 391166.67 | ... M62: =M22 -> 463166.67 | N62: =SUM(B62:M62) -> 4790000
A63: Engineering Expenses | B63: =B30 -> 1074500 | C63: =C30 -> 1074500 | D63: =D30 -> 1090500 | E63: =E30 -> 1090500 | F63: =F30 -> 1090500 | G63: =G30 -> 1090500 | H63: =H30 -> 1090500 | I63: =I30 -> 1090500 | ... M63: =M30 -> 1138500 | N63: =SUM(B63:M63) -> 13150000
A64: Product Expenses | B64: =B38 -> 212083.33 | C64: =C38 -> 212083.33 | D64: =D38 -> 212083.33 | E64: =E38 -> 212083.33 | F64: =F38 -> 212083.33 | G64: =G38 -> 212083.33 | H64: =H38 -> 212083.33 | I64: =I38 -> 212083.33 | ... M64: =M38 -> 212083.33 | N64: =SUM(B64:M64) -> 2545000
A65: Customer Success Expenses | B65: =B46 -> 267500 | C65: =C46 -> 267500 | D65: =D46 -> 267500 | E65: =E46 -> 267500 | F65: =F46 -> 267500 | G65: =G46 -> 267500 | H65: =H46 -> 267500 | I65: =I46 -> 267500 | ... M65: =M46 -> 267500 | N65: =SUM(B65:M65) -> 3210000
A66: G&A Expenses | B66: =B55 -> 314583.33 | C66: =C55 -> 314583.33 | D66: =D55 -> 314583.33 | E66: =E55 -> 314583.33 | F66: =F55 -> 314583.33 | G66: =G55 -> 314583.33 | H66: =H55 -> 314583.33 | I66: =I55 -> 314583.33 | ... M66: =M55 -> 314583.33 | N66: =SUM(B66:M66) -> 3775000
A67: Total Operating Expenses | B67: =SUM(B61:B66) -> 2891000 | C67: =SUM(C61:C66) -> 2891000 | D67: =SUM(D61:D66) -> 2949000 | E67: =SUM(E61:E66) -> 2949000 | F67: =SUM(F61:F66) -> 2949000 | G67: =SUM(G61:G66) -> 2949000 | H67: =SUM(H61:H66) -> 2949000 | I67: =SUM(I61:I66) -> 2949000 | ... M67: =SUM(M61:M66) -> 3123000 | N67: =SUM(B67:M67) -> 35620000
A69: Operating Profit | B69: =B59-B67 -> -91000 | C69: =C59-C67 -> -91000 | D69: =D59-D67 -> 251000 | E69: =E59-E67 -> 251000 | F69: =F59-F67 -> 251000 | G69: =G59-G67 -> 251000 | H69: =H59-H67 -> 251000 | I69: =I59-I67 -> 251000 | ... N69: =N59-N67 -> 4380000
A70: Operating Margin | B70: =B69/B59 -> -0.0325 | C70: =C69/C59 -> -0.0325 | D70: =D69/D59 -> 0.0784375 | E70: =E69/E59 -> 0.0784375 | F70: =F69/F59 -> 0.0784375 | G70: =G69/G59 -> 0.0784375 | H70: =H69/H59 -> 0.0784375 | I70: =I69/I59 -> 0.0784375 | ... N70: =N69/N59 -> 0.1095

Sheet 2025_budget
A1: Revenue | B1: Jan | C1: Feb | D1: Mar | E1: Apr | F1: May | G1: Jun | H1: Jul | I1: Aug | J1: Sep | K1: Oct | L1: Nov | M1: Dec | N1: FY 2025
A2: Subscription Revenue | B2: =assumptions!$C$7*assumptions!B53 -> 2898000 | C2: =assumptions!$C$7*assumptions!C53 -> 2898000 | D2: =assumptions!$C$7*assumptions!D53 -> 3312000 | E2: =assumptions!$C$7*assumptions!E53 -> 3312000 | F2: =assumptions!$C$7*assumptions!F53 -> 3312000 | G2: =assumptions!$C$7*assumptions!G53 -> 3312000 | H2: =assumptions!$C$7*assumptions!H53 -> 3312000 | I2: =assumptions!$C$7*assumptions!I53 -> 3312000 | ... M2: =assumptions!$C$7*assumptions!M53 -> 4554000 | N2: =SUM(B2:M2) -> 41400000
A3: Professional Services | B3: =assumptions!$C$8*assumptions!B53 -> 322000 | C3: =assumptions!$C$8*assumptions!C53 -> 322000 | D3: =assumptions!$C$8*assumptions!D53 -> 368000 | E3: =assumptions!$C$8*assumptions!E53 -> 368000 | F3: =assumptions!$C$8*assumptions!F53 -> 368000 | G3: =assumptions!$C$8*assumptions!G53 -> 368000 | H3: =assumptions!$C$8*assumptions!H53 -> 368000 | I3: =assumptions!$C$8*assumptions!I53 -> 368000 | ... M3: =assumptions!$C$8*assumptions!M53 -> 506000 | N3: =SUM(B3:M3) -> 4600000
A4: Total Revenue | B4: =SUM(B2:B3) -> 3220000 | C4: =SUM(C2:C3) -> 3220000 | D4: =SUM(D2:D3) -> 3680000 | E4: =SUM(E2:E3) -> 3680000 | F4: =SUM(F2:F3) -> 3680000 | G4: =SUM(G2:G3) -> 3680000 | H4: =SUM(H2:H3) -> 3680000 | I4: =SUM(I2:I3) -> 3680000 | ... N4: =SUM(N2:N3) -> 46000000
A7: Sales | B7: Jan | C7: Feb | D7: Mar | E7: Apr | F7: May | G7: Jun | H7: Jul | I7: Aug | J7: Sep | K7: Oct | L7: Nov | M7: Dec | N7: FY 2025
A8: Salaries & Wages | B8: =assumptions!$C$15*assumptions!$C$25/12 -> 472083.33 | C8: =assumptions!$C$15*assumptions!$C$25/12 -> 472083.33 | D8: =assumptions!$C$15*assumptions!$C$25/12 -> 472083.33 | E8: =assumptions!$C$15*assumptions!$C$25/12 -> 472083.33 | F8: =assumptions!$C$15*assumptions!$C$25/12 -> 472083.33 | G8: =assumptions!$C$15*assumptions!$C$25/12 -> 472083.33 | H8: =assumptions!$C$15*assumptions!$C$25/12 -> 472083.33 | I8: =assumptions!$C$15*assumptions!$C$25/12 -> 472083.33 | ... M8: =assumptions!$C$15*assumptions!$C$25/12 -> 472083.33 | N8: =SUM(B8:M8) -> 5665000
A9: Employee Benefits | B9: =$B$8*assumptions!$C$33 -> 94416.667 | C9: =$B$8*assumptions!$C$33 -> 94416.667 | D9: =$B$8*assumptions!$C$33 -> 94416.667 | E9: =$B$8*assumptions!$C$33 -> 94416.667 | F9: =$B$8*assumptions!$C$33 -> 94416.667 | G9: =$B$8*assumptions!$C$33 -> 94416.667 | H9: =$B$8*assumptions!$C$33 -> 94416.667 | I9: =$B$8*assumptions!$C$33 -> 94416.667 | ... M9: =$B$8*assumptions!$C$33 -> 94416.667 | N9: =SUM(B9:M9) -> 1133000
A10: Sales Commissions | B10: =B2*assumptions!$C$40 -> 144900 | C10: =C2*assumptions!$C$40 -> 144900 | D10: =D2*assumptions!$C$40 -> 165600 | E10: =E2*assumptions!$C$40 -> 165600 | F10: =F2*assumptions!$C$40 -> 165600 | G10: =G2*assumptions!$C$40 -> 165600 | H10: =H2*assumptions!$C$40 -> 165600 | I10: =I2*assumptions!$C$40 -> 165600 | ... M10: =M2*assumptions!$C$40 -> 227700 | N10: =SUM(B10:M10) -> 2070000
A11: Software & Tools | B11: =(assumptions!$C$15*assumptions!$C$41)/12 -> 13750 | C11: =(assumptions!$C$15*assumptions!$C$41)/12 -> 13750 | D11: =(assumptions!$C$15*assumptions!$C$41)/12 -> 13750 | E11: =(assumptions!$C$15*assumptions!$C$41)/12 -> 13750 | F11: =(assumptions!$C$15*assumptions!$C$41)/12 -> 13750 | G11: =(assumptions!$C$15*assumptions!$C$41)/12 -> 13750 | H11: =(assumptions!$C$15*assumptions!$C$41)/12 -> 13750 | I11: =(assumptions!$C$15*assumptions!$C$41)/12 -> 13750 | ... M11: =(assumptions!$C$15*assumptions!$C$41)/12 -> 13750 | N11: =SUM(B11:M11) -> 165000
A12: Travel & Entertainment | B12: =(assumptions!$C$15*assumptions!$C$42)/12 -> 18333.333 | C12: =(assumptions!$C$15*assumptions!$C$42)/12 -> 18333.333 | D12: =(assumptions!$C$15*assumptions!$C$42)/12 -> 18333.333 | E12: =(assumptions!$C$15*assumptions!$C$42)/12 -> 18333.333 | F12: =(assumptions!$C$15*assumptions!$C$42)/12 -> 18333.333 | G12: =(assumptions!$C$15*assumptions!$C$42)/12 -> 18333.333 | H12: =(assumptions!$C$15*assumptions!$C$42)/12 -> 18333.333 | I12: =(assumptions!$C$15*assumptions!$C$42)/12 -> 18333.333 | ... M12: =(assumptions!$C$15*assumptions!$C$42)/12 -> 18333.333 | N12: =SUM(B12:M12) -> 220000
A13: Total Sales Expenses | B13: =SUM(B8:B12) -> 743483.33 | C13: =SUM(C8:C12) -> 743483.33 | D13: =SUM(D8:D12) -> 764183.33 | E13: =SUM(E8:E12) -> 764183.33 | F13: =SUM(F8:F12) -> 764183.33 | G13: =SUM(G8:G12) -> 764183.33 | H13: =SUM(H8:H12) -> 764183.33 | I13: =SUM(I8:I12) -> 764183.33 | ... N13: =SUM(N8:N12) -> 9253000
A16: Marketing | B16: Jan | C16: Feb | D16: Mar | E16: Apr | F16: May | G16: Jun | H16: Jul | I16: Aug | J16: Sep | K16: Oct | L16: Nov | M16: Dec | N16: FY 2025
A17: Salaries & Wages | B17: =(assumptions!$C$27*assumptions!$C$17)/12 -> 179391.67 | C17: =(assumptions!$C$27*assumptions!$C$17)/12 -> 179391.67 | D17: =(assumptions!$C$27*assumptions!$C$17)/12 -> 179391.67 | E17: =(assumptions!$C$27*assumptions!$C$17)/12 -> 179391.67 | F17: =(assumptions!$C$27*assumptions!$C$17)/12 -> 179391.67 | G17: =(assumptions!$C$27*assumptions!$C$17)/12 -> 179391.67 | H17: =(assumptions!$C$27*assumptions!$C$17)/12 -> 179391.67 | I17: =(assumptions!$C$27*assumptions!$C$17)/12 -> 179391.67 | ... M17: =(assumptions!$C$27*assumptions!$C$17)/12 -> 179391.67 | N17: =SUM(B17:M17) -> 2152700
A18: Employee Benefits | B18: =B17*assumptions!$C$33 -> 35878.333 | C18: =C17*assumptions!$C$33 -> 35878.333 | D18: =D17*assumptions!$C$33 -> 35878.333 | E18: =E17*assumptions!$C$33 -> 35878.333 | F18: =F17*assumptions!$C$33 -> 35878.333 | G18: =G17*assumptions!$C$33 -> 35878.333 | H18: =H17*assumptions!$C$33 -> 35878.333 | I18: =I17*assumptions!$C$33 -> 35878.333 | ... M18: =M17*assumptions!$C$33 -> 35878.333 | N18: =SUM(B18:M18) -> 430540
A19: Marketing & Advertising | B19: =B4*assumptions!$C$45 -> 193200 | C19: =C4*assumptions!$C$45 -> 193200 | D19: =D4*assumptions!$C$45 -> 220800 | E19: =E4*assumptions!$C$45 -> 220800 | F19: =F4*assumptions!$C$45 -> 220800 | G19: =G4*assumptions!$C$45 -> 220800 | H19: =H4*assumptions!$C$45 -> 220800 | I19: =I4*assumptions!$C$45 -> 220800 | ... M19: =M4*assumptions!$C$45 -> 303600 | N19: =SUM(B19:M19) -> 2760000
A20: Software & Tools | B20: =(assumptions!$C$17*assumptions!$C$41)/12 -> 5500 | C20: =(assumptions!$C$17*assumptions!$C$41)/12 -> 5500 | D20: =(assumptions!$C$17*assumptions!$C$41)/12 -> 5500 | E20: =(assumptions!$C$17*assumptions!$C$41)/12 -> 5500 | F20: =(assumptions!$C$17*assumptions!$C$41)/12 -> 5500 | G20: =(assumptions!$C$17*assumptions!$C$41)/12 -> 5500 | H20: =(assumptions!$C$17*assumptions!$C$41)/12 -> 5500 | I20: =(assumptions!$C$17*assumptions!$C$41)/12 -> 5500 | ... M20: =(assumptions!$C$17*assumptions!$C$41)/12 -> 5500 | N20: =SUM(B20:M20) -> 66000
A21: Travel & Entertainment | B21: =(assumptions!$C$44*assumptions!$C$17)/12 -> 4583.3333 | C21: =(assumptions!$C$44*assumptions!$C$17)/12 -> 4583.3333 | D21: =(assumptions!$C$44*assumptions!$C$17)/12 -> 4583.3333 | E21: =(assumptions!$C$44*assumptions!$C$17)/12 -> 4583.3333 | F21: =(assumptions!$C$44*assumptions!$C$17)/12 -> 4583.3333 | G21: =(assumptions!$C$44*assumptions!$C$17)/12 -> 4583.3333 | H21: =(assumptions!$C$44*assumptions!$C$17)/12 -> 4583.3333 | I21: =(assumptions!$C$44*assumptions!$C$17)/12 -> 4583.3333 | ... M21: =(assumptions!$C$44*assumptions!$C$17)/12 -> 4583.3333 | N21: =SUM(B21:M21) -> 55000
A22: Total Marketing Expenses | B22: =SUM(B$17:B$21) -> 418553.33 | C22: =SUM(C$17:C$21) -> 418553.33 | D22: =SUM(D$17:D$21) -> 446153.33 | E22: =SUM(E$17:E$21) -> 446153.33 | F22: =SUM(F$17:F$21) -> 446153.33 | G22: =SUM(G$17:G$21) -> 446153.33 | H22: =SUM(H$17:H$21) -> 446153.33 | I22: =SUM(I$17:I$21) -> 446153.33 | ... N22: =SUM(N$17:N$21) -> 5464240
A25: Engineering | B25: Jan | C25: Feb | D25: Mar | E25: Apr | F25: May | G25: Jun | H25: Jul | I25: Aug | J25: Sep | K25: Oct | L25: Nov | M25: Dec | N25: FY 2025
A26: Salaries & Wages | B26: =(assumptions!$C$24*assumptions!$C$14)/12 -> 880650 | C26: =(assumptions!$C$24*assumptions!$C$14)/12 -> 880650 | D26: =(assumptions!$C$24*assumptions!$C$14)/12 -> 880650 | E26: =(assumptions!$C$24*assumptions!$C$14)/12 -> 880650 | F26: =(assumptions!$C$24*assumptions!$C$14)/12 -> 880650 | G26: =(assumptions!$C$24*assumptions!$C$14)/12 -> 880650 | H26: =(assumptions!$C$24*assumptions!$C$14)/12 -> 880650 | I26: =(assumptions!$C$24*assumptions!$C$14)/12 -> 880650 | ... M26: =(assumptions!$C$24*assumptions!$C$14)/12 -> 880650 | N26: =SUM(B26:M26) -> 10567800
A27: Employee Benefits | B27: =assumptions!$C$33*B26 -> 176130 | C27: =assumptions!$C$33*C26 -> 176130 | D27: =assumptions!$C$33*D26 -> 176130 | E27: =assumptions!$C$33*E26 -> 176130 | F27: =assumptions!$C$33*F26 -> 176130 | G27: =assumptions!$C$33*G26 -> 176130 | H27: =assumptions!$C$33*H26 -> 176130 | I27: =assumptions!$C$33*I26 -> 176130 | ... M27: =assumptions!$C$33*M26 -> 176130 | N27: =SUM(B27:M27) -> 2113560
A28: Cloud & Hosting | B28: =assumptions!$C$46*B4 -> 128800 | C28: =assumptions!$C$46*C4 -> 128800 | D28: =assumptions!$C$46*D4 -> 147200 | E28: =assumptions!$C$46*E4 -> 147200 | F28: =assumptions!$C$46*F4 -> 147200 | G28: =assumptions!$C$46*G4 -> 147200 | H28: =assumptions!$C$46*H4 -> 147200 | I28: =assumptions!$C$46*I4 -> 147200 | ... M28: =assumptions!$C$46*M4 -> 202400 | N28: =SUM(B28:M28) -> 1840000
A29: Software & Tools | B29: =(assumptions!$C$14*assumptions!$C$41)/12 -> 19000 | C29: =(assumptions!$C$14*assumptions!$C$41)/12 -> 19000 | D29: =(assumptions!$C$14*assumptions!$C$41)/12 -> 19000 | E29: =(assumptions!$C$14*assumptions!$C$41)/12 -> 19000 | F29: =(assumptions!$C$14*assumptions!$C$41)/12 -> 19000 | G29: =(assumptions!$C$14*assumptions!$C$41)/12 -> 19000 | H29: =(assumptions!$C$14*assumptions!$C$41)/12 -> 19000 | I29: =(assumptions!$C$14*assumptions!$C$41)/12 -> 19000 | ... M29: =(assumptions!$C$14*assumptions!$C$41)/12 -> 19000 | N29: =SUM(B29:M29) -> 228000
A30: Total Engineering Expenses | B30: =SUM(B26:B29) -> 1204580 | C30: =SUM(C26:C29) -> 1204580 | D30: =SUM(D26:D29) -> 1222980 | E30: =SUM(E26:E29) -> 1222980 | F30: =SUM(F26:F29) -> 1222980 | G30: =SUM(G26:G29) -> 1222980 | H30: =SUM(H26:H29) -> 1222980 | I30: =SUM(I26:I29) -> 1222980 | ... N30: =SUM(N26:N29) -> 14749360
A33: Product | B33: Jan | C33: Feb | D33: Mar | E33: Apr | F33: May | G33: Jun | H33: Jul | I33: Aug | J33: Sep | K33: Oct | L33: Nov | M33: Dec | N33: FY 2025
A34: Salaries & Wages | B34: =(assumptions!$C$18*assumptions!$C$28)/12 -> 182395.83 | C34: =(assumptions!$C$18*assumptions!$C$28)/12 -> 182395.83 | D34: =(assumptions!$C$18*assumptions!$C$28)/12 -> 182395.83 | E34: =(assumptions!$C$18*assumptions!$C$28)/12 -> 182395.83 | F34: =(assumptions!$C$18*assumptions!$C$28)/12 -> 182395.83 | G34: =(assumptions!$C$18*assumptions!$C$28)/12 -> 182395.83 | H34: =(assumptions!$C$18*assumptions!$C$28)/12 -> 182395.83 | I34: =(assumptions!$C$18*assumptions!$C$28)/12 -> 182395.83 | ... M34: =(assumptions!$C$18*assumptions!$C$28)/12 -> 182395.83 | N34: =SUM(B34:M34) -> 2188750
A35: Employee Benefits | B35: =B34*assumptions!$C$33 -> 36479.167 | C35: =C34*assumptions!$C$33 -> 36479.167 | D35: =D34*assumptions!$C$33 -> 36479.167 | E35: =E34*assumptions!$C$33 -> 36479.167 | F35: =F34*assumptions!$C$33 -> 36479.167 | G35: =G34*assumptions!$C$33 -> 36479.167 | H35: =H34*assumptions!$C$33 -> 36479.167 | I35: =I34*assumptions!$C$33 -> 36479.167 | ... M35: =M34*assumptions!$C$33 -> 36479.167 | N35: =SUM(B35:M35) -> 437750
A36: Software & Tools | B36: =(assumptions!$C$18*assumptions!$C$41)/12 -> 4250 | C36: =(assumptions!$C$18*assumptions!$C$41)/12 -> 4250 | D36: =(assumptions!$C$18*assumptions!$C$41)/12 -> 4250 | E36: =(assumptions!$C$18*assumptions!$C$41)/12 -> 4250 | F36: =(assumptions!$C$18*assumptions!$C$41)/12 -> 4250 | G36: =(assumptions!$C$18*assumptions!$C$41)/12 -> 4250 | H36: =(assumptions!$C$18*assumptions!$C$41)/12 -> 4250 | I36: =(assumptions!$C$18*assumptions!$C$41)/12 -> 4250 | ... M36: =(assumptions!$C$18*assumptions!$C$41)/12 -> 4250 | N36: =SUM(B36:M36) -> 51000
A37: Professional Services | B37: =assumptions!$C$47/12 -> 25000 | C37: =assumptions!$C$47/12 -> 25000 | D37: =assumptions!$C$47/12 -> 25000 | E37: =assumptions!$C$47/12 -> 25000 | F37: =assumptions!$C$47/12 -> 25000 | G37: =assumptions!$C$47/12 -> 25000 | H37: =assumptions!$C$47/12 -> 25000 | I37: =assumptions!$C$47/12 -> 25000 | ... M37: =assumptions!$C$47/12 -> 25000 | N37: =SUM(B37:M37) -> 300000
A38: Total Product Expenses | B38: =SUM(B34:B37) -> 248125 | C38: =SUM(C34:C37) -> 248125 | D38: =SUM(D34:D37) -> 248125 | E38: =SUM(E34:E37) -> 248125 | F38: =SUM(F34:F37) -> 248125 | G38: =SUM(G34:G37) -> 248125 | H38: =SUM(H34:H37) -> 248125 | I38: =SUM(I34:I37) -> 248125 | ... N38: =SUM(N34:N37) -> 2977500
A41: Customer Success | B41: Jan | C41: Feb | D41: Mar | E41: Apr | F41: May | G41: Jun | H41: Jul | I41: Aug | J41: Sep | K41: Oct | L41: Nov | M41: Dec | N41: FY 2025
A42: Salaries & Wages | B42: =(assumptions!$C$26*assumptions!$C$16)/12 -> 240762.5 | C42: =(assumptions!$C$26*assumptions!$C$16)/12 -> 240762.5 | D42: =(assumptions!$C$26*assumptions!$C$16)/12 -> 240762.5 | E42: =(assumptions!$C$26*assumptions!$C$16)/12 -> 240762.5 | F42: =(assumptions!$C$26*assumptions!$C$16)/12 -> 240762.5 | G42: =(assumptions!$C$26*assumptions!$C$16)/12 -> 240762.5 | H42: =(assumptions!$C$26*assumptions!$C$16)/12 -> 240762.5 | I42: =(assumptions!$C$26*assumptions!$C$16)/12 -> 240762.5 | ... M42: =(assumptions!$C$26*assumptions!$C$16)/12 -> 240762.5 | N42: =SUM(B42:M42) -> 2889150
A43: Employee Benefits | B43: =B42*assumptions!$C$33 -> 48152.5 | C43: =C42*assumptions!$C$33 -> 48152.5 | D43: =D42*assumptions!$C$33 -> 48152.5 | E43: =E42*assumptions!$C$33 -> 48152.5 | F43: =F42*assumptions!$C$33 -> 48152.5 | G43: =G42*assumptions!$C$33 -> 48152.5 | H43: =H42*assumptions!$C$33 -> 48152.5 | I43: =I42*assumptions!$C$33 -> 48152.5 | ... M43: =M42*assumptions!$C$33 -> 48152.5 | N43: =SUM(B43:M43) -> 577830
A44: Software & Tools | B44: =(assumptions!$C$16*assumptions!$C$41)/12 -> 8250 | C44: =(assumptions!$C$16*assumptions!$C$41)/12 -> 8250 | D44: =(assumptions!$C$16*assumptions!$C$41)/12 -> 8250 | E44: =(assumptions!$C$16*assumptions!$C$41)/12 -> 8250 | F44: =(assumptions!$C$16*assumptions!$C$41)/12 -> 8250 | G44: =(assumptions!$C$16*assumptions!$C$41)/12 -> 8250 | H44: =(assumptions!$C$16*assumptions!$C$41)/12 -> 8250 | I44: =(assumptions!$C$16*assumptions!$C$41)/12 -> 8250 | ... M44: =(assumptions!$C$16*assumptions!$C$41)/12 -> 8250 | N44: =SUM(B44:M44) -> 99000
A45: Travel & Entertainment | B45: =(assumptions!$C$43*assumptions!$C$16)/12 -> 5500 | C45: =(assumptions!$C$43*assumptions!$C$16)/12 -> 5500 | D45: =(assumptions!$C$43*assumptions!$C$16)/12 -> 5500 | E45: =(assumptions!$C$43*assumptions!$C$16)/12 -> 5500 | F45: =(assumptions!$C$43*assumptions!$C$16)/12 -> 5500 | G45: =(assumptions!$C$43*assumptions!$C$16)/12 -> 5500 | H45: =(assumptions!$C$43*assumptions!$C$16)/12 -> 5500 | I45: =(assumptions!$C$43*assumptions!$C$16)/12 -> 5500 | ... M45: =(assumptions!$C$43*assumptions!$C$16)/12 -> 5500 | N45: =SUM(B45:M45) -> 66000
A46: Total Customer Success Expenses | B46: =SUM(B42:B45) -> 302665 | C46: =SUM(C42:C45) -> 302665 | D46: =SUM(D42:D45) -> 302665 | E46: =SUM(E42:E45) -> 302665 | F46: =SUM(F42:F45) -> 302665 | G46: =SUM(G42:G45) -> 302665 | H46: =SUM(H42:H45) -> 302665 | I46: =SUM(I42:I45) -> 302665 | ... M46: =SUM(M42:M45) -> 302665 | N46: =SUM(B46:M46) -> 3631980
A49: G&A | B49: Jan | C49: Feb | D49: Mar | E49: Apr | F49: May | G49: Jun | H49: Jul | I49: Aug | J49: Sep | K49: Oct | L49: Nov | M49: Dec | N49: FY 2025
A50: Salaries & Wages | B50: =(assumptions!$C$19*assumptions!$C$29)/12 -> 234325 | C50: =(assumptions!$C$19*assumptions!$C$29)/12 -> 234325 | D50: =(assumptions!$C$19*assumptions!$C$29)/12 -> 234325 | E50: =(assumptions!$C$19*assumptions!$C$29)/12 -> 234325 | F50: =(assumptions!$C$19*assumptions!$C$29)/12 -> 234325 | G50: =(assumptions!$C$19*assumptions!$C$29)/12 -> 234325 | H50: =(assumptions!$C$19*assumptions!$C$29)/12 -> 234325 | I50: =(assumptions!$C$19*assumptions!$C$29)/12 -> 234325 | ... M50: =(assumptions!$C$19*assumptions!$C$29)/12 -> 234325 | N50: =SUM(B50:M50) -> 2811900
A51: Employee Benefits | B51: =B50*assumptions!$C$33 -> 46865 | C51: =C50*assumptions!$C$33 -> 46865 | D51: =D50*assumptions!$C$33 -> 46865 | E51: =E50*assumptions!$C$33 -> 46865 | F51: =F50*assumptions!$C$33 -> 46865 | G51: =G50*assumptions!$C$33 -> 46865 | H51: =H50*assumptions!$C$33 -> 46865 | I51: =I50*assumptions!$C$33 -> 46865 | ... M51: =M50*assumptions!$C$33 -> 46865 | N51: =SUM(B51:M51) -> 562380
A52: Software & Tools | B52: =(assumptions!$C$19*assumptions!$C$41)/12 -> 6500 | C52: =(assumptions!$C$19*assumptions!$C$41)/12 -> 6500 | D52: =(assumptions!$C$19*assumptions!$C$41)/12 -> 6500 | E52: =(assumptions!$C$19*assumptions!$C$41)/12 -> 6500 | F52: =(assumptions!$C$19*assumptions!$C$41)/12 -> 6500 | G52: =(assumptions!$C$19*assumptions!$C$41)/12 -> 6500 | H52: =(assumptions!$C$19*assumptions!$C$41)/12 -> 6500 | I52: =(assumptions!$C$19*assumptions!$C$41)/12 -> 6500 | ... M52: =(assumptions!$C$19*assumptions!$C$41)/12 -> 6500 | N52: =SUM(B52:M52) -> 78000
A53: Consulting & Professional Fees | B53: =assumptions!$C$48/12 -> 35416.667 | C53: =assumptions!$C$48/12 -> 35416.667 | D53: =assumptions!$C$48/12 -> 35416.667 | E53: =assumptions!$C$48/12 -> 35416.667 | F53: =assumptions!$C$48/12 -> 35416.667 | G53: =assumptions!$C$48/12 -> 35416.667 | H53: =assumptions!$C$48/12 -> 35416.667 | I53: =assumptions!$C$48/12 -> 35416.667 | ... M53: =assumptions!$C$48/12 -> 35416.667 | N53: =SUM(B53:M53) -> 425000
A54: Rent & Facilities | B54: =(assumptions!$C$49*assumptions!$C$19)/12 -> 13000 | C54: =(assumptions!$C$49*assumptions!$C$19)/12 -> 13000 | D54: =(assumptions!$C$49*assumptions!$C$19)/12 -> 13000 | E54: =(assumptions!$C$49*assumptions!$C$19)/12 -> 13000 | F54: =(assumptions!$C$49*assumptions!$C$19)/12 -> 13000 | G54: =(assumptions!$C$49*assumptions!$C$19)/12 -> 13000 | H54: =(assumptions!$C$49*assumptions!$C$19)/12 -> 13000 | I54: =(assumptions!$C$49*assumptions!$C$19)/12 -> 13000 | ... M54: =(assumptions!$C$49*assumptions!$C$19)/12 -> 13000 | N54: =SUM(B54:M54) -> 156000
A55: Total G&A Expenses | B55: =SUM(B50:B54) -> 336106.67 | C55: =SUM(C50:C54) -> 336106.67 | D55: =SUM(D50:D54) -> 336106.67 | E55: =SUM(E50:E54) -> 336106.67 | F55: =SUM(F50:F54) -> 336106.67 | G55: =SUM(G50:G54) -> 336106.67 | H55: =SUM(H50:H54) -> 336106.67 | I55: =SUM(I50:I54) -> 336106.67 | ... M55: =SUM(M50:M54) -> 336106.67 | N55: =SUM(B55:M55) -> 4033280
A58: 2025 Budget Summary | B58: Jan | C58: Feb | D58: Mar | E58: Apr | F58: May | G58: Jun | H58: Jul | I58: Aug | J58: Sep | K58: Oct | L58: Nov | M58: Dec | N58: FY 2025
A59: Total Revenue | B59: =B4 -> 3220000 | C59: =C4 -> 3220000 | D59: =D4 -> 3680000 | E59: =E4 -> 3680000 | F59: =F4 -> 3680000 | G59: =G4 -> 3680000 | H59: =H4 -> 3680000 | I59: =I4 -> 3680000 | ... M59: =M4 -> 5060000 | N59: =SUM(B59:M59) -> 46000000
A61: Sales Expenses | B61: =B13 -> 743483.33 | C61: =C13 -> 743483.33 | D61: =D13 -> 764183.33 | E61: =E13 -> 764183.33 | F61: =F13 -> 764183.33 | G61: =G13 -> 764183.33 | H61: =H13 -> 764183.33 | I61: =I13 -> 764183.33 | ... M61: =M13 -> 826283.33 | N61: =SUM(B61:M61) -> 9253000
A62: Marketing Expenses | B62: =B22 -> 418553.33 | C62: =C22 -> 418553.33 | D62: =D22 -> 446153.33 | E62: =E22 -> 446153.33 | F62: =F22 -> 446153.33 | G62: =G22 -> 446153.33 | H62: =H22 -> 446153.33 | I62: =I22 -> 446153.33 | ... M62: =M22 -> 528953.33 | N62: =SUM(B62:M62) -> 5464240
A63: Engineering Expenses | B63: =B30 -> 1204580 | C63: =C30 -> 1204580 | D63: =D30 -> 1222980 | E63: =E30 -> 1222980 | F63: =F30 -> 1222980 | G63: =G30 -> 1222980 | H63: =H30 -> 1222980 | I63: =I30 -> 1222980 | ... M63: =M30 -> 1278180 | N63: =SUM(B63:M63) -> 14749360
A64: Product Expenses | B64: =B38 -> 248125 | C64: =C38 -> 248125 | D64: =D38 -> 248125 | E64: =E38 -> 248125 | F64: =F38 -> 248125 | G64: =G38 -> 248125 | H64: =H38 -> 248125 | I64: =I38 -> 248125 | ... M64: =M38 -> 248125 | N64: =SUM(B64:M64) -> 2977500
A65: Customer Success Expenses | B65: =B46 -> 302665 | C65: =C46 -> 302665 | D65: =D46 -> 302665 | E65: =E46 -> 302665 | F65: =F46 -> 302665 | G65: =G46 -> 302665 | H65: =H46 -> 302665 | I65: =I46 -> 302665 | ... M65: =M46 -> 302665 | N65: =SUM(B65:M65) -> 3631980
A66: G&A Expenses | B66: =B55 -> 336106.67 | C66: =C55 -> 336106.67 | D66: =D55 -> 336106.67 | E66: =E55 -> 336106.67 | F66: =F55 -> 336106.67 | G66: =G55 -> 336106.67 | H66: =H55 -> 336106.67 | I66: =I55 -> 336106.67 | ... M66: =M55 -> 336106.67 | N66: =SUM(B66:M66) -> 4033280
A67: Total Operating Expenses | B67: =SUM(B61:B66) -> 3253513.3 | C67: =SUM(C61:C66) -> 3253513.3 | D67: =SUM(D61:D66) -> 3320213.3 | E67: =SUM(E61:E66) -> 3320213.3 | F67: =SUM(F61:F66) -> 3320213.3 | G67: =SUM(G61:G66) -> 3320213.3 | H67: =SUM(H61:H66) -> 3320213.3 | I67: =SUM(I61:I66) -> 3320213.3 | ... M67: =SUM(M61:M66) -> 3520313.3 | N67: =SUM(B67:M67) -> 40109360
A69: Operating Profit | B69: =B59-B67 -> -33513.333 | C69: =C59-C67 -> -33513.333 | D69: =D59-D67 -> 359786.67 | E69: =E59-E67 -> 359786.67 | F69: =F59-F67 -> 359786.67 | G69: =G59-G67 -> 359786.67 | H69: =H59-H67 -> 359786.67 | I69: =I59-I67 -> 359786.67 | ... N69: =N59-N67 -> 5890640
A70: Operating Margin | B70: =B69/B59 -> -0.010407867 | C70: =C69/C59 -> -0.010407867 | D70: =D69/D59 -> 0.097768116 | E70: =E69/E59 -> 0.097768116 | F70: =F69/F59 -> 0.097768116 | G70: =G69/G59 -> 0.097768116 | H70: =H69/H59 -> 0.097768116 | I70: =I69/I59 -> 0.097768116 | ... N70: =N69/N59 -> 0.12805739

Sheet 2026_budget
A1: Revenue | B1: Jan | C1: Feb | D1: Mar | E1: Apr | F1: May | G1: Jun | H1: Jul | I1: Aug | J1: Sep | K1: Oct | L1: Nov | M1: Dec | N1: FY 2026
A2: Subscription Revenue | B2: =assumptions!$D$7*assumptions!B53 -> 3332700 | C2: =assumptions!$D$7*assumptions!C53 -> 3332700 | D2: =assumptions!$D$7*assumptions!D53 -> 3808800 | E2: =assumptions!$D$7*assumptions!E53 -> 3808800 | F2: =assumptions!$D$7*assumptions!F53 -> 3808800 | G2: =assumptions!$D$7*assumptions!G53 -> 3808800 | H2: =assumptions!$D$7*assumptions!H53 -> 3808800 | I2: =assumptions!$D$7*assumptions!I53 -> 3808800 | ... M2: =assumptions!$D$7*assumptions!M53 -> 5237100 | N2: =SUM(B2:M2) -> 47610000
A3: Professional Services | B3: =assumptions!$D$8*assumptions!B53 -> 370300 | C3: =assumptions!$D$8*assumptions!C53 -> 370300 | D3: =assumptions!$D$8*assumptions!D53 -> 423200 | E3: =assumptions!$D$8*assumptions!E53 -> 423200 | F3: =assumptions!$D$8*assumptions!F53 -> 423200 | G3: =assumptions!$D$8*assumptions!G53 -> 423200 | H3: =assumptions!$D$8*assumptions!H53 -> 423200 | I3: =assumptions!$D$8*assumptions!I53 -> 423200 | ... M3: =assumptions!$D$8*assumptions!M53 -> 581900 | N3: =SUM(B3:M3) -> 5290000
A4: Total Revenue | B4: =SUM(B2:B3) -> 3703000 | C4: =SUM(C2:C3) -> 3703000 | D4: =SUM(D2:D3) -> 4232000 | E4: =SUM(E2:E3) -> 4232000 | F4: =SUM(F2:F3) -> 4232000 | G4: =SUM(G2:G3) -> 4232000 | H4: =SUM(H2:H3) -> 4232000 | I4: =SUM(I2:I3) -> 4232000 | ... N4: =SUM(N2:N3) -> 52900000
A7: Sales | B7: Jan | C7: Feb | D7: Mar | E7: Apr | F7: May | G7: Jun | H7: Jul | I7: Aug | J7: Sep | K7: Oct | L7: Nov | M7: Dec | N7: FY 2026
A8: Salaries & Wages | B8: =assumptions!$D$15*assumptions!$D$25/12 -> 530450 | C8: =assumptions!$D$15*assumptions!$D$25/12 -> 530450 | D8: =assumptions!$D$15*assumptions!$D$25/12 -> 530450 | E8: =assumptions!$D$15*assumptions!$D$25/12 -> 530450 | F8: =assumptions!$D$15*assumptions!$D$25/12 -> 530450 | G8: =assumptions!$D$15*assumptions!$D$25/12 -> 530450 | H8: =assumptions!$D$15*assumptions!$D$25/12 -> 530450 | I8: =assumptions!$D$15*assumptions!$D$25/12 -> 530450 | ... M8: =assumptions!$D$15*assumptions!$D$25/12 -> 530450 | N8: =SUM(B8:M8) -> 6365400
A9: Employee Benefits | B9: =$B$8*assumptions!$D$33 -> 106090 | C9: =$B$8*assumptions!$D$33 -> 106090 | D9: =$B$8*assumptions!$D$33 -> 106090 | E9: =$B$8*assumptions!$D$33 -> 106090 | F9: =$B$8*assumptions!$D$33 -> 106090 | G9: =$B$8*assumptions!$D$33 -> 106090 | H9: =$B$8*assumptions!$D$33 -> 106090 | I9: =$B$8*assumptions!$D$33 -> 106090 | ... M9: =$B$8*assumptions!$D$33 -> 106090 | N9: =SUM(B9:M9) -> 1273080
A10: Sales Commissions | B10: =B2*assumptions!$D$40 -> 166635 | C10: =C2*assumptions!$D$40 -> 166635 | D10: =D2*assumptions!$D$40 -> 190440 | E10: =E2*assumptions!$D$40 -> 190440 | F10: =F2*assumptions!$D$40 -> 190440 | G10: =G2*assumptions!$D$40 -> 190440 | H10: =H2*assumptions!$D$40 -> 190440 | I10: =I2*assumptions!$D$40 -> 190440 | ... M10: =M2*assumptions!$D$40 -> 261855 | N10: =SUM(B10:M10) -> 2380500
A11: Software & Tools | B11: =(assumptions!$D$15*assumptions!$D$41)/12 -> 15000 | C11: =(assumptions!$D$15*assumptions!$D$41)/12 -> 15000 | D11: =(assumptions!$D$15*assumptions!$D$41)/12 -> 15000 | E11: =(assumptions!$D$15*assumptions!$D$41)/12 -> 15000 | F11: =(assumptions!$D$15*assumptions!$D$41)/12 -> 15000 | G11: =(assumptions!$D$15*assumptions!$D$41)/12 -> 15000 | H11: =(assumptions!$D$15*assumptions!$D$41)/12 -> 15000 | I11: =(assumptions!$D$15*assumptions!$D$41)/12 -> 15000 | ... M11: =(assumptions!$D$15*assumptions!$D$41)/12 -> 15000 | N11: =SUM(B11:M11) -> 180000
A12: Travel & Entertainment | B12: =(assumptions!$D$15*assumptions!$D$42)/12 -> 20000 | C12: =(assumptions!$D$15*assumptions!$D$42)/12 -> 20000 | D12: =(assumptions!$D$15*assumptions!$D$42)/12 -> 20000 | E12: =(assumptions!$D$15*assumptions!$D$42)/12 -> 20000 | F12: =(assumptions!$D$15*assumptions!$D$42)/12 -> 20000 | G12: =(assumptions!$D$15*assumptions!$D$42)/12 -> 20000 | H12: =(assumptions!$D$15*assumptions!$D$42)/12 -> 20000 | I12: =(assumptions!$D$15*assumptions!$D$42)/12 -> 20000 | ... M12: =(assumptions!$D$15*assumptions!$D$42)/12 -> 20000 | N12: =SUM(B12:M12) -> 240000
A13: Total Sales Expenses | B13: =SUM(B8:B12) -> 838175 | C13: =SUM(C8:C12) -> 838175 | D13: =SUM(D8:D12) -> 861980 | E13: =SUM(E8:E12) -> 861980 | F13: =SUM(F8:F12) -> 861980 | G13: =SUM(G8:G12) -> 861980 | H13: =SUM(H8:H12) -> 861980 | I13: =SUM(I8:I12) -> 861980 | ... N13: =SUM(N8:N12) -> 10438980
A16: Marketing | B16: Jan | C16: Feb | D16: Mar | E16: Apr | F16: May | G16: Jun | H16: Jul | I16: Aug | J16: Sep | K16: Oct | L16: Nov | M16: Dec | N16: FY 2026
A17: Salaries & Wages | B17: =(assumptions!$D$27*assumptions!$D$17)/12 -> 201571 | C17: =(assumptions!$D$27*assumptions!$D$17)/12 -> 201571 | D17: =(assumptions!$D$27*assumptions!$D$17)/12 -> 201571 | E17: =(assumptions!$D$27*assumptions!$D$17)/12 -> 201571 | F17: =(assumptions!$D$27*assumptions!$D$17)/12 -> 201571 | G17: =(assumptions!$D$27*assumptions!$D$17)/12 -> 201571 | H17: =(assumptions!$D$27*assumptions!$D$17)/12 -> 201571 | I17: =(assumptions!$D$27*assumptions!$D$17)/12 -> 201571 | ... M17: =(assumptions!$D$27*assumptions!$D$17)/12 -> 201571 | N17: =SUM(B17:M17) -> 2418852
A18: Employee Benefits | B18: =B17*assumptions!$D$33 -> 40314.2 | C18: =C17*assumptions!$D$33 -> 40314.2 | D18: =D17*assumptions!$D$33 -> 40314.2 | E18: =E17*assumptions!$D$33 -> 40314.2 | F18: =F17*assumptions!$D$33 -> 40314.2 | G18: =G17*assumptions!$D$33 -> 40314.2 | H18: =H17*assumptions!$D$33 -> 40314.2 | I18: =I17*assumptions!$D$33 -> 40314.2 | ... M18: =M17*assumptions!$D$33 -> 40314.2 | N18: =SUM(B18:M18) -> 483770.4
A19: Marketing & Advertising | B19: =B4*assumptions!$D$45 -> 222180 | C19: =C4*assumptions!$D$45 -> 222180 | D19: =D4*assumptions!$D$45 -> 253920 | E19: =E4*assumptions!$D$45 -> 253920 | F19: =F4*assumptions!$D$45 -> 253920 | G19: =G4*assumptions!$D$45 -> 253920 | H19: =H4*assumptions!$D$45 -> 253920 | I19: =I4*assumptions!$D$45 -> 253920 | ... M19: =M4*assumptions!$D$45 -> 349140 | N19: =SUM(B19:M19) -> 3174000
A20: Software & Tools | B20: =(assumptions!$D$17*assumptions!$D$41)/12 -> 6000 | C20: =(assumptions!$D$17*assumptions!$D$41)/12 -> 6000 | D20: =(assumptions!$D$17*assumptions!$D$41)/12 -> 6000 | E20: =(assumptions!$D$17*assumptions!$D$41)/12 -> 6000 | F20: =(assumptions!$D$17*assumptions!$D$41)/12 -> 6000 | G20: =(assumptions!$D$17*assumptions!$D$41)/12 -> 6000 | H20: =(assumptions!$D$17*assumptions!$D$41)/12 -> 6000 | I20: =(assumptions!$D$17*assumptions!$D$41)/12 -> 6000 | ... M20: =(assumptions!$D$17*assumptions!$D$41)/12 -> 6000 | N20: =SUM(B20:M20) -> 72000
A21: Travel & Entertainment | B21: =(assumptions!$D$44*assumptions!$D$17)/12 -> 5000 | C21: =(assumptions!$D$44*assumptions!$D$17)/12 -> 5000 | D21: =(assumptions!$D$44*assumptions!$D$17)/12 -> 5000 | E21: =(assumptions!$D$44*assumptions!$D$17)/12 -> 5000 | F21: =(assumptions!$D$44*assumptions!$D$17)/12 -> 5000 | G21: =(assumptions!$D$44*assumptions!$D$17)/12 -> 5000 | H21: =(assumptions!$D$44*assumptions!$D$17)/12 -> 5000 | I21: =(assumptions!$D$44*assumptions!$D$17)/12 -> 5000 | ... M21: =(assumptions!$D$44*assumptions!$D$17)/12 -> 5000 | N21: =SUM(B21:M21) -> 60000
A22: Total Marketing Expenses | B22: =SUM(B$17:B$21) -> 475065.2 | C22: =SUM(C$17:C$21) -> 475065.2 | D22: =SUM(D$17:D$21) -> 506805.2 | E22: =SUM(E$17:E$21) -> 506805.2 | F22: =SUM(F$17:F$21) -> 506805.2 | G22: =SUM(G$17:G$21) -> 506805.2 | H22: =SUM(H$17:H$21) -> 506805.2 | I22: =SUM(I$17:I$21) -> 506805.2 | ... N22: =SUM(N$17:N$21) -> 6208622.4
A25: Engineering | B25: Jan | C25: Feb | D25: Mar | E25: Apr | F25: May | G25: Jun | H25: Jul | I25: Aug | J25: Sep | K25: Oct | L25: Nov | M25: Dec | N25: FY 2026
A26: Salaries & Wages | B26: =(assumptions!$D$24*assumptions!$D$14)/12 -> 978680.25 | C26: =(assumptions!$D$24*assumptions!$D$14)/12 -> 978680.25 | D26: =(assumptions!$D$24*assumptions!$D$14)/12 -> 978680.25 | E26: =(assumptions!$D$24*assumptions!$D$14)/12 -> 978680.25 | F26: =(assumptions!$D$24*assumptions!$D$14)/12 -> 978680.25 | G26: =(assumptions!$D$24*assumptions!$D$14)/12 -> 978680.25 | H26: =(assumptions!$D$24*assumptions!$D$14)/12 -> 978680.25 | I26: =(assumptions!$D$24*assumptions!$D$14)/12 -> 978680.25 | ... M26: =(assumptions!$D$24*assumptions!$D$14)/12 -> 978680.25 | N26: =SUM(B26:M26) -> 11744163
A27: Employee Benefits | B27: =assumptions!$D$33*B26 -> 195736.05 | C27: =assumptions!$D$33*C26 -> 195736.05 | D27: =assumptions!$D$33*D26 -> 195736.05 | E27: =assumptions!$D$33*E26 -> 195736.05 | F27: =assumptions!$D$33*F26 -> 195736.05 | G27: =assumptions!$D$33*G26 -> 195736.05 | H27: =assumptions!$D$33*H26 -> 195736.05 | I27: =assumptions!$D$33*I26 -> 195736.05 | ... M27: =assumptions!$D$33*M26 -> 195736.05 | N27: =SUM(B27:M27) -> 2348832.6
A28: Cloud & Hosting | B28: =assumptions!$D$46*B4 -> 148120 | C28: =assumptions!$D$46*C4 -> 148120 | D28: =assumptions!$D$46*D4 -> 169280 | E28: =assumptions!$D$46*E4 -> 169280 | F28: =assumptions!$D$46*F4 -> 169280 | G28: =assumptions!$D$46*G4 -> 169280 | H28: =assumptions!$D$46*H4 -> 169280 | I28: =assumptions!$D$46*I4 -> 169280 | ... M28: =assumptions!$D$46*M4 -> 232760 | N28: =SUM(B28:M28) -> 2116000
A29: Software & Tools | B29: =(assumptions!$D$14*assumptions!$D$41)/12 -> 20500 | C29: =(assumptions!$D$14*assumptions!$D$41)/12 -> 20500 | D29: =(assumptions!$D$14*assumptions!$D$41)/12 -> 20500 | E29: =(assumptions!$D$14*assumptions!$D$41)/12 -> 20500 | F29: =(assumptions!$D$14*assumptions!$D$41)/12 -> 20500 | G29: =(assumptions!$D$14*assumptions!$D$41)/12 -> 20500 | H29: =(assumptions!$D$14*assumptions!$D$41)/12 -> 20500 | I29: =(assumptions!$D$14*assumptions!$D$41)/12 -> 20500 | ... M29: =(assumptions!$D$14*assumptions!$D$41)/12 -> 20500 | N29: =SUM(B29:M29) -> 246000
A30: Total Engineering Expenses | B30: =SUM(B26:B29) -> 1343036.3 | C30: =SUM(C26:C29) -> 1343036.3 | D30: =SUM(D26:D29) -> 1364196.3 | E30: =SUM(E26:E29) -> 1364196.3 | F30: =SUM(F26:F29) -> 1364196.3 | G30: =SUM(G26:G29) -> 1364196.3 | H30: =SUM(H26:H29) -> 1364196.3 | I30: =SUM(I26:I29) -> 1364196.3 | ... N30: =SUM(N26:N29) -> 16454996
A33: Product | B33: Jan | C33: Feb | D33: Mar | E33: Apr | F33: May | G33: Jun | H33: Jul | I33: Aug | J33: Sep | K33: Oct | L33: Nov | M33: Dec | N33: FY 2026
A34: Salaries & Wages | B34: =(assumptions!$D$18*assumptions!$D$28)/12 -> 209969.79 | C34: =(assumptions!$D$18*assumptions!$D$28)/12 -> 209969.79 | D34: =(assumptions!$D$18*assumptions!$D$28)/12 -> 209969.79 | E34: =(assumptions!$D$18*assumptions!$D$28)/12 -> 209969.79 | F34: =(assumptions!$D$18*assumptions!$D$28)/12 -> 209969.79 | G34: =(assumptions!$D$18*assumptions!$D$28)/12 -> 209969.79 | H34: =(assumptions!$D$18*assumptions!$D$28)/12 -> 209969.79 | I34: =(assumptions!$D$18*assumptions!$D$28)/12 -> 209969.79 | ... M34: =(assumptions!$D$18*assumptions!$D$28)/12 -> 209969.79 | N34: =SUM(B34:M34) -> 2519637.5
A35: Employee Benefits | B35: =B34*assumptions!$D$33 -> 41993.958 | C35: =C34*assumptions!$D$33 -> 41993.958 | D35: =D34*assumptions!$D$33 -> 41993.958 | E35: =E34*assumptions!$D$33 -> 41993.958 | F35: =F34*assumptions!$D$33 -> 41993.958 | G35: =G34*assumptions!$D$33 -> 41993.958 | H35: =H34*assumptions!$D$33 -> 41993.958 | I35: =I34*assumptions!$D$33 -> 41993.958 | ... M35: =M34*assumptions!$D$33 -> 41993.958 | N35: =SUM(B35:M35) -> 503927.5
A36: Software & Tools | B36: =(assumptions!$D$18*assumptions!$D$41)/12 -> 4750 | C36: =(assumptions!$D$18*assumptions!$D$41)/12 -> 4750 | D36: =(assumptions!$D$18*assumptions!$D$41)/12 -> 4750 | E36: =(assumptions!$D$18*assumptions!$D$41)/12 -> 4750 | F36: =(assumptions!$D$18*assumptions!$D$41)/12 -> 4750 | G36: =(assumptions!$D$18*assumptions!$D$41)/12 -> 4750 | H36: =(assumptions!$D$18*assumptions!$D$41)/12 -> 4750 | I36: =(assumptions!$D$18*assumptions!$D$41)/12 -> 4750 | ... M36: =(assumptions!$D$18*assumptions!$D$41)/12 -> 4750 | N36: =SUM(B36:M36) -> 57000
A37: Professional Services | B37: =assumptions!$D$47/12 -> 27083.333 | C37: =assumptions!$D$47/12 -> 27083.333 | D37: =assumptions!$D$47/12 -> 27083.333 | E37: =assumptions!$D$47/12 -> 27083.333 | F37: =assumptions!$D$47/12 -> 27083.333 | G37: =assumptions!$D$47/12 -> 27083.333 | H37: =assumptions!$D$47/12 -> 27083.333 | I37: =assumptions!$D$47/12 -> 27083.333 | ... M37: =assumptions!$D$47/12 -> 27083.333 | N37: =SUM(B37:M37) -> 325000
A38: Total Product Expenses | B38: =SUM(B34:B37) -> 283797.08 | C38: =SUM(C34:C37) -> 283797.08 | D38: =SUM(D34:D37) -> 283797.08 | E38: =SUM(E34:E37) -> 283797.08 | F38: =SUM(F34:F37) -> 283797.08 | G38: =SUM(G34:G37) -> 283797.08 | H38: =SUM(H34:H37) -> 283797.08 | I38: =SUM(I34:I37) -> 283797.08 | ... N38: =SUM(N34:N37) -> 3405565
A41: Customer Success | B41: Jan | C41: Feb | D41: Mar | E41: Apr | F41: May | G41: Jun | H41: Jul | I41: Aug | J41: Sep | K41: Oct | L41: Nov | M41: Dec | N41: FY 2026
A42: Salaries & Wages | B42: =(assumptions!$D$26*assumptions!$D$16)/12 -> 270529.5 | C42: =(assumptions!$D$26*assumptions!$D$16)/12 -> 270529.5 | D42: =(assumptions!$D$26*assumptions!$D$16)/12 -> 270529.5 | E42: =(assumptions!$D$26*assumptions!$D$16)/12 -> 270529.5 | F42: =(assumptions!$D$26*assumptions!$D$16)/12 -> 270529.5 | G42: =(assumptions!$D$26*assumptions!$D$16)/12 -> 270529.5 | H42: =(assumptions!$D$26*assumptions!$D$16)/12 -> 270529.5 | I42: =(assumptions!$D$26*assumptions!$D$16)/12 -> 270529.5 | ... M42: =(assumptions!$D$26*assumptions!$D$16)/12 -> 270529.5 | N42: =SUM(B42:M42) -> 3246354
A43: Employee Benefits | B43: =B42*assumptions!$D$33 -> 54105.9 | C43: =C42*assumptions!$D$33 -> 54105.9 | D43: =D42*assumptions!$D$33 -> 54105.9 | E43: =E42*assumptions!$D$33 -> 54105.9 | F43: =F42*assumptions!$D$33 -> 54105.9 | G43: =G42*assumptions!$D$33 -> 54105.9 | H43: =H42*assumptions!$D$33 -> 54105.9 | I43: =I42*assumptions!$D$33 -> 54105.9 | ... M43: =M42*assumptions!$D$33 -> 54105.9 | N43: =SUM(B43:M43) -> 649270.8
A44: Software & Tools | B44: =(assumptions!$D$16*assumptions!$D$41)/12 -> 9000 | C44: =(assumptions!$D$16*assumptions!$D$41)/12 -> 9000 | D44: =(assumptions!$D$16*assumptions!$D$41)/12 -> 9000 | E44: =(assumptions!$D$16*assumptions!$D$41)/12 -> 9000 | F44: =(assumptions!$D$16*assumptions!$D$41)/12 -> 9000 | G44: =(assumptions!$D$16*assumptions!$D$41)/12 -> 9000 | H44: =(assumptions!$D$16*assumptions!$D$41)/12 -> 9000 | I44: =(assumptions!$D$16*assumptions!$D$41)/12 -> 9000 | ... M44: =(assumptions!$D$16*assumptions!$D$41)/12 -> 9000 | N44: =SUM(B44:M44) -> 108000
A45: Travel & Entertainment | B45: =(assumptions!$D$43*assumptions!$D$16)/12 -> 6000 | C45: =(assumptions!$D$43*assumptions!$D$16)/12 -> 6000 | D45: =(assumptions!$D$43*assumptions!$D$16)/12 -> 6000 | E45: =(assumptions!$D$43*assumptions!$D$16)/12 -> 6000 | F45: =(assumptions!$D$43*assumptions!$D$16)/12 -> 6000 | G45: =(assumptions!$D$43*assumptions!$D$16)/12 -> 6000 | H45: =(assumptions!$D$43*assumptions!$D$16)/12 -> 6000 | I45: =(assumptions!$D$43*assumptions!$D$16)/12 -> 6000 | ... M45: =(assumptions!$D$43*assumptions!$D$16)/12 -> 6000 | N45: =SUM(B45:M45) -> 72000
A46: Total Customer Success Expenses | B46: =SUM(B42:B45) -> 339635.4 | C46: =SUM(C42:C45) -> 339635.4 | D46: =SUM(D42:D45) -> 339635.4 | E46: =SUM(E42:E45) -> 339635.4 | F46: =SUM(F42:F45) -> 339635.4 | G46: =SUM(G42:G45) -> 339635.4 | H46: =SUM(H42:H45) -> 339635.4 | I46: =SUM(I42:I45) -> 339635.4 | ... M46: =SUM(M42:M45) -> 339635.4 | N46: =SUM(B46:M46) -> 4075624.8
A49: G&A | B49: Jan | C49: Feb | D49: Mar | E49: Apr | F49: May | G49: Jun | H49: Jul | I49: Aug | J49: Sep | K49: Oct | L49: Nov | M49: Dec | N49: FY 2026
A50: Salaries & Wages | B50: =(assumptions!$D$19*assumptions!$D$29)/12 -> 250637.62 | C50: =(assumptions!$D$19*assumptions!$D$29)/12 -> 250637.62 | D50: =(assumptions!$D$19*assumptions!$D$29)/12 -> 250637.62 | E50: =(assumptions!$D$19*assumptions!$D$29)/12 -> 250637.62 | F50: =(assumptions!$D$19*assumptions!$D$29)/12 -> 250637.62 | G50: =(assumptions!$D$19*assumptions!$D$29)/12 -> 250637.62 | H50: =(assumptions!$D$19*assumptions!$D$29)/12 -> 250637.62 | I50: =(assumptions!$D$19*assumptions!$D$29)/12 -> 250637.62 | ... M50: =(assumptions!$D$19*assumptions!$D$29)/12 -> 250637.62 | N50: =SUM(B50:M50) -> 3007651.5
A51: Employee Benefits | B51: =B50*assumptions!$D$33 -> 50127.525 | C51: =C50*assumptions!$D$33 -> 50127.525 | D51: =D50*assumptions!$D$33 -> 50127.525 | E51: =E50*assumptions!$D$33 -> 50127.525 | F51: =F50*assumptions!$D$33 -> 50127.525 | G51: =G50*assumptions!$D$33 -> 50127.525 | H51: =H50*assumptions!$D$33 -> 50127.525 | I51: =I50*assumptions!$D$33 -> 50127.525 | ... M51: =M50*assumptions!$D$33 -> 50127.525 | N51: =SUM(B51:M51) -> 601530.3
A52: Software & Tools | B52: =(assumptions!$D$19*assumptions!$D$41)/12 -> 6750 | C52: =(assumptions!$D$19*assumptions!$D$41)/12 -> 6750 | D52: =(assumptions!$D$19*assumptions!$D$41)/12 -> 6750 | E52: =(assumptions!$D$19*assumptions!$D$41)/12 -> 6750 | F52: =(assumptions!$D$19*assumptions!$D$41)/12 -> 6750 | G52: =(assumptions!$D$19*assumptions!$D$41)/12 -> 6750 | H52: =(assumptions!$D$19*assumptions!$D$41)/12 -> 6750 | I52: =(assumptions!$D$19*assumptions!$D$41)/12 -> 6750 | ... M52: =(assumptions!$D$19*assumptions!$D$41)/12 -> 6750 | N52: =SUM(B52:M52) -> 81000
A53: Consulting & Professional Fees | B53: =assumptions!$D$48/12 -> 37500 | C53: =assumptions!$D$48/12 -> 37500 | D53: =assumptions!$D$48/12 -> 37500 | E53: =assumptions!$D$48/12 -> 37500 | F53: =assumptions!$D$48/12 -> 37500 | G53: =assumptions!$D$48/12 -> 37500 | H53: =assumptions!$D$48/12 -> 37500 | I53: =assumptions!$D$48/12 -> 37500 | ... M53: =assumptions!$D$48/12 -> 37500 | N53: =SUM(B53:M53) -> 450000
A54: Rent & Facilities | B54: =(assumptions!$D$49*assumptions!$D$19)/12 -> 13500 | C54: =(assumptions!$D$49*assumptions!$D$19)/12 -> 13500 | D54: =(assumptions!$D$49*assumptions!$D$19)/12 -> 13500 | E54: =(assumptions!$D$49*assumptions!$D$19)/12 -> 13500 | F54: =(assumptions!$D$49*assumptions!$D$19)/12 -> 13500 | G54: =(assumptions!$D$49*assumptions!$D$19)/12 -> 13500 | H54: =(assumptions!$D$49*assumptions!$D$19)/12 -> 13500 | I54: =(assumptions!$D$49*assumptions!$D$19)/12 -> 13500 | ... M54: =(assumptions!$D$49*assumptions!$D$19)/12 -> 13500 | N54: =SUM(B54:M54) -> 162000
A55: Total G&A Expenses | B55: =SUM(B50:B54) -> 358515.15 | C55: =SUM(C50:C54) -> 358515.15 | D55: =SUM(D50:D54) -> 358515.15 | E55: =SUM(E50:E54) -> 358515.15 | F55: =SUM(F50:F54) -> 358515.15 | G55: =SUM(G50:G54) -> 358515.15 | H55: =SUM(H50:H54) -> 358515.15 | I55: =SUM(I50:I54) -> 358515.15 | ... M55: =SUM(M50:M54) -> 358515.15 | N55: =SUM(B55:M55) -> 4302181.8
A58: 2026 Budget Summary | B58: Jan | C58: Feb | D58: Mar | E58: Apr | F58: May | G58: Jun | H58: Jul | I58: Aug | J58: Sep | K58: Oct | L58: Nov | M58: Dec | N58: FY 2026
A59: Total Revenue | B59: =B4 -> 3703000 | C59: =C4 -> 3703000 | D59: =D4 -> 4232000 | E59: =E4 -> 4232000 | F59: =F4 -> 4232000 | G59: =G4 -> 4232000 | H59: =H4 -> 4232000 | I59: =I4 -> 4232000 | ... M59: =M4 -> 5819000 | N59: =SUM(B59:M59) -> 52900000
A61: Sales Expenses | B61: =B13 -> 838175 | C61: =C13 -> 838175 | D61: =D13 -> 861980 | E61: =E13 -> 861980 | F61: =F13 -> 861980 | G61: =G13 -> 861980 | H61: =H13 -> 861980 | I61: =I13 -> 861980 | ... M61: =M13 -> 933395 | N61: =SUM(B61:M61) -> 10438980
A62: Marketing Expenses | B62: =B22 -> 475065.2 | C62: =C22 -> 475065.2 | D62: =D22 -> 506805.2 | E62: =E22 -> 506805.2 | F62: =F22 -> 506805.2 | G62: =G22 -> 506805.2 | H62: =H22 -> 506805.2 | I62: =I22 -> 506805.2 | ... M62: =M22 -> 602025.2 | N62: =SUM(B62:M62) -> 6208622.4
A63: Engineering Expenses | B63: =B30 -> 1343036.3 | C63: =C30 -> 1343036.3 | D63: =D30 -> 1364196.3 | E63: =E30 -> 1364196.3 | F63: =F30 -> 1364196.3 | G63: =G30 -> 1364196.3 | H63: =H30 -> 1364196.3 | I63: =I30 -> 1364196.3 | ... M63: =M30 -> 1427676.3 | N63: =SUM(B63:M63) -> 16454996
A64: Product Expenses | B64: =B38 -> 283797.08 | C64: =C38 -> 283797.08 | D64: =D38 -> 283797.08 | E64: =E38 -> 283797.08 | F64: =F38 -> 283797.08 | G64: =G38 -> 283797.08 | H64: =H38 -> 283797.08 | I64: =I38 -> 283797.08 | ... M64: =M38 -> 283797.08 | N64: =SUM(B64:M64) -> 3405565
A65: Customer Success Expenses | B65: =B46 -> 339635.4 | C65: =C46 -> 339635.4 | D65: =D46 -> 339635.4 | E65: =E46 -> 339635.4 | F65: =F46 -> 339635.4 | G65: =G46 -> 339635.4 | H65: =H46 -> 339635.4 | I65: =I46 -> 339635.4 | ... M65: =M46 -> 339635.4 | N65: =SUM(B65:M65) -> 4075624.8
A66: G&A Expenses | B66: =B55 -> 358515.15 | C66: =C55 -> 358515.15 | D66: =D55 -> 358515.15 | E66: =E55 -> 358515.15 | F66: =F55 -> 358515.15 | G66: =G55 -> 358515.15 | H66: =H55 -> 358515.15 | I66: =I55 -> 358515.15 | ... M66: =M55 -> 358515.15 | N66: =SUM(B66:M66) -> 4302181.8
A67: Total Operating Expenses | B67: =SUM(B61:B66) -> 3638224.1 | C67: =SUM(C61:C66) -> 3638224.1 | D67: =SUM(D61:D66) -> 3714929.1 | E67: =SUM(E61:E66) -> 3714929.1 | F67: =SUM(F61:F66) -> 3714929.1 | G67: =SUM(G61:G66) -> 3714929.1 | H67: =SUM(H61:H66) -> 3714929.1 | I67: =SUM(I61:I66) -> 3714929.1 | ... M67: =SUM(M61:M66) -> 3945044.1 | N67: =SUM(B67:M67) -> 44885970
A69: Operating Profit | B69: =B59-B67 -> 64775.867 | C69: =C59-C67 -> 64775.867 | D69: =D59-D67 -> 517070.87 | E69: =E59-E67 -> 517070.87 | F69: =F59-F67 -> 517070.87 | G69: =G59-G67 -> 517070.87 | H69: =H59-H67 -> 517070.87 | I69: =I59-I67 -> 517070.87 | ... N69: =N59-N67 -> 8014030.4
A70: Operating Margin | B70: =B69/B59 -> 0.017492808 | C70: =C69/C59 -> 0.017492808 | D70: =D69/D59 -> 0.12218121 | E70: =E69/E59 -> 0.12218121 | F70: =F69/F59 -> 0.12218121 | G70: =G69/G59 -> 0.12218121 | H70: =H69/H59 -> 0.12218121 | I70: =I69/I59 -> 0.12218121 | ... N70: =N69/N59 -> 0.15149396

Sheet 2024_actual
A1: 2024 Actual Revenue | B1: Jan | C1: Feb | D1: Mar | E1: Apr | F1: May | G1: Jun | H1: Jul | I1: Aug | J1: Sep | K1: Oct | L1: Nov | M1: Dec | N1: FY 2024
A2: Subscription Revenue | B2: 2420000 | C2: 2440000 | D2: 2720000 | E2: 2760000 | F2: 2790000 | G2: 2820000 | H2: 2840000 | I2: 2870000 | J2: 3180000 | K2: 3220000 | L2: 3270000 | M2: 3670000 | N2: =SUM(B2:M2) -> 35000000
A3: Professional Services Revenue | B3: 270000 | C3: 275000 | D3: 305000 | E3: 310000 | F3: 315000 | G3: 315000 | H3: 320000 | I3: 325000 | J3: 360000 | K3: 365000 | L3: 375000 | M3: 465000 | N3: =SUM(B3:M3) -> 4000000
A4: Total Revenue | B4: =SUM(B2:B3) -> 2690000 | C4: =SUM(C2:C3) -> 2715000 | D4: =SUM(D2:D3) -> 3025000 | E4: =SUM(E2:E3) -> 3070000 | F4: =SUM(F2:F3) -> 3105000 | G4: =SUM(G2:G3) -> 3135000 | H4: =SUM(H2:H3) -> 3160000 | I4: =SUM(I2:I3) -> 3195000 | ... M4: =SUM(M2:M3) -> 4135000 | N4: =SUM(B4:M4) -> 39000000
A7: 2024 Actual Sales | B7: Jan | C7: Feb | D7: Mar | E7: Apr | F7: May | G7: Jun | H7: Jul | I7: Aug | J7: Sep | K7: Oct | L7: Nov | M7: Dec | N7: FY 2024
A8: Salaries & Wages | B8: 400000 | C8: 400000 | D8: 405000 | E8: 405000 | F8: 405000 | G8: 410000 | H8: 410000 | I8: 410000 | J8: 415000 | K8: 415000 | L8: 415000 | M8: 420000 | N8: =SUM(B8:M8) -> 4910000
A9: Employee Benefits | B9: 80000 | C9: 80000 | D9: 81000 | E9: 81000 | F9: 81000 | G9: 82000 | H9: 82000 | I9: 82000 | J9: 83000 | K9: 83000 | L9: 83000 | M9: 84000 | N9: =SUM(B9:M9) -> 982000
A10: Sales Commissions | B10: 121000 | C10: 122000 | D10: 136000 | E10: 138000 | F10: 139500 | G10: 141000 | H10: 142000 | I10: 143500 | J10: 159000 | K10: 161000 | L10: 163500 | M10: 183500 | N10: =SUM(B10:M10) -> 1750000
A11: Software & Tools | B11: 12000 | C11: 12000 | D11: 12000 | E11: 12000 | F11: 12000 | G11: 12000 | H11: 12000 | I11: 12000 | J11: 12000 | K11: 12000 | L11: 12000 | M11: 12000 | N11: =SUM(B11:M11) -> 144000
A12: Travel & Entertainment | B12: 14000 | C12: 15000 | D12: 15000 | E12: 16000 | F12: 16000 | G12: 17000 | H12: 17000 | I12: 17000 | J12: 18000 | K12: 18000 | L12: 19000 | M12: 19000 | N12: =SUM(B12:M12) -> 201000
A13: Total Sales Expenses | B13: =SUM(B8:B12) -> 627000 | C13: =SUM(C8:C12) -> 629000 | D13: =SUM(D8:D12) -> 649000 | E13: =SUM(E8:E12) -> 652000 | F13: =SUM(F8:F12) -> 653500 | G13: =SUM(G8:G12) -> 662000 | H13: =SUM(H8:H12) -> 663000 | I13: =SUM(I8:I12) -> 664500 | ... M13: =SUM(M8:M12) -> 718500 | N13: =SUM(B13:M13) -> 7987000
A16: 2024 Actual Marketing | B16: Jan | C16: Feb | D16: Mar | E16: Apr | F16: May | G16: Jun | H16: Jul | I16: Aug | J16: Sep | K16: Oct | L16: Nov | M16: Dec | N16: FY 2024
A17: Salaries & Wages | B17: 156000 | C17: 156000 | D17: 157000 | E17: 157000 | F17: 158000 | G17: 158000 | H17: 159000 | I17: 159000 | J17: 160000 | K17: 160000 | L17: 161000 | M17: 161000 | N17: =SUM(B17:M17) -> 1902000
A18: Employee Benefits | B18: 31200 | C18: 31200 | D18: 31400 | E18: 31400 | F18: 31600 | G18: 31600 | H18: 31800 | I18: 31800 | J18: 32000 | K18: 32000 | L18: 32200 | M18: 32200 | N18: =SUM(B18:M18) -> 380400
A19: Marketing & Advertising | B19: 180000 | C19: 185000 | D19: 195000 | E19: 200000 | F19: 205000 | G19: 210000 | H19: 215000 | I19: 220000 | J19: 230000 | K19: 235000 | L19: 240000 | M19: 265000 | N19: =SUM(B19:M19) -> 2580000
A20: Software & Tools | B20: 5000 | C20: 5000 | D20: 5000 | E20: 5000 | F20: 5000 | G20: 5000 | H20: 5000 | I20: 5000 | J20: 5000 | K20: 5000 | L20: 5000 | M20: 5000 | N20: =SUM(B20:M20) -> 60000
A21: Travel & Entertainment | B21: 3000 | C21: 3000 | D21: 3500 | E21: 3500 | F21: 4000 | G21: 4000 | H21: 4000 | I21: 4500 | J21: 4500 | K21: 5000 | L21: 5000 | M21: 6000 | N21: =SUM(B21:M21) -> 50000
A22: Total Marketing Expenses | B22: =SUM(B17:B21) -> 375200 | C22: =SUM(C17:C21) -> 380200 | D22: =SUM(D17:D21) -> 391900 | E22: =SUM(E17:E21) -> 396900 | F22: =SUM(F17:F21) -> 403600 | G22: =SUM(G17:G21) -> 408600 | H22: =SUM(H17:H21) -> 414800 | I22: =SUM(I17:I21) -> 420300 | ... M22: =SUM(M17:M21) -> 469200 | N22: =SUM(B22:M22) -> 4972400
A25: 2024 Actual Engineering | B25: Jan | C25: Feb | D25: Mar | E25: Apr | F25: May | G25: Jun | H25: Jul | I25: Aug | J25: Sep | K25: Oct | L25: Nov | M25: Dec | N25: FY 2024
A26: Salaries & Wages | B26: 775000 | C26: 775000 | D26: 780000 | E26: 780000 | F26: 785000 | G26: 785000 | H26: 790000 | I26: 790000 | J26: 795000 | K26: 795000 | L26: 800000 | M26: 800000 | N26: =SUM(B26:M26) -> 9450000
A27: Employee Benefits | B27: 155000 | C27: 155000 | D27: 156000 | E27: 156000 | F27: 157000 | G27: 157000 | H27: 158000 | I27: 158000 | J27: 159000 | K27: 159000 | L27: 160000 | M27: 160000 | N27: =SUM(B27:M27) -> 1890000
A28: Cloud & Hosting | B28: 125000 | C28: 130000 | D28: 135000 | E28: 138000 | F28: 140000 | G28: 142000 | H28: 145000 | I28: 148000 | J28: 155000 | K28: 160000 | L28: 165000 | M28: 177000 | N28: =SUM(B28:M28) -> 1760000
A29: Software & Tools | B29: 17000 | C29: 17000 | D29: 17000 | E29: 17000 | F29: 17000 | G29: 17000 | H29: 17000 | I29: 17000 | J29: 17000 | K29: 17000 | L29: 17000 | M29: 17000 | N29: =SUM(B29:M29) -> 204000
A30: Total Engineering Expenses | B30: =SUM(B26:B29) -> 1072000 | C30: =SUM(C26:C29) -> 1077000 | D30: =SUM(D26:D29) -> 1088000 | E30: =SUM(E26:E29) -> 1091000 | F30: =SUM(F26:F29) -> 1099000 | G30: =SUM(G26:G29) -> 1101000 | H30: =SUM(H26:H29) -> 1110000 | I30: =SUM(I26:I29) -> 1113000 | ... M30: =SUM(M26:M29) -> 1154000 | N30: =SUM(B30:M30) -> 13304000
A33: 2024 Actual Product | B33: Jan | C33: Feb | D33: Mar | E33: Apr | F33: May | G33: Jun | H33: Jul | I33: Aug | J33: Sep | K33: Oct | L33: Nov | M33: Dec | N33: FY 2024
A34: Salaries & Wages | B34: 156000 | C34: 156000 | D34: 156000 | E34: 156000 | F34: 156000 | G34: 156000 | H34: 156000 | I34: 156000 | J34: 157000 | K34: 157000 | L34: 157000 | M34: 157000 | N34: =SUM(B34:M34) -> 1876000
A35: Employee Benefits | B35: 31200 | C35: 31200 | D35: 31200 | E35: 31200 | F35: 31200 | G35: 31200 | H35: 31200 | I35: 31200 | J35: 31400 | K35: 31400 | L35: 31400 | M35: 31400 | N35: =SUM(B35:M35) -> 375200
A36: Software & Tools | B36: 3750 | C36: 3750 | D36: 3750 | E36: 3750 | F36: 3750 | G36: 3750 | H36: 3750 | I36: 3750 | J36: 3750 | K36: 3750 | L36: 3750 | M36: 3750 | N36: =SUM(B36:M36) -> 45000
A37: Consulting & Contractors | B37: 18000 | C37: 18000 | D37: 20000 | E37: 20000 | F37: 21000 | G37: 21000 | H37: 22000 | I37: 22000 | J37: 24000 | K37: 24000 | L37: 25000 | M37: 25000 | N37: =SUM(B37:M37) -> 260000
A38: Total Product Expenses | B38: =SUM(B34:B37) -> 208950 | C38: =SUM(C34:C37) -> 208950 | D38: =SUM(D34:D37) -> 210950 | E38: =SUM(E34:E37) -> 210950 | F38: =SUM(F34:F37) -> 211950 | G38: =SUM(G34:G37) -> 211950 | H38: =SUM(H34:H37) -> 212950 | I38: =SUM(I34:I37) -> 212950 | ... M38: =SUM(M34:M37) -> 217150 | N38: =SUM(B38:M38) -> 2556200
A41: 2024 Actual Customer Success | B41: Jan | C41: Feb | D41: Mar | E41: Apr | F41: May | G41: Jun | H41: Jul | I41: Aug | J41: Sep | K41: Oct | L41: Nov | M41: Dec | N41: FY 2024
A42: Salaries & Wages | B42: 208000 | C42: 208000 | D42: 210000 | E42: 210000 | F42: 211000 | G42: 211000 | H42: 212000 | I42: 212000 | J42: 213000 | K42: 213000 | L42: 214000 | M42: 214000 | N42: =SUM(B42:M42) -> 2536000
A43: Employee Benefits | B43: 41600 | C43: 41600 | D43: 42000 | E43: 42000 | F43: 42200 | G43: 42200 | H43: 42400 | I43: 42400 | J43: 42600 | K43: 42600 | L43: 42800 | M43: 42800 | N43: =SUM(B43:M43) -> 507200
A44: Software & Tools | B44: 7500 | C44: 7500 | D44: 7500 | E44: 7500 | F44: 7500 | G44: 7500 | H44: 7500 | I44: 7500 | J44: 7500 | K44: 7500 | L44: 7500 | M44: 7500 | N44: =SUM(B44:M44) -> 90000
A45: Travel & Entertainment | B45: 4000 | C45: 4000 | D45: 4000 | E45: 4500 | F45: 4500 | G45: 4500 | H45: 5000 | I45: 5000 | J45: 5000 | K45: 5000 | L45: 5500 | M45: 5500 | N45: =SUM(B45:M45) -> 56500
A46: Total Customer Success Expenses | B46: =SUM(B42:B45) -> 261100 | C46: =SUM(C42:C45) -> 261100 | D46: =SUM(D42:D45) -> 263500 | E46: =SUM(E42:E45) -> 264000 | F46: =SUM(F42:F45) -> 265200 | G46: =SUM(G42:G45) -> 265200 | H46: =SUM(H42:H45) -> 266900 | I46: =SUM(I42:I45) -> 266900 | ... M46: =SUM(M42:M45) -> 269800 | N46: =SUM(B46:M46) -> 3189700
A49: 2024 Actual G&A | B49: Jan | C49: Feb | D49: Mar | E49: Apr | F49: May | G49: Jun | H49: Jul | I49: Aug | J49: Sep | K49: Oct | L49: Nov | M49: Dec | N49: FY 2024
A50: Salaries & Wages | B50: 216000 | C50: 216000 | D50: 217000 | E50: 217000 | F50: 218000 | G50: 218000 | H50: 219000 | I50: 219000 | J50: 220000 | K50: 220000 | L50: 221000 | M50: 221000 | N50: =SUM(B50:M50) -> 2622000
A51: Employee Benefits | B51: 43200 | C51: 43200 | D51: 43400 | E51: 43400 | F51: 43600 | G51: 43600 | H51: 43800 | I51: 43800 | J51: 44000 | K51: 44000 | L51: 44200 | M51: 44200 | N51: =SUM(B51:M51) -> 524400
A52: Software & Tools | B52: 6250 | C52: 6250 | D52: 6250 | E52: 6250 | F52: 6250 | G52: 6250 | H52: 6250 | I52: 6250 | J52: 6250 | K52: 6250 | L52: 6250 | M52: 6250 | N52: =SUM(B52:M52) -> 75000
A53: Consulting & Professional Fees | B53: 30000 | C53: 30000 | D53: 32000 | E53: 32000 | F53: 34000 | G53: 34000 | H53: 35000 | I53: 35000 | J53: 37000 | K53: 37000 | L53: 40000 | M53: 40000 | N53: =SUM(B53:M53) -> 416000
A54: Rent & Facilities | B54: 12500 | C54: 12500 | D54: 12500 | E54: 12500 | F54: 12500 | G54: 12500 | H54: 12500 | I54: 12500 | J54: 13000 | K54: 13000 | L54: 13000 | M54: 13000 | N54: =SUM(B54:M54) -> 152000
A55: Total G&A Expenses | B55: =SUM(B50:B54) -> 307950 | C55: =SUM(C50:C54) -> 307950 | D55: =SUM(D50:D54) -> 311150 | E55: =SUM(E50:E54) -> 311150 | F55: =SUM(F50:F54) -> 314350 | G55: =SUM(G50:G54) -> 314350 | H55: =SUM(H50:H54) -> 316550 | I55: =SUM(I50:I54) -> 316550 | ... M55: =SUM(M50:M54) -> 324450 | N55: =SUM(B55:M55) -> 3789400
A58: 2024 Actual Summary | B58: Jan | C58: Feb | D58: Mar | E58: Apr | F58: May | G58: Jun | H58: Jul | I58: Aug | J58: Sep | K58: Oct | L58: Nov | M58: Dec | N58: FY 2024
A59: Total Revenue | B59: =B4 -> 2690000 | C59: =C4 -> 2715000 | D59: =D4 -> 3025000 | E59: =E4 -> 3070000 | F59: =F4 -> 3105000 | G59: =G4 -> 3135000 | H59: =H4 -> 3160000 | I59: =I4 -> 3195000 | ... M59: =M4 -> 4135000 | N59: =SUM(B59:M59) -> 39000000
A61: Sales Expenses | B61: =B13 -> 627000 | C61: =C13 -> 629000 | D61: =D13 -> 649000 | E61: =E13 -> 652000 | F61: =F13 -> 653500 | G61: =G13 -> 662000 | H61: =H13 -> 663000 | I61: =I13 -> 664500 | ... M61: =M13 -> 718500 | N61: =SUM(B61:M61) -> 7987000
A62: Marketing Expenses | B62: =B22 -> 375200 | C62: =C22 -> 380200 | D62: =D22 -> 391900 | E62: =E22 -> 396900 | F62: =F22 -> 403600 | G62: =G22 -> 408600 | H62: =H22 -> 414800 | I62: =I22 -> 420300 | ... M62: =M22 -> 469200 | N62: =SUM(B62:M62) -> 4972400
A63: Engineering Expenses | B63: =B30 -> 1072000 | C63: =C30 -> 1077000 | D63: =D30 -> 1088000 | E63: =E30 -> 1091000 | F63: =F30 -> 1099000 | G63: =G30 -> 1101000 | H63: =H30 -> 1110000 | I63: =I30 -> 1113000 | ... M63: =M30 -> 1154000 | N63: =SUM(B63:M63) -> 13304000
A64: Product Expenses | B64: =B38 -> 208950 | C64: =C38 -> 208950 | D64: =D38 -> 210950 | E64: =E38 -> 210950 | F64: =F38 -> 211950 | G64: =G38 -> 211950 | H64: =H38 -> 212950 | I64: =I38 -> 212950 | ... M64: =M38 -> 217150 | N64: =SUM(B64:M64) -> 2556200
A65: Customer Success Expenses | B65: =B46 -> 261100 | C65: =C46 -> 261100 | D65: =D46 -> 263500 | E65: =E46 -> 264000 | F65: =F46 -> 265200 | G65: =G46 -> 265200 | H65: =H46 -> 266900 | I65: =I46 -> 266900 | ... M65: =M46 -> 269800 | N65: =SUM(B65:M65) -> 3189700
A66: G&A Expenses | B66: =B55 -> 307950 | C66: =C55 -> 307950 | D66: =D55 -> 311150 | E66: =E55 -> 311150 | F66: =F55 -> 314350 | G66: =G55 -> 314350 | H66: =H55 -> 316550 | I66: =I55 -> 316550 | ... M66: =M55 -> 324450 | N66: =SUM(B66:M66) -> 3789400
A67: Total Operating Expenses | B67: =SUM(B61:B66) -> 2852200 | C67: =SUM(C61:C66) -> 2864200 | D67: =SUM(D61:D66) -> 2914500 | E67: =SUM(E61:E66) -> 2926000 | F67: =SUM(F61:F66) -> 2947600 | G67: =SUM(G61:G66) -> 2963100 | H67: =SUM(H61:H66) -> 2984200 | I67: =SUM(I61:I66) -> 2994200 | ... M67: =SUM(M61:M66) -> 3153100 | N67: =SUM(B67:M67) -> 35798700
A69: Operating Profit | B69: =B59-B67 -> -162200 | C69: =C59-C67 -> -149200 | D69: =D59-D67 -> 110500 | E69: =E59-E67 -> 144000 | F69: =F59-F67 -> 157400 | G69: =G59-G67 -> 171900 | H69: =H59-H67 -> 175800 | I69: =I59-I67 -> 200800 | ... N69: =N59-N67 -> 3201300
A70: Operating Margin | B70: =B69/B59 -> -0.060297398 | C70: =C69/C59 -> -0.054953959 | D70: =D69/D59 -> 0.036528926 | E70: =E69/E59 -> 0.046905537 | F70: =F69/F59 -> 0.050692432 | G70: =G69/G59 -> 0.054832536 | H70: =H69/H59 -> 0.055632911 | I70: =I69/I59 -> 0.0628482 | ... N70: =N69/N59 -> 0.082084615

Sheet 2025_actual
A1: 2025 Actual Revenue | B1: Jan | C1: Feb | D1: Mar | E1: Apr | F1: May | G1: Jun | H1: Jul | I1: Aug | J1: Sep | K1: Oct | L1: Nov | M1: Dec | N1: FY 2025
A2: Subscription Revenue | B2: 2850000 | C2: 2900000 | D2: 3300000 | E2: 3350000 | F2: 3380000 | G2: 3400000 | H2: 3420000 | I2: 3450000 | J2: 3850000 | K2: 3900000 | L2: 3950000 | M2: 4650000 | N2: =SUM(B2:M2) -> 42400000
A3: Professional Services Revenue | B3: 310000 | C3: 315000 | D3: 350000 | E3: 350000 | F3: 355000 | G3: 360000 | H3: 365000 | I3: 370000 | J3: 400000 | K3: 405000 | L3: 410000 | M3: 410000 | N3: =SUM(B3:M3) -> 4400000
A4: Total Revenue | B4: =SUM(B2:B3) -> 3160000 | C4: =SUM(C2:C3) -> 3215000 | D4: =SUM(D2:D3) -> 3650000 | E4: =SUM(E2:E3) -> 3700000 | F4: =SUM(F2:F3) -> 3735000 | G4: =SUM(G2:G3) -> 3760000 | H4: =SUM(H2:H3) -> 3785000 | I4: =SUM(I2:I3) -> 3820000 | ... M4: =SUM(M2:M3) -> 5060000 | N4: =SUM(B4:M4) -> 46800000
A7: 2025 Actual Sales | B7: Jan | C7: Feb | D7: Mar | E7: Apr | F7: May | G7: Jun | H7: Jul | I7: Aug | J7: Sep | K7: Oct | L7: Nov | M7: Dec | N7: FY 2025
A8: Salaries & Wages | B8: 465000 | C8: 465000 | D8: 470000 | E8: 470000 | F8: 475000 | G8: 475000 | H8: 480000 | I8: 480000 | J8: 485000 | K8: 485000 | L8: 490000 | M8: 490000 | N8: =SUM(B8:M8) -> 5730000
A9: Employee Benefits | B9: 93000 | C9: 93000 | D9: 94000 | E9: 94000 | F9: 95000 | G9: 95000 | H9: 96000 | I9: 96000 | J9: 97000 | K9: 97000 | L9: 98000 | M9: 98000 | N9: =SUM(B9:M9) -> 1146000
A10: Sales Commissions | B10: 145000 | C10: 147500 | D10: 165000 | E10: 167500 | F10: 169000 | G10: 170000 | H10: 171000 | I10: 172500 | J10: 192500 | K10: 195000 | L10: 197500 | M10: 232500 | N10: =SUM(B10:M10) -> 2125000
A11: Software & Tools | B11: 13750 | C11: 13750 | D11: 13750 | E11: 13750 | F11: 13750 | G11: 13750 | H11: 13750 | I11: 13750 | J11: 13750 | K11: 13750 | L11: 13750 | M11: 13750 | N11: =SUM(B11:M11) -> 165000
A12: Travel & Entertainment | B12: 17000 | C12: 17000 | D12: 17500 | E12: 17500 | F12: 18000 | G12: 18000 | H12: 18500 | I12: 18500 | J12: 19000 | K12: 19000 | L12: 20000 | M12: 20000 | N12: =SUM(B12:M12) -> 220000
A13: Total Sales Expenses | B13: =SUM(B8:B12) -> 733750 | C13: =SUM(C8:C12) -> 736250 | D13: =SUM(D8:D12) -> 760250 | E13: =SUM(E8:E12) -> 762750 | F13: =SUM(F8:F12) -> 770750 | G13: =SUM(G8:G12) -> 771750 | H13: =SUM(H8:H12) -> 779250 | I13: =SUM(I8:I12) -> 780750 | ... M13: =SUM(M8:M12) -> 854250 | N13: =SUM(B13:M13) -> 9386000
A16: 2025 Actual Marketing | B16: Jan | C16: Feb | D16: Mar | E16: Apr | F16: May | G16: Jun | H16: Jul | I16: Aug | J16: Sep | K16: Oct | L16: Nov | M16: Dec | N16: FY 2025
A17: Salaries & Wages | B17: 178000 | C17: 178000 | D17: 179000 | E17: 179000 | F17: 180000 | G17: 180000 | H17: 181000 | I17: 181000 | J17: 182000 | K17: 182000 | L17: 183000 | M17: 183000 | N17: =SUM(B17:M17) -> 2166000
A18: Employee Benefits | B18: 35600 | C18: 35600 | D18: 35800 | E18: 35800 | F18: 36000 | G18: 36000 | H18: 36200 | I18: 36200 | J18: 36400 | K18: 36400 | L18: 36600 | M18: 36600 | N18: =SUM(B18:M18) -> 433200
A19: Marketing & Advertising | B19: 200000 | C19: 205000 | D19: 225000 | E19: 230000 | F19: 235000 | G19: 240000 | H19: 245000 | I19: 250000 | J19: 270000 | K19: 275000 | L19: 280000 | M19: 325000 | N19: =SUM(B19:M19) -> 2980000
A20: Software & Tools | B20: 5500 | C20: 5500 | D20: 5500 | E20: 5500 | F20: 5500 | G20: 5500 | H20: 5500 | I20: 5500 | J20: 5500 | K20: 5500 | L20: 5500 | M20: 5500 | N20: =SUM(B20:M20) -> 66000
A21: Travel & Entertainment | B21: 4000 | C21: 4000 | D21: 4000 | E21: 4500 | F21: 4500 | G21: 4500 | H21: 4500 | I21: 5000 | J21: 5000 | K21: 5000 | L21: 5500 | M21: 5500 | N21: =SUM(B21:M21) -> 56000
A22: Total Marketing Expenses | B22: =SUM(B17:B21) -> 423100 | C22: =SUM(C17:C21) -> 428100 | D22: =SUM(D17:D21) -> 449300 | E22: =SUM(E17:E21) -> 454800 | F22: =SUM(F17:F21) -> 461000 | G22: =SUM(G17:G21) -> 466000 | H22: =SUM(H17:H21) -> 472200 | I22: =SUM(I17:I21) -> 477700 | ... M22: =SUM(M17:M21) -> 555600 | N22: =SUM(B22:M22) -> 5701200
A25: 2025 Actual Engineering | B25: Jan | C25: Feb | D25: Mar | E25: Apr | F25: May | G25: Jun | H25: Jul | I25: Aug | J25: Sep | K25: Oct | L25: Nov | M25: Dec | N25: FY 2025
A26: Salaries & Wages | B26: 870000 | C26: 870000 | D26: 875000 | E26: 875000 | F26: 880000 | G26: 880000 | H26: 885000 | I26: 885000 | J26: 890000 | K26: 890000 | L26: 895000 | M26: 895000 | N26: =SUM(B26:M26) -> 10590000
A27: Employee Benefits | B27: 174000 | C27: 174000 | D27: 175000 | E27: 175000 | F27: 176000 | G27: 176000 | H27: 177000 | I27: 177000 | J27: 178000 | K27: 178000 | L27: 179000 | M27: 179000 | N27: =SUM(B27:M27) -> 2118000
A28: Cloud & Hosting | B28: 145000 | C28: 150000 | D28: 155000 | E28: 158000 | F28: 160000 | G28: 162000 | H28: 165000 | I28: 168000 | J28: 175000 | K28: 180000 | L28: 185000 | M28: 197000 | N28: =SUM(B28:M28) -> 2000000
A29: Software & Tools | B29: 19000 | C29: 19000 | D29: 19000 | E29: 19000 | F29: 19000 | G29: 19000 | H29: 19000 | I29: 19000 | J29: 19000 | K29: 19000 | L29: 19000 | M29: 19000 | N29: =SUM(B29:M29) -> 228000
A30: Total Engineering Expenses | B30: =SUM(B26:B29) -> 1208000 | C30: =SUM(C26:C29) -> 1213000 | D30: =SUM(D26:D29) -> 1224000 | E30: =SUM(E26:E29) -> 1227000 | F30: =SUM(F26:F29) -> 1235000 | G30: =SUM(G26:G29) -> 1237000 | H30: =SUM(H26:H29) -> 1246000 | I30: =SUM(I26:I29) -> 1249000 | ... M30: =SUM(M26:M29) -> 1290000 | N30: =SUM(B30:M30) -> 14936000
A33: 2025 Actual Product | B33: Jan | C33: Feb | D33: Mar | E33: Apr | F33: May | G33: Jun | H33: Jul | I33: Aug | J33: Sep | K33: Oct | L33: Nov | M33: Dec | N33: FY 2025
A34: Salaries & Wages | B34: 181000 | C34: 181000 | D34: 182000 | E34: 182000 | F34: 182000 | G34: 182000 | H34: 183000 | I34: 183000 | J34: 184000 | K34: 184000 | L34: 185000 | M34: 185000 | N34: =SUM(B34:M34) -> 2194000
A35: Employee Benefits | B35: 36200 | C35: 36200 | D35: 36400 | E35: 36400 | F35: 36400 | G35: 36400 | H35: 36600 | I35: 36600 | J35: 36800 | K35: 36800 | L35: 37000 | M35: 37000 | N35: =SUM(B35:M35) -> 438800
A36: Software & Tools | B36: 4250 | C36: 4250 | D36: 4250 | E36: 4250 | F36: 4250 | G36: 4250 | H36: 4250 | I36: 4250 | J36: 4250 | K36: 4250 | L36: 4250 | M36: 4250 | N36: =SUM(B36:M36) -> 51000
A37: Consulting & Contractors | B37: 23000 | C37: 23000 | D37: 24000 | E37: 24000 | F37: 25000 | G37: 25000 | H37: 26000 | I37: 26000 | J37: 27000 | K37: 27000 | L37: 28000 | M37: 32000 | N37: =SUM(B37:M37) -> 310000
A38: Total Product Expenses | B38: =SUM(B34:B37) -> 244450 | C38: =SUM(C34:C37) -> 244450 | D38: =SUM(D34:D37) -> 246650 | E38: =SUM(E34:E37) -> 246650 | F38: =SUM(F34:F37) -> 247650 | G38: =SUM(G34:G37) -> 247650 | H38: =SUM(H34:H37) -> 249850 | I38: =SUM(I34:I37) -> 249850 | ... M38: =SUM(M34:M37) -> 258250 | N38: =SUM(B38:M38) -> 2993800
A41: 2025 Actual Customer Success | B41: Jan | C41: Feb | D41: Mar | E41: Apr | F41: May | G41: Jun | H41: Jul | I41: Aug | J41: Sep | K41: Oct | L41: Nov | M41: Dec | N41: FY 2025
A42: Salaries & Wages | B42: 237000 | C42: 237000 | D42: 238000 | E42: 238000 | F42: 239000 | G42: 239000 | H42: 240000 | I42: 240000 | J42: 241000 | K42: 241000 | L42: 242000 | M42: 242000 | N42: =SUM(B42:M42) -> 2874000
A43: Employee Benefits | B43: 47400 | C43: 47400 | D43: 47600 | E43: 47600 | F43: 47800 | G43: 47800 | H43: 48000 | I43: 48000 | J43: 48200 | K43: 48200 | L43: 48400 | M43: 48400 | N43: =SUM(B43:M43) -> 574800
A44: Software & Tools | B44: 8250 | C44: 8250 | D44: 8250 | E44: 8250 | F44: 8250 | G44: 8250 | H44: 8250 | I44: 8250 | J44: 8250 | K44: 8250 | L44: 8250 | M44: 8250 | N44: =SUM(B44:M44) -> 99000
A45: Travel & Entertainment | B45: 4500 | C45: 4500 | D45: 4500 | E45: 5000 | F45: 5000 | G45: 5000 | H45: 5000 | I45: 5500 | J45: 5500 | K45: 5500 | L45: 5500 | M45: 6000 | N45: =SUM(B45:M45) -> 61500
A46: Total Customer Success Expenses | B46: =SUM(B42:B45) -> 297150 | C46: =SUM(C42:C45) -> 297150 | D46: =SUM(D42:D45) -> 298350 | E46: =SUM(E42:E45) -> 298850 | F46: =SUM(F42:F45) -> 300050 | G46: =SUM(G42:G45) -> 300050 | H46: =SUM(H42:H45) -> 301250 | I46: =SUM(I42:I45) -> 301750 | ... M46: =SUM(M42:M45) -> 304650 | N46: =SUM(B46:M46) -> 3609300
A49: 2025 Actual G&A | B49: Jan | C49: Feb | D49: Mar | E49: Apr | F49: May | G49: Jun | H49: Jul | I49: Aug | J49: Sep | K49: Oct | L49: Nov | M49: Dec | N49: FY 2025
A50: Salaries & Wages | B50: 232000 | C50: 232000 | D50: 233000 | E50: 233000 | F50: 234000 | G50: 234000 | H50: 235000 | I50: 235000 | J50: 236000 | K50: 236000 | L50: 237000 | M50: 237000 | N50: =SUM(B50:M50) -> 2814000
A51: Employee Benefits | B51: 46400 | C51: 46400 | D51: 46600 | E51: 46600 | F51: 46800 | G51: 46800 | H51: 47000 | I51: 47000 | J51: 47200 | K51: 47200 | L51: 47400 | M51: 47400 | N51: =SUM(B51:M51) -> 562800
A52: Software & Tools | B52: 6500 | C52: 6500 | D52: 6500 | E52: 6500 | F52: 6500 | G52: 6500 | H52: 6500 | I52: 6500 | J52: 6500 | K52: 6500 | L52: 6500 | M52: 6500 | N52: =SUM(B52:M52) -> 78000
A53: Consulting & Professional Fees | B53: 34000 | C53: 34000 | D53: 35000 | E53: 35000 | F53: 36000 | G53: 36000 | H53: 37000 | I53: 37000 | J53: 38000 | K53: 38000 | L53: 39000 | M53: 41000 | N53: =SUM(B53:M53) -> 440000
A54: Rent & Facilities | B54: 13000 | C54: 13000 | D54: 13000 | E54: 13000 | F54: 13000 | G54: 13000 | H54: 13000 | I54: 13000 | J54: 13000 | K54: 13000 | L54: 13000 | M54: 13000 | N54: =SUM(B54:M54) -> 156000
A55: Total G&A Expenses | B55: =SUM(B50:B54) -> 331900 | C55: =SUM(C50:C54) -> 331900 | D55: =SUM(D50:D54) -> 334100 | E55: =SUM(E50:E54) -> 334100 | F55: =SUM(F50:F54) -> 336300 | G55: =SUM(G50:G54) -> 336300 | H55: =SUM(H50:H54) -> 338500 | I55: =SUM(I50:I54) -> 338500 | ... M55: =SUM(M50:M54) -> 344900 | N55: =SUM(B55:M55) -> 4050800
A58: 2025 Actual Summary | B58: Jan | C58: Feb | D58: Mar | E58: Apr | F58: May | G58: Jun | H58: Jul | I58: Aug | J58: Sep | K58: Oct | L58: Nov | M58: Dec | N58: FY 2025
A59: Total Revenue | B59: =B4 -> 3160000 | C59: =C4 -> 3215000 | D59: =D4 -> 3650000 | E59: =E4 -> 3700000 | F59: =F4 -> 3735000 | G59: =G4 -> 3760000 | H59: =H4 -> 3785000 | I59: =I4 -> 3820000 | ... M59: =M4 -> 5060000 | N59: =SUM(B59:M59) -> 46800000
A61: Sales Expenses | B61: =B13 -> 733750 | C61: =C13 -> 736250 | D61: =D13 -> 760250 | E61: =E13 -> 762750 | F61: =F13 -> 770750 | G61: =G13 -> 771750 | H61: =H13 -> 779250 | I61: =I13 -> 780750 | ... M61: =M13 -> 854250 | N61: =SUM(B61:M61) -> 9386000
A62: Marketing Expenses | B62: =B22 -> 423100 | C62: =C22 -> 428100 | D62: =D22 -> 449300 | E62: =E22 -> 454800 | F62: =F22 -> 461000 | G62: =G22 -> 466000 | H62: =H22 -> 472200 | I62: =I22 -> 477700 | ... M62: =M22 -> 555600 | N62: =SUM(B62:M62) -> 5701200
A63: Engineering Expenses | B63: =B30 -> 1208000 | C63: =C30 -> 1213000 | D63: =D30 -> 1224000 | E63: =E30 -> 1227000 | F63: =F30 -> 1235000 | G63: =G30 -> 1237000 | H63: =H30 -> 1246000 | I63: =I30 -> 1249000 | ... M63: =M30 -> 1290000 | N63: =SUM(B63:M63) -> 14936000
A64: Product Expenses | B64: =B38 -> 244450 | C64: =C38 -> 244450 | D64: =D38 -> 246650 | E64: =E38 -> 246650 | F64: =F38 -> 247650 | G64: =G38 -> 247650 | H64: =H38 -> 249850 | I64: =I38 -> 249850 | ... M64: =M38 -> 258250 | N64: =SUM(B64:M64) -> 2993800
A65: Customer Success Expenses | B65: =B46 -> 297150 | C65: =C46 -> 297150 | D65: =D46 -> 298350 | E65: =E46 -> 298850 | F65: =F46 -> 300050 | G65: =G46 -> 300050 | H65: =H46 -> 301250 | I65: =I46 -> 301750 | ... M65: =M46 -> 304650 | N65: =SUM(B65:M65) -> 3609300
A66: G&A Expenses | B66: =B55 -> 331900 | C66: =C55 -> 331900 | D66: =D55 -> 334100 | E66: =E55 -> 334100 | F66: =F55 -> 336300 | G66: =G55 -> 336300 | H66: =H55 -> 338500 | I66: =I55 -> 338500 | ... M66: =M55 -> 344900 | N66: =SUM(B66:M66) -> 4050800
A67: Total Operating Expenses | B67: =SUM(B61:B66) -> 3238350 | C67: =SUM(C61:C66) -> 3250850 | D67: =SUM(D61:D66) -> 3312650 | E67: =SUM(E61:E66) -> 3324150 | F67: =SUM(F61:F66) -> 3350750 | G67: =SUM(G61:G66) -> 3358750 | H67: =SUM(H61:H66) -> 3387050 | I67: =SUM(I61:I66) -> 3397550 | ... M67: =SUM(M61:M66) -> 3607650 | N67: =SUM(B67:M67) -> 40677100
A69: Operating Profit | B69: =B59-B67 -> -78350 | C69: =C59-C67 -> -35850 | D69: =D59-D67 -> 337350 | E69: =E59-E67 -> 375850 | F69: =F59-F67 -> 384250 | G69: =G59-G67 -> 401250 | H69: =H59-H67 -> 397950 | I69: =I59-I67 -> 422450 | ... N69: =N59-N67 -> 6122900
A70: Operating Margin | B70: =B69/B59 -> -0.024794304 | C70: =C69/C59 -> -0.011150855 | D70: =D69/D59 -> 0.092424658 | E70: =E69/E59 -> 0.10158108 | F70: =F69/F59 -> 0.10287818 | G70: =G69/G59 -> 0.10671543 | H70: =H69/H59 -> 0.10513871 | I70: =I69/I59 -> 0.11058901 | ... N70: =N69/N59 -> 0.1308312

Sheet 2026_actual
A1: 2026 Actual Revenue | B1: Jan | C1: Feb | D1: Mar | E1: Apr | F1: May | G1: Jun | H1: Jul | I1: Aug | J1: Sep | K1: Oct | L1: Nov | M1: Dec | N1: FY 2026
A2: Subscription Revenue | B2: 3280000 | C2: 3350000 | D2: 3750000 | E2: 3820000 | F2: 3870000 | G2: 3900000 | H2: 3940000 | I2: 3980000 | J2: 4410000 | K2: 4460000 | L2: 4520000 | M2: 5370000 | N2: =SUM(B2:M2) -> 48650000
A3: Professional Services Revenue | B3: 370000 | C3: 370000 | D3: 430000 | E3: 430000 | F3: 430000 | G3: 440000 | H3: 440000 | I3: 440000 | J3: 490000 | K3: 500000 | L3: 500000 | M3: 560000 | N3: =SUM(B3:M3) -> 5400000
A4: Total Revenue | B4: =SUM(B2:B3) -> 3650000 | C4: =SUM(C2:C3) -> 3720000 | D4: =SUM(D2:D3) -> 4180000 | E4: =SUM(E2:E3) -> 4250000 | F4: =SUM(F2:F3) -> 4300000 | G4: =SUM(G2:G3) -> 4340000 | H4: =SUM(H2:H3) -> 4380000 | I4: =SUM(I2:I3) -> 4420000 | ... M4: =SUM(M2:M3) -> 5930000 | N4: =SUM(B4:M4) -> 54050000
A7: 2026 Actual Sales | B7: Jan | C7: Feb | D7: Mar | E7: Apr | F7: May | G7: Jun | H7: Jul | I7: Aug | J7: Sep | K7: Oct | L7: Nov | M7: Dec | N7: FY 2026
A8: Salaries & Wages | B8: 520000 | C8: 520000 | D8: 525000 | E8: 525000 | F8: 530000 | G8: 530000 | H8: 535000 | I8: 535000 | J8: 540000 | K8: 540000 | L8: 545000 | M8: 545000 | N8: =SUM(B8:M8) -> 6390000
A9: Employee Benefits | B9: 104000 | C9: 104000 | D9: 105000 | E9: 105000 | F9: 106000 | G9: 106000 | H9: 107000 | I9: 107000 | J9: 108000 | K9: 108000 | L9: 109000 | M9: 109000 | N9: =SUM(B9:M9) -> 1278000
A10: Sales Commissions | B10: 164000 | C10: 168000 | D10: 188000 | E10: 191000 | F10: 194000 | G10: 195000 | H10: 197000 | I10: 199000 | J10: 221000 | K10: 223000 | L10: 226000 | M10: 269000 | N10: =SUM(B10:M10) -> 2435000
A11: Software & Tools | B11: 15000 | C11: 15000 | D11: 15000 | E11: 15000 | F11: 15000 | G11: 15000 | H11: 15000 | I11: 15000 | J11: 15000 | K11: 15000 | L11: 15000 | M11: 15000 | N11: =SUM(B11:M11) -> 180000
A12: Travel & Entertainment | B12: 19000 | C12: 19000 | D12: 20000 | E12: 20000 | F12: 20000 | G12: 20000 | H12: 21000 | I12: 21000 | J12: 21000 | K12: 21000 | L12: 22000 | M12: 22000 | N12: =SUM(B12:M12) -> 246000
A13: Total Sales Expenses | B13: =SUM(B8:B12) -> 822000 | C13: =SUM(C8:C12) -> 826000 | D13: =SUM(D8:D12) -> 853000 | E13: =SUM(E8:E12) -> 856000 | F13: =SUM(F8:F12) -> 865000 | G13: =SUM(G8:G12) -> 866000 | H13: =SUM(H8:H12) -> 875000 | I13: =SUM(I8:I12) -> 877000 | ... N13: =SUM(N8:N12) -> 10529000
A16: 2026 Actual Marketing | B16: Jan | C16: Feb | D16: Mar | E16: Apr | F16: May | G16: Jun | H16: Jul | I16: Aug | J16: Sep | K16: Oct | L16: Nov | M16: Dec | N16: FY 2026
A17: Salaries & Wages | B17: 198000 | C17: 198000 | D17: 199000 | E17: 199000 | F17: 200000 | G17: 200000 | H17: 201000 | I17: 201000 | J17: 202000 | K17: 202000 | L17: 203000 | M17: 203000 | N17: =SUM(B17:M17) -> 2406000
A18: Employee Benefits | B18: 39600 | C18: 39600 | D18: 39800 | E18: 39800 | F18: 40000 | G18: 40000 | H18: 40200 | I18: 40200 | J18: 40400 | K18: 40400 | L18: 40600 | M18: 40600 | N18: =SUM(B18:M18) -> 481200
A19: Marketing & Advertising | B19: 235000 | C19: 240000 | D19: 255000 | E19: 260000 | F19: 265000 | G19: 270000 | H19: 275000 | I19: 280000 | J19: 300000 | K19: 305000 | L19: 310000 | M19: 350000 | N19: =SUM(B19:M19) -> 3345000
A20: Software & Tools | B20: 6000 | C20: 6000 | D20: 6000 | E20: 6000 | F20: 6000 | G20: 6000 | H20: 6000 | I20: 6000 | J20: 6000 | K20: 6000 | L20: 6000 | M20: 6000 | N20: =SUM(B20:M20) -> 72000
A21: Travel & Entertainment | B21: 4500 | C21: 4500 | D21: 5000 | E21: 5000 | F21: 5000 | G21: 5000 | H21: 5500 | I21: 5500 | J21: 5500 | K21: 5500 | L21: 6000 | M21: 6000 | N21: =SUM(B21:M21) -> 63000
A22: Total Marketing Expenses | B22: =SUM(B17:B21) -> 483100 | C22: =SUM(C17:C21) -> 488100 | D22: =SUM(D17:D21) -> 504800 | E22: =SUM(E17:E21) -> 509800 | F22: =SUM(F17:F21) -> 516000 | G22: =SUM(G17:G21) -> 521000 | H22: =SUM(H17:H21) -> 527700 | I22: =SUM(I17:I21) -> 532700 | ... N22: =SUM(N17:N21) -> 6367200
A25: 2026 Actual Engineering | B25: Jan | C25: Feb | D25: Mar | E25: Apr | F25: May | G25: Jun | H25: Jul | I25: Aug | J25: Sep | K25: Oct | L25: Nov | M25: Dec | N25: FY 2026
A26: Salaries & Wages | B26: 960000 | C26: 960000 | D26: 965000 | E26: 965000 | F26: 970000 | G26: 970000 | H26: 975000 | I26: 975000 | J26: 980000 | K26: 980000 | L26: 985000 | M26: 985000 | N26: =SUM(B26:M26) -> 11670000
A27: Employee Benefits | B27: 192000 | C27: 192000 | D27: 193000 | E27: 193000 | F27: 194000 | G27: 194000 | H27: 195000 | I27: 195000 | J27: 196000 | K27: 196000 | L27: 197000 | M27: 197000 | N27: =SUM(B27:M27) -> 2334000
A28: Cloud & Hosting | B28: 175000 | C28: 180000 | D28: 185000 | E28: 190000 | F28: 195000 | G28: 200000 | H28: 205000 | I28: 210000 | J28: 220000 | K28: 225000 | L28: 230000 | M28: 250000 | N28: =SUM(B28:M28) -> 2465000
A29: Software & Tools | B29: 20500 | C29: 20500 | D29: 20500 | E29: 20500 | F29: 20500 | G29: 20500 | H29: 20500 | I29: 20500 | J29: 20500 | K29: 20500 | L29: 20500 | M29: 20500 | N29: =SUM(B29:M29) -> 246000
A30: Total Engineering Expenses | B30: =SUM(B26:B29) -> 1347500 | C30: =SUM(C26:C29) -> 1352500 | D30: =SUM(D26:D29) -> 1363500 | E30: =SUM(E26:E29) -> 1368500 | F30: =SUM(F26:F29) -> 1379500 | G30: =SUM(G26:G29) -> 1384500 | H30: =SUM(H26:H29) -> 1395500 | I30: =SUM(I26:I29) -> 1400500 | ... N30: =SUM(N26:N29) -> 16715000
A33: 2026 Actual Product | B33: Jan | C33: Feb | D33: Mar | E33: Apr | F33: May | G33: Jun | H33: Jul | I33: Aug | J33: Sep | K33: Oct | L33: Nov | M33: Dec | N33: FY 2026
A34: Salaries & Wages | B34: 207000 | C34: 207000 | D34: 208000 | E34: 208000 | F34: 209000 | G34: 209000 | H34: 210000 | I34: 210000 | J34: 211000 | K34: 211000 | L34: 212000 | M34: 212000 | N34: =SUM(B34:M34) -> 2514000
A35: Employee Benefits | B35: 41400 | C35: 41400 | D35: 41600 | E35: 41600 | F35: 41800 | G35: 41800 | H35: 42000 | I35: 42000 | J35: 42200 | K35: 42200 | L35: 42400 | M35: 42400 | N35: =SUM(B35:M35) -> 502800
A36: Software & Tools | B36: 4750 | C36: 4750 | D36: 4750 | E36: 4750 | F36: 4750 | G36: 4750 | H36: 4750 | I36: 4750 | J36: 4750 | K36: 4750 | L36: 4750 | M36: 4750 | N36: =SUM(B36:M36) -> 57000
A37: Consulting & Contractors | B37: 25000 | C37: 25000 | D37: 26000 | E37: 26000 | F37: 27000 | G37: 27000 | H37: 28000 | I37: 28000 | J37: 29000 | K37: 29000 | L37: 30000 | M37: 35000 | N37: =SUM(B37:M37) -> 335000
A38: Total Product Expenses | B38: =SUM(B34:B37) -> 278150 | C38: =SUM(C34:C37) -> 278150 | D38: =SUM(D34:D37) -> 280350 | E38: =SUM(E34:E37) -> 280350 | F38: =SUM(F34:F37) -> 282550 | G38: =SUM(G34:G37) -> 282550 | H38: =SUM(H34:H37) -> 284750 | I38: =SUM(I34:I37) -> 284750 | ... N38: =SUM(N34:N37) -> 3408800
A41: 2026 Actual Customer Success | B41: Jan | C41: Feb | D41: Mar | E41: Apr | F41: May | G41: Jun | H41: Jul | I41: Aug | J41: Sep | K41: Oct | L41: Nov | M41: Dec | N41: FY 2026
A42: Salaries & Wages | B42: 267000 | C42: 267000 | D42: 268000 | E42: 268000 | F42: 269000 | G42: 269000 | H42: 270000 | I42: 270000 | J42: 271000 | K42: 271000 | L42: 272000 | M42: 272000 | N42: =SUM(B42:M42) -> 3234000
A43: Employee Benefits | B43: 53400 | C43: 53400 | D43: 53600 | E43: 53600 | F43: 53800 | G43: 53800 | H43: 54000 | I43: 54000 | J43: 54200 | K43: 54200 | L43: 54400 | M43: 54400 | N43: =SUM(B43:M43) -> 646800
A44: Software & Tools | B44: 9000 | C44: 9000 | D44: 9000 | E44: 9000 | F44: 9000 | G44: 9000 | H44: 9000 | I44: 9000 | J44: 9000 | K44: 9000 | L44: 9000 | M44: 9000 | N44: =SUM(B44:M44) -> 108000
A45: Travel & Entertainment | B45: 5000 | C45: 5000 | D45: 5000 | E45: 5500 | F45: 5500 | G45: 5500 | H45: 6000 | I45: 6000 | J45: 6000 | K45: 6000 | L45: 6500 | M45: 6500 | N45: =SUM(B45:M45) -> 68500
A46: Total Customer Success Expenses | B46: =SUM(B42:B45) -> 334400 | C46: =SUM(C42:C45) -> 334400 | D46: =SUM(D42:D45) -> 335600 | E46: =SUM(E42:E45) -> 336100 | F46: =SUM(F42:F45) -> 337300 | G46: =SUM(G42:G45) -> 337300 | H46: =SUM(H42:H45) -> 339000 | I46: =SUM(I42:I45) -> 339000 | ... N46: =SUM(N42:N45) -> 4057300
A49: 2026 Actual G&A | B49: Jan | C49: Feb | D49: Mar | E49: Apr | F49: May | G49: Jun | H49: Jul | I49: Aug | J49: Sep | K49: Oct | L49: Nov | M49: Dec | N49: FY 2026
A50: Salaries & Wages | B50: 247000 | C50: 247000 | D50: 248000 | E50: 248000 | F50: 249000 | G50: 249000 | H50: 250000 | I50: 250000 | J50: 251000 | K50: 251000 | L50: 252000 | M50: 252000 | N50: =SUM(B50:M50) -> 2994000
A51: Employee Benefits | B51: 49400 | C51: 49400 | D51: 49600 | E51: 49600 | F51: 49800 | G51: 49800 | H51: 50000 | I51: 50000 | J51: 50200 | K51: 50200 | L51: 50400 | M51: 50400 | N51: =SUM(B51:M51) -> 598800
A52: Software & Tools | B52: 6750 | C52: 6750 | D52: 6750 | E52: 6750 | F52: 6750 | G52: 6750 | H52: 6750 | I52: 6750 | J52: 6750 | K52: 6750 | L52: 6750 | M52: 6750 | N52: =SUM(B52:M52) -> 81000
A53: Consulting & Professional Fees | B53: 36000 | C53: 36000 | D53: 37000 | E53: 37000 | F53: 38000 | G53: 38000 | H53: 39000 | I53: 39000 | J53: 40000 | K53: 40000 | L53: 41000 | M53: 45000 | N53: =SUM(B53:M53) -> 466000
A54: Rent & Facilities | B54: 13500 | C54: 13500 | D54: 13500 | E54: 13500 | F54: 13500 | G54: 13500 | H54: 13500 | I54: 13500 | J54: 13500 | K54: 13500 | L54: 13500 | M54: 13500 | N54: =SUM(B54:M54) -> 162000
A55: Total G&A Expenses | B55: =SUM(B50:B54) -> 352650 | C55: =SUM(C50:C54) -> 352650 | D55: =SUM(D50:D54) -> 354850 | E55: =SUM(E50:E54) -> 354850 | F55: =SUM(F50:F54) -> 357050 | G55: =SUM(G50:G54) -> 357050 | H55: =SUM(H50:H54) -> 359250 | I55: =SUM(I50:I54) -> 359250 | ... N55: =SUM(N50:N54) -> 4301800
A58: 2026 Actual Summary | B58: Jan | C58: Feb | D58: Mar | E58: Apr | F58: May | G58: Jun | H58: Jul | I58: Aug | J58: Sep | K58: Oct | L58: Nov | M58: Dec | N58: FY 2026
A59: Total Revenue | B59: =B4 -> 3650000 | C59: =C4 -> 3720000 | D59: =D4 -> 4180000 | E59: =E4 -> 4250000 | F59: =F4 -> 4300000 | G59: =G4 -> 4340000 | H59: =H4 -> 4380000 | I59: =I4 -> 4420000 | ... M59: =M4 -> 5930000 | N59: =SUM(B59:M59) -> 54050000
A61: Sales Expenses | B61: =B13 -> 822000 | C61: =C13 -> 826000 | D61: =D13 -> 853000 | E61: =E13 -> 856000 | F61: =F13 -> 865000 | G61: =G13 -> 866000 | H61: =H13 -> 875000 | I61: =I13 -> 877000 | ... M61: =M13 -> 960000 | N61: =SUM(B61:M61) -> 10529000
A62: Marketing Expenses | B62: =B22 -> 483100 | C62: =C22 -> 488100 | D62: =D22 -> 504800 | E62: =E22 -> 509800 | F62: =F22 -> 516000 | G62: =G22 -> 521000 | H62: =H22 -> 527700 | I62: =I22 -> 532700 | ... M62: =M22 -> 605600 | N62: =SUM(B62:M62) -> 6367200
A63: Engineering Expenses | B63: =B30 -> 1347500 | C63: =C30 -> 1352500 | D63: =D30 -> 1363500 | E63: =E30 -> 1368500 | F63: =F30 -> 1379500 | G63: =G30 -> 1384500 | H63: =H30 -> 1395500 | I63: =I30 -> 1400500 | ... M63: =M30 -> 1452500 | N63: =SUM(B63:M63) -> 16715000
A64: Product Expenses | B64: =B38 -> 278150 | C64: =C38 -> 278150 | D64: =D38 -> 280350 | E64: =E38 -> 280350 | F64: =F38 -> 282550 | G64: =G38 -> 282550 | H64: =H38 -> 284750 | I64: =I38 -> 284750 | ... M64: =M38 -> 294150 | N64: =SUM(B64:M64) -> 3408800
A65: Customer Success Expenses | B65: =B46 -> 334400 | C65: =C46 -> 334400 | D65: =D46 -> 335600 | E65: =E46 -> 336100 | F65: =F46 -> 337300 | G65: =G46 -> 337300 | H65: =H46 -> 339000 | I65: =I46 -> 339000 | ... M65: =M46 -> 341900 | N65: =SUM(B65:M65) -> 4057300
A66: G&A Expenses | B66: =B55 -> 352650 | C66: =C55 -> 352650 | D66: =D55 -> 354850 | E66: =E55 -> 354850 | F66: =F55 -> 357050 | G66: =G55 -> 357050 | H66: =H55 -> 359250 | I66: =I55 -> 359250 | ... M66: =M55 -> 367650 | N66: =SUM(B66:M66) -> 4301800
A67: Total Operating Expenses | B67: =SUM(B61:B66) -> 3617800 | C67: =SUM(C61:C66) -> 3631800 | D67: =SUM(D61:D66) -> 3692100 | E67: =SUM(E61:E66) -> 3705600 | F67: =SUM(F61:F66) -> 3737400 | G67: =SUM(G61:G66) -> 3748400 | H67: =SUM(H61:H66) -> 3781200 | I67: =SUM(I61:I66) -> 3793200 | ... M67: =SUM(M61:M66) -> 4021800 | N67: =SUM(B67:M67) -> 45379100
A69: Operating Profit | B69: =B59-B67 -> 32200 | C69: =C59-C67 -> 88200 | D69: =D59-D67 -> 487900 | E69: =E59-E67 -> 544400 | F69: =F59-F67 -> 562600 | G69: =G59-G67 -> 591600 | H69: =H59-H67 -> 598800 | I69: =I59-I67 -> 626800 | ... N69: =N59-N67 -> 8670900
A70: Operating Margin | B70: =B69/B59 -> 0.0088219178 | C70: =C69/C59 -> 0.023709677 | D70: =D69/D59 -> 0.11672249 | E70: =E69/E59 -> 0.12809412 | F70: =F69/F59 -> 0.13083721 | G70: =G69/G59 -> 0.13631336 | H70: =H69/H59 -> 0.13671233 | I70: =I69/I59 -> 0.14180995 | ... N70: =N69/N59 -> 0.16042368

Sheet variance_analysis
A1: January 2024 Variance Analysis | B1: Budget | C1: Actual | D1: Variance $ | E1: Variance % | F1: F / U
A2: Total Revenue | B2: ='2024_budget'!B59 -> 2800000 | C2: ='2024_actual'!B59 -> 2690000 | D2: =C2-B2 -> -110000 | E2: =D2/B2 -> -0.039285714 | F2: =IF(C2>=B2,"F","U") -> U
A3: Sales Expenses | B3: ='2024_budget'!B61 -> 655166.67 | C3: ='2024_actual'!B61 -> 627000 | D3: =C3-B3 -> -28166.667 | E3: =D3/B3 -> -0.042991605 | F3: =IF(C3<=B3,"F","U") -> F
A4: Marketing Expenses | B4: ='2024_budget'!B62 -> 367166.67 | C4: ='2024_actual'!B62 -> 375200 | D4: =C4-B4 -> 8033.3333 | E4: =D4/B4 -> 0.021879256 | F4: =IF(C4<=B4,"F","U") -> U
A5: Engineering Expenses | B5: ='2024_budget'!B63 -> 1074500 | C5: ='2024_actual'!B63 -> 1072000 | D5: =C5-B5 -> -2500 | E5: =D5/B5 -> -0.0023266636 | F5: =IF(C5<=B5,"F","U") -> F
A6: Product Expenses | B6: ='2024_budget'!B64 -> 212083.33 | C6: ='2024_actual'!B64 -> 208950 | D6: =C6-B6 -> -3133.3333 | E6: =D6/B6 -> -0.014774067 | F6: =IF(C6<=B6,"F","U") -> F
A7: Customer Success Expenses | B7: ='2024_budget'!B65 -> 267500 | C7: ='2024_actual'!B65 -> 261100 | D7: =C7-B7 -> -6400 | E7: =D7/B7 -> -0.023925234 | F7: =IF(C7<=B7,"F","U") -> F
A8: G&A Expenses | B8: ='2024_budget'!B66 -> 314583.33 | C8: ='2024_actual'!B66 -> 307950 | D8: =C8-B8 -> -6633.3333 | E8: =D8/B8 -> -0.021086093 | F8: =IF(C8<=B8,"F","U") -> F
A9: Total Operating Expenses | B9: ='2024_budget'!B67 -> 2891000 | C9: ='2024_actual'!B67 -> 2852200 | D9: =C9-B9 -> -38800 | E9: =D9/B9 -> -0.013420962 | F9: =IF(C9<=B9,"F","U") -> F
A10: Operating Profit | B10: ='2024_budget'!B69 -> -91000 | C10: ='2024_actual'!B69 -> -162200 | D10: =C10-B10 -> -71200 | E10: =D10/B10 -> 0.78241758 | F10: =IF(C10>=B10,"F","U") -> U
A11: Operating Margin | B11: ='2024_budget'!B70 -> -0.0325 | C11: ='2024_actual'!B70 -> -0.060297398 | D11: =(C11-B11)*100 -> -2.7797398 | E11: N/A | F11: =IF(C11>=B11,"F","U") -> U
A14: FY 2024 Variance Analysis | B14: Budget | C14: Actual | D14: Variance $ | E14: Variance % | F14: F / U
A15: Total Revenue | B15: ='2024_budget'!N59 -> 40000000 | C15: ='2024_actual'!N59 -> 39000000 | D15: =C15-B15 -> -1000000 | E15: =D15/B15 -> -0.025 | F15: =IF(C15>=B15,"F","U") -> U
A16: Sales Expenses | B16: ='2024_budget'!N61 -> 8150000 | C16: ='2024_actual'!N61 -> 7987000 | D16: =C16-B16 -> -163000 | E16: =D16/B16 -> -0.02 | F16: =IF(C16<=B16,"F","U") -> F
A17: Marketing Expenses | B17: ='2024_budget'!N62 -> 4790000 | C17: ='2024_actual'!N62 -> 4972400 | D17: =C17-B17 -> 182400 | E17: =D17/B17 -> 0.038079332 | F17: =IF(C17<=B17,"F","U") -> U
A18: Engineering Expenses | B18: ='2024_budget'!N63 -> 13150000 | C18: ='2024_actual'!N63 -> 13304000 | D18: =C18-B18 -> 154000 | E18: =D18/B18 -> 0.011711027 | F18: =IF(C18<=B18,"F","U") -> U
A19: Product Expenses | B19: ='2024_budget'!N64 -> 2545000 | C19: ='2024_actual'!N64 -> 2556200 | D19: =C19-B19 -> 11200 | E19: =D19/B19 -> 0.0044007859 | F19: =IF(C19<=B19,"F","U") -> U
A20: Customer Success Expenses | B20: ='2024_budget'!N65 -> 3210000 | C20: ='2024_actual'!N65 -> 3189700 | D20: =C20-B20 -> -20300 | E20: =D20/B20 -> -0.0063239875 | F20: =IF(C20<=B20,"F","U") -> F
A21: G&A Expenses | B21: ='2024_budget'!N66 -> 3775000 | C21: ='2024_actual'!N66 -> 3789400 | D21: =C21-B21 -> 14400 | E21: =D21/B21 -> 0.0038145695 | F21: =IF(C21<=B21,"F","U") -> U
A22: Total Operating Expenses | B22: ='2024_budget'!N67 -> 35620000 | C22: ='2024_actual'!N67 -> 35798700 | D22: =C22-B22 -> 178700 | E22: =D22/B22 -> 0.0050168445 | F22: =IF(C22<=B22,"F","U") -> U
A23: Operating Profit | B23: ='2024_budget'!N69 -> 4380000 | C23: ='2024_actual'!N69 -> 3201300 | D23: =C23-B23 -> -1178700 | E23: =D23/B23 -> -0.26910959 | F23: =IF(C23>=B23,"F","U") -> U
A24: Operating Margin | B24: ='2024_budget'!N70 -> 0.1095 | C24: ='2024_actual'!N70 -> 0.082084615 | D24: =(C24-B24)*100 -> -2.7415385 | E24: N/A | F24: =IF(C24>=B24,"F","U") -> U
A27: January 2025 Variance Analysis | B27: Budget | C27: Actual | D27: Variance $ | E27: Variance % | F27: F / U
A28: Total Revenue | B28: ='2025_budget'!B59 -> 3220000 | C28: ='2025_actual'!B59 -> 3160000 | D28: =C28-B28 -> -60000 | E28: =D28/B28 -> -0.01863354 | F28: =IF(C28>=B28,"F","U") -> U
A29: Sales Expenses | B29: ='2025_budget'!B61 -> 743483.33 | C29: ='2025_actual'!B61 -> 733750 | D29: =C29-B29 -> -9733.3333 | E29: =D29/B29 -> -0.013091529 | F29: =IF(C29<=B29,"F","U") -> F
A30: Marketing Expenses | B30: ='2025_budget'!B62 -> 418553.33 | C30: ='2025_actual'!B62 -> 423100 | D30: =C30-B30 -> 4546.6667 | E30: =D30/B30 -> 0.010862813 | F30: =IF(C30<=B30,"F","U") -> U
A31: Engineering Expenses | B31: ='2025_budget'!B63 -> 1204580 | C31: ='2025_actual'!B63 -> 1208000 | D31: =C31-B31 -> 3420 | E31: =D31/B31 -> 0.0028391639 | F31: =IF(C31<=B31,"F","U") -> U
A32: Product Expenses | B32: ='2025_budget'!B64 -> 248125 | C32: ='2025_actual'!B64 -> 244450 | D32: =C32-B32 -> -3675 | E32: =D32/B32 -> -0.014811083 | F32: =IF(C32<=B32,"F","U") -> F
A33: Customer Success Expenses | B33: ='2025_budget'!B65 -> 302665 | C33: ='2025_actual'!B65 -> 297150 | D33: =C33-B33 -> -5515 | E33: =D33/B33 -> -0.018221466 | F33: =IF(C33<=B33,"F","U") -> F
A34: G&A Expenses | B34: ='2025_budget'!B66 -> 336106.67 | C34: ='2025_actual'!B66 -> 331900 | D34: =C34-B34 -> -4206.6667 | E34: =D34/B34 -> -0.012515868 | F34: =IF(C34<=B34,"F","U") -> F
A35: Total Operating Expenses | B35: ='2025_budget'!B67 -> 3253513.3 | C35: ='2025_actual'!B67 -> 3238350 | D35: =C35-B35 -> -15163.333 | E35: =D35/B35 -> -0.0046606028 | F35: =IF(C35<=B35,"F","U") -> F
A36: Operating Profit | B36: ='2025_budget'!B69 -> -33513.333 | C36: ='2025_actual'!B69 -> -78350 | D36: =C36-B36 -> -44836.667 | E36: =D36/B36 -> 1.3378755 | F36: =IF(C36>=B36,"F","U") -> U
A37: Operating Margin | B37: ='2025_budget'!B70 -> -0.010407867 | C37: ='2025_actual'!B70 -> -0.024794304 | D37: =(C37-B37)*100 -> -1.4386436 | E37: N/A | F37: =IF(C37>=B37,"F","U") -> U
A40: FY 2025 Variance Analysis | B40: Budget | C40: Actual | D40: Variance $ | E40: Variance % | F40: F / U
A41: Total Revenue | B41: ='2025_budget'!N59 -> 46000000 | C41: ='2025_actual'!N59 -> 46800000 | D41: =C41-B41 -> 800000 | E41: =D41/B41 -> 0.017391304 | F41: =IF(C41>=B41,"F","U") -> F
A42: Sales Expenses | B42: ='2025_budget'!N61 -> 9253000 | C42: ='2025_actual'!N61 -> 9386000 | D42: =C42-B42 -> 133000 | E42: =D42/B42 -> 0.014373717 | F42: =IF(C42<=B42,"F","U") -> U
A43: Marketing Expenses | B43: ='2025_budget'!N62 -> 5464240 | C43: ='2025_actual'!N62 -> 5701200 | D43: =C43-B43 -> 236960 | E43: =D43/B43 -> 0.043365592 | F43: =IF(C43<=B43,"F","U") -> U
A44: Engineering Expenses | B44: ='2025_budget'!N63 -> 14749360 | C44: ='2025_actual'!N63 -> 14936000 | D44: =C44-B44 -> 186640 | E44: =D44/B44 -> 0.012654108 | F44: =IF(C44<=B44,"F","U") -> U
A45: Product Expenses | B45: ='2025_budget'!N64 -> 2977500 | C45: ='2025_actual'!N64 -> 2993800 | D45: =C45-B45 -> 16300 | E45: =D45/B45 -> 0.0054743913 | F45: =IF(C45<=B45,"F","U") -> U
A46: Customer Success Expenses | B46: ='2025_budget'!N65 -> 3631980 | C46: ='2025_actual'!N65 -> 3609300 | D46: =C46-B46 -> -22680 | E46: =D46/B46 -> -0.0062445278 | F46: =IF(C46<=B46,"F","U") -> F
A47: G&A Expenses | B47: ='2025_budget'!N66 -> 4033280 | C47: ='2025_actual'!N66 -> 4050800 | D47: =C47-B47 -> 17520 | E47: =D47/B47 -> 0.0043438591 | F47: =IF(C47<=B47,"F","U") -> U
A48: Total Operating Expenses | B48: ='2025_budget'!N67 -> 40109360 | C48: ='2025_actual'!N67 -> 40677100 | D48: =C48-B48 -> 567740 | E48: =D48/B48 -> 0.014154801 | F48: =IF(C48<=B48,"F","U") -> U
A49: Operating Profit | B49: ='2025_budget'!N69 -> 5890640 | C49: ='2025_actual'!N69 -> 6122900 | D49: =C49-B49 -> 232260 | E49: =D49/B49 -> 0.039428653 | F49: =IF(C49>=B49,"F","U") -> F
A50: Operating Margin | B50: ='2025_budget'!N70 -> 0.12805739 | C50: ='2025_actual'!N70 -> 0.1308312 | D50: =(C50-B50)*100 -> 0.27738053 | E50: N/A | F50: =IF(C50>=B50,"F","U") -> F
A53: January 2026 Variance Analysis | B53: Budget | C53: Actual | D53: Variance $ | E53: Variance % | F53: F / U
A54: Total Revenue | B54: ='2026_budget'!B59 -> 3703000 | C54: ='2026_actual'!B59 -> 3650000 | D54: =C54-B54 -> -53000 | E54: =D54/B54 -> -0.014312719 | F54: =IF(C54>=B54,"F","U") -> U
A55: Sales Expenses | B55: ='2026_budget'!B61 -> 838175 | C55: ='2026_actual'!B61 -> 822000 | D55: =C55-B55 -> -16175 | E55: =D55/B55 -> -0.019297879 | F55: =IF(C55<=B55,"F","U") -> F
A56: Marketing Expenses | B56: ='2026_budget'!B62 -> 475065.2 | C56: ='2026_actual'!B62 -> 483100 | D56: =C56-B56 -> 8034.8 | E56: =D56/B56 -> 0.016913047 | F56: =IF(C56<=B56,"F","U") -> U
A57: Engineering Expenses | B57: ='2026_budget'!B63 -> 1343036.3 | C57: ='2026_actual'!B63 -> 1347500 | D57: =C57-B57 -> 4463.7 | E57: =D57/B57 -> 0.0033235885 | F57: =IF(C57<=B57,"F","U") -> U
A58: Product Expenses | B58: ='2026_budget'!B64 -> 283797.08 | C58: ='2026_actual'!B64 -> 278150 | D58: =C58-B58 -> -5647.0833 | E58: =D58/B58 -> -0.019898313 | F58: =IF(C58<=B58,"F","U") -> F
A59: Customer Success Expenses | B59: ='2026_budget'!B65 -> 339635.4 | C59: ='2026_actual'!B65 -> 334400 | D59: =C59-B59 -> -5235.4 | E59: =D59/B59 -> -0.015414765 | F59: =IF(C59<=B59,"F","U") -> F
A60: G&A Expenses | B60: ='2026_budget'!B66 -> 358515.15 | C60: ='2026_actual'!B66 -> 352650 | D60: =C60-B60 -> -5865.15 | E60: =D60/B60 -> -0.01635956 | F60: =IF(C60<=B60,"F","U") -> F
A61: Total Operating Expenses | B61: ='2026_budget'!B67 -> 3638224.1 | C61: ='2026_actual'!B67 -> 3617800 | D61: =C61-B61 -> -20424.133 | E61: =D61/B61 -> -0.0056137645 | F61: =IF(C61<=B61,"F","U") -> F
A62: Operating Profit | B62: ='2026_budget'!B69 -> 64775.867 | C62: ='2026_actual'!B69 -> 32200 | D62: =C62-B62 -> -32575.867 | E62: =D62/B62 -> -0.50290129 | F62: =IF(C62>=B62,"F","U") -> U
A63: Operating Margin | B63: ='2026_budget'!B70 -> 0.017492808 | C63: ='2026_actual'!B70 -> 0.0088219178 | D63: =(C63-B63)*100 -> -0.86708898 | E63: N/A | F63: =IF(C63>=B63,"F","U") -> U
A66: FY 2026 Variance Analysis | B66: Budget | C66: Actual | D66: Variance $ | E66: Variance % | F66: F / U
A67: Total Revenue | B67: ='2026_budget'!N59 -> 52900000 | C67: ='2026_actual'!N59 -> 54050000 | D67: =C67-B67 -> 1150000 | E67: =D67/B67 -> 0.02173913 | F67: =IF(C67>=B67,"F","U") -> F
A68: Sales Expenses | B68: ='2026_budget'!N61 -> 10438980 | C68: ='2026_actual'!N61 -> 10529000 | D68: =C68-B68 -> 90020 | E68: =D68/B68 -> 0.0086234479 | F68: =IF(C68<=B68,"F","U") -> U
A69: Marketing Expenses | B69: ='2026_budget'!N62 -> 6208622.4 | C69: ='2026_actual'!N62 -> 6367200 | D69: =C69-B69 -> 158577.6 | E69: =D69/B69 -> 0.025541511 | F69: =IF(C69<=B69,"F","U") -> U
A70: Engineering Expenses | B70: ='2026_budget'!N63 -> 16454996 | C70: ='2026_actual'!N63 -> 16715000 | D70: =C70-B70 -> 260004.4 | E70: =D70/B70 -> 0.01580094 | F70: =IF(C70<=B70,"F","U") -> U
A71: Product Expenses | B71: ='2026_budget'!N64 -> 3405565 | C71: ='2026_actual'!N64 -> 3408800 | D71: =C71-B71 -> 3235 | E71: =D71/B71 -> 0.0009499158 | F71: =IF(C71<=B71,"F","U") -> U
A72: Customer Success Expenses | B72: ='2026_budget'!N65 -> 4075624.8 | C72: ='2026_actual'!N65 -> 4057300 | D72: =C72-B72 -> -18324.8 | E72: =D72/B72 -> -0.0044961941 | F72: =IF(C72<=B72,"F","U") -> F
A73: G&A Expenses | B73: ='2026_budget'!N66 -> 4302181.8 | C73: ='2026_actual'!N66 -> 4301800 | D73: =C73-B73 -> -381.8 | E73: =D73/B73 -> -8.8745669e-05 | F73: =IF(C73<=B73,"F","U") -> F
A74: Total Operating Expenses | B74: ='2026_budget'!N67 -> 44885970 | C74: ='2026_actual'!N67 -> 45379100 | D74: =C74-B74 -> 493130.4 | E74: =D74/B74 -> 0.010986293 | F74: =IF(C74<=B74,"F","U") -> U
A75: Operating Profit | B75: ='2026_budget'!N69 -> 8014030.4 | C75: ='2026_actual'!N69 -> 8670900 | D75: =C75-B75 -> 656869.6 | E75: =D75/B75 -> 0.08196495 | F75: =IF(C75>=B75,"F","U") -> F
A76: Operating Margin | B76: ='2026_budget'!N70 -> 0.15149396 | C76: ='2026_actual'!N70 -> 0.16042368 | D76: =(C76-B76)*100 -> 0.89297234 | E76: N/A | F76: =IF(C76>=B76,"F","U") -> F
A79: Year | B79: Metric | C79: Variance $ | D79: F / U | E79: Management Commentary
A80: 2024 | B80: Revenue | C80: =D15 -> -1000000 | D80: =F15 -> U | E80: Subscription revenue finished below plan due to slower customer acquisition in the first half.
A81: 2024 | B81: Sales | C81: =D16 -> -163000 | D81: =F16 -> F | E81: Sales expenses finished below budget, reflecting lower-than-planned spending and subscription-driven commissions.
A82: 2024 | B82: Marketing | C82: =D17 -> 182400 | D82: =F17 -> U | E82: Marketing spend exceeded budget as management increased investment to support customer acquisition.
A83: 2024 | B83: Engineering | C83: =D18 -> 154000 | D83: =F18 -> U | E83: Engineering exceeded budget primarily due to higher cloud and hosting costs.
A84: 2024 | B84: Operating Profit | C84: =D23 -> -1178700 | D84: =F23 -> U | E84: Revenue underperformance and higher Marketing and Engineering costs drove operating profit below plan.
A85: 2025 | B85: Revenue | C85: =D41 -> 800000 | D85: =F41 -> F | E85: Stronger subscription demand drove revenue above budget.
A86: 2025 | B86: Sales | C86: =D42 -> 133000 | D86: =F42 -> U | E86: Sales expenses exceeded budget as spending increased to support stronger customer growth.
A87: 2025 | B87: Marketing | C87: =D43 -> 236960 | D87: =F43 -> U | E87: Marketing investment remained above plan to support continued revenue growth.
A88: 2025 | B88: Engineering | C88: =D44 -> 186640 | D88: =F44 -> U | E88: Engineering remained above budget due to continued cloud-cost pressure.
A89: 2025 | B89: Operating Profit | C89: =D49 -> 232260 | D89: =F49 -> F | E89: Revenue outperformance more than offset higher operating expenses, resulting in profit above plan.
A90: 2026 | B90: Revenue | C90: =D67 -> 1150000 | D90: =F67 -> F | E90: Strong subscription growth drove revenue $1.15M above budget.
A91: 2026 | B91: Sales | C91: =D68 -> 90020 | D91: =F68 -> U | E91: Sales expenses exceeded budget as the company supported higher-than-planned revenue growth.
A92: 2026 | B92: Marketing | C92: =D69 -> 158577.6 | D92: =F69 -> U | E92: Marketing spending remained above plan as the company continued investing in growth.
A93: 2026 | B93: Engineering | C93: =D70 -> 260004.4 | D93: =F70 -> U | E93: Engineering was the largest departmental overspend, driven by higher infrastructure and cloud costs.
A94: 2026 | B94: Operating Profit | C94: =D75 -> 656869.6 | D94: =F75 -> F | E94: Revenue outperformance more than offset higher operating expenses, driving profit $657K above budget.

Sheet tableau_data
A1: Date | B1: Year | C1: Month | D1: Department | E1: Category | F1: Budget | G1: Actual | H1: Variance $ | I1: Variance % | J1: F / U
A2: 45292 | B2: 2024 | C2: Jan | D2: Company | E2: Total Revenue | F2: {=_xlfn.SWITCH(B2, 2024,INDEX('2024_budget'!$B$59:$M$69,MATCH(E2,'2024_budget'!$A$59:$A$69,0),MATCH(C2,'2024_budget'!$B$58:$M$58,0)), 2025,INDEX('2025_budget'!$B$59:$M$69,MATCH(E2,'2025_budget'!$A$59:$A$69,0),MATCH(C2,'2025_budget'!$B$58:$M$58,0)), 2026,INDEX('2026_budget'!$B$59:$M$69,MATCH(E2,'2026_budget'!$A$59:$A$69,0),MATCH(C2,'2026_budget'!$B$58:$M$58,0)) )} -> 2800000 | G2: {=_xlfn.SWITCH(B2, 2024,INDEX('2024_actual'!$B$59:$M$69,MATCH(E2,'2024_actual'!$A$59:$A$69,0),MATCH(C2,'2024_actual'!$B$58:$M$58,0)), 2025,INDEX('2025_actual'!$B$59:$M$69,MATCH(E2,'2025_actual'!$A$59:$A$69,0),MATCH(C2,'2025_actual'!$B$58:$M$58,0)), 2026,INDEX('2026_actual'!$B$59:$M$69,MATCH(E2,'2026_actual'!$A$59:$A$69,0),MATCH(C2,'2026_actual'!$B$58:$M$58,0)) )} -> 2690000 | H2: =G2-F2 -> -110000 | I2: =IF(AND(E2="Operating Profit",F2<=0),NA(),IFERROR(H2/F2,0)) -> -0.039285714 | J2: =IF(G2>=F2,"F","U") -> U
A3: 45292 | B3: 2024 | C3: Jan | D3: Sales | E3: Sales Expenses | F3: {=_xlfn.SWITCH(B3, 2024,INDEX('2024_budget'!$B$59:$M$69,MATCH(E3,'2024_budget'!$A$59:$A$69,0),MATCH(C3,'2024_budget'!$B$58:$M$58,0)), 2025,INDEX('2025_budget'!$B$59:$M$69,MATCH(E3,'2025_budget'!$A$59:$A$69,0),MATCH(C3,'2025_budget'!$B$58:$M$58,0)), 2026,INDEX('2026_budget'!$B$59:$M$69,MATCH(E3,'2026_budget'!$A$59:$A$69,0),MATCH(C3,'2026_budget'!$B$58:$M$58,0)) )} -> 655166.67 | G3: {=_xlfn.SWITCH(B3, 2024,INDEX('2024_actual'!$B$59:$M$69,MATCH(E3,'2024_actual'!$A$59:$A$69,0),MATCH(C3,'2024_actual'!$B$58:$M$58,0)), 2025,INDEX('2025_actual'!$B$59:$M$69,MATCH(E3,'2025_actual'!$A$59:$A$69,0),MATCH(C3,'2025_actual'!$B$58:$M$58,0)), 2026,INDEX('2026_actual'!$B$59:$M$69,MATCH(E3,'2026_actual'!$A$59:$A$69,0),MATCH(C3,'2026_actual'!$B$58:$M$58,0)) )} -> 627000 | H3: =G3-F3 -> -28166.667 | I3: =IF(AND(E3="Operating Profit",F3<=0),NA(),IFERROR(H3/F3,0)) -> -0.042991605 | J3: =IF(G3<=F3,"F","U") -> F
A4: 45292 | B4: 2024 | C4: Jan | D4: Marketing | E4: Marketing Expenses | F4: {=_xlfn.SWITCH(B4, 2024,INDEX('2024_budget'!$B$59:$M$69,MATCH(E4,'2024_budget'!$A$59:$A$69,0),MATCH(C4,'2024_budget'!$B$58:$M$58,0)), 2025,INDEX('2025_budget'!$B$59:$M$69,MATCH(E4,'2025_budget'!$A$59:$A$69,0),MATCH(C4,'2025_budget'!$B$58:$M$58,0)), 2026,INDEX('2026_budget'!$B$59:$M$69,MATCH(E4,'2026_budget'!$A$59:$A$69,0),MATCH(C4,'2026_budget'!$B$58:$M$58,0)) )} -> 367166.67 | G4: {=_xlfn.SWITCH(B4, 2024,INDEX('2024_actual'!$B$59:$M$69,MATCH(E4,'2024_actual'!$A$59:$A$69,0),MATCH(C4,'2024_actual'!$B$58:$M$58,0)), 2025,INDEX('2025_actual'!$B$59:$M$69,MATCH(E4,'2025_actual'!$A$59:$A$69,0),MATCH(C4,'2025_actual'!$B$58:$M$58,0)), 2026,INDEX('2026_actual'!$B$59:$M$69,MATCH(E4,'2026_actual'!$A$59:$A$69,0),MATCH(C4,'2026_actual'!$B$58:$M$58,0)) )} -> 375200 | H4: =G4-F4 -> 8033.3333 | I4: =IF(AND(E4="Operating Profit",F4<=0),NA(),IFERROR(H4/F4,0)) -> 0.021879256 | J4: =IF(G4<=F4,"F","U") -> U
A5: 45292 | B5: 2024 | C5: Jan | D5: Engineering | E5: Engineering Expenses | F5: {=_xlfn.SWITCH(B5, 2024,INDEX('2024_budget'!$B$59:$M$69,MATCH(E5,'2024_budget'!$A$59:$A$69,0),MATCH(C5,'2024_budget'!$B$58:$M$58,0)), 2025,INDEX('2025_budget'!$B$59:$M$69,MATCH(E5,'2025_budget'!$A$59:$A$69,0),MATCH(C5,'2025_budget'!$B$58:$M$58,0)), 2026,INDEX('2026_budget'!$B$59:$M$69,MATCH(E5,'2026_budget'!$A$59:$A$69,0),MATCH(C5,'2026_budget'!$B$58:$M$58,0)) )} -> 1074500 | G5: {=_xlfn.SWITCH(B5, 2024,INDEX('2024_actual'!$B$59:$M$69,MATCH(E5,'2024_actual'!$A$59:$A$69,0),MATCH(C5,'2024_actual'!$B$58:$M$58,0)), 2025,INDEX('2025_actual'!$B$59:$M$69,MATCH(E5,'2025_actual'!$A$59:$A$69,0),MATCH(C5,'2025_actual'!$B$58:$M$58,0)), 2026,INDEX('2026_actual'!$B$59:$M$69,MATCH(E5,'2026_actual'!$A$59:$A$69,0),MATCH(C5,'2026_actual'!$B$58:$M$58,0)) )} -> 1072000 | H5: =G5-F5 -> -2500 | I5: =IF(AND(E5="Operating Profit",F5<=0),NA(),IFERROR(H5/F5,0)) -> -0.0023266636 | J5: =IF(G5<=F5,"F","U") -> F
A6: 45292 | B6: 2024 | C6: Jan | D6: Product | E6: Product Expenses | F6: {=_xlfn.SWITCH(B6, 2024,INDEX('2024_budget'!$B$59:$M$69,MATCH(E6,'2024_budget'!$A$59:$A$69,0),MATCH(C6,'2024_budget'!$B$58:$M$58,0)), 2025,INDEX('2025_budget'!$B$59:$M$69,MATCH(E6,'2025_budget'!$A$59:$A$69,0),MATCH(C6,'2025_budget'!$B$58:$M$58,0)), 2026,INDEX('2026_budget'!$B$59:$M$69,MATCH(E6,'2026_budget'!$A$59:$A$69,0),MATCH(C6,'2026_budget'!$B$58:$M$58,0)) )} -> 212083.33 | G6: {=_xlfn.SWITCH(B6, 2024,INDEX('2024_actual'!$B$59:$M$69,MATCH(E6,'2024_actual'!$A$59:$A$69,0),MATCH(C6,'2024_actual'!$B$58:$M$58,0)), 2025,INDEX('2025_actual'!$B$59:$M$69,MATCH(E6,'2025_actual'!$A$59:$A$69,0),MATCH(C6,'2025_actual'!$B$58:$M$58,0)), 2026,INDEX('2026_actual'!$B$59:$M$69,MATCH(E6,'2026_actual'!$A$59:$A$69,0),MATCH(C6,'2026_actual'!$B$58:$M$58,0)) )} -> 208950 | H6: =G6-F6 -> -3133.3333 | I6: =IF(AND(E6="Operating Profit",F6<=0),NA(),IFERROR(H6/F6,0)) -> -0.014774067 | J6: =IF(G6<=F6,"F","U") -> F
A7: 45292 | B7: 2024 | C7: Jan | D7: Customer Success | E7: Customer Success Expenses | F7: {=_xlfn.SWITCH(B7, 2024,INDEX('2024_budget'!$B$59:$M$69,MATCH(E7,'2024_budget'!$A$59:$A$69,0),MATCH(C7,'2024_budget'!$B$58:$M$58,0)), 2025,INDEX('2025_budget'!$B$59:$M$69,MATCH(E7,'2025_budget'!$A$59:$A$69,0),MATCH(C7,'2025_budget'!$B$58:$M$58,0)), 2026,INDEX('2026_budget'!$B$59:$M$69,MATCH(E7,'2026_budget'!$A$59:$A$69,0),MATCH(C7,'2026_budget'!$B$58:$M$58,0)) )} -> 267500 | G7: {=_xlfn.SWITCH(B7, 2024,INDEX('2024_actual'!$B$59:$M$69,MATCH(E7,'2024_actual'!$A$59:$A$69,0),MATCH(C7,'2024_actual'!$B$58:$M$58,0)), 2025,INDEX('2025_actual'!$B$59:$M$69,MATCH(E7,'2025_actual'!$A$59:$A$69,0),MATCH(C7,'2025_actual'!$B$58:$M$58,0)), 2026,INDEX('2026_actual'!$B$59:$M$69,MATCH(E7,'2026_actual'!$A$59:$A$69,0),MATCH(C7,'2026_actual'!$B$58:$M$58,0)) )} -> 261100 | H7: =G7-F7 -> -6400 | I7: =IF(AND(E7="Operating Profit",F7<=0),NA(),IFERROR(H7/F7,0)) -> -0.023925234 | J7: =IF(G7<=F7,"F","U") -> F
A8: 45292 | B8: 2024 | C8: Jan | D8: G&A | E8: G&A Expenses | F8: {=_xlfn.SWITCH(B8, 2024,INDEX('2024_budget'!$B$59:$M$69,MATCH(E8,'2024_budget'!$A$59:$A$69,0),MATCH(C8,'2024_budget'!$B$58:$M$58,0)), 2025,INDEX('2025_budget'!$B$59:$M$69,MATCH(E8,'2025_budget'!$A$59:$A$69,0),MATCH(C8,'2025_budget'!$B$58:$M$58,0)), 2026,INDEX('2026_budget'!$B$59:$M$69,MATCH(E8,'2026_budget'!$A$59:$A$69,0),MATCH(C8,'2026_budget'!$B$58:$M$58,0)) )} -> 314583.33 | G8: {=_xlfn.SWITCH(B8, 2024,INDEX('2024_actual'!$B$59:$M$69,MATCH(E8,'2024_actual'!$A$59:$A$69,0),MATCH(C8,'2024_actual'!$B$58:$M$58,0)), 2025,INDEX('2025_actual'!$B$59:$M$69,MATCH(E8,'2025_actual'!$A$59:$A$69,0),MATCH(C8,'2025_actual'!$B$58:$M$58,0)), 2026,INDEX('2026_actual'!$B$59:$M$69,MATCH(E8,'2026_actual'!$A$59:$A$69,0),MATCH(C8,'2026_actual'!$B$58:$M$58,0)) )} -> 307950 | H8: =G8-F8 -> -6633.3333 | I8: =IF(AND(E8="Operating Profit",F8<=0),NA(),IFERROR(H8/F8,0)) -> -0.021086093 | J8: =IF(G8<=F8,"F","U") -> F
A9: 45292 | B9: 2024 | C9: Jan | D9: Company | E9: Total Operating Expenses | F9: {=_xlfn.SWITCH(B9, 2024,INDEX('2024_budget'!$B$59:$M$69,MATCH(E9,'2024_budget'!$A$59:$A$69,0),MATCH(C9,'2024_budget'!$B$58:$M$58,0)), 2025,INDEX('2025_budget'!$B$59:$M$69,MATCH(E9,'2025_budget'!$A$59:$A$69,0),MATCH(C9,'2025_budget'!$B$58:$M$58,0)), 2026,INDEX('2026_budget'!$B$59:$M$69,MATCH(E9,'2026_budget'!$A$59:$A$69,0),MATCH(C9,'2026_budget'!$B$58:$M$58,0)) )} -> 2891000 | G9: {=_xlfn.SWITCH(B9, 2024,INDEX('2024_actual'!$B$59:$M$69,MATCH(E9,'2024_actual'!$A$59:$A$69,0),MATCH(C9,'2024_actual'!$B$58:$M$58,0)), 2025,INDEX('2025_actual'!$B$59:$M$69,MATCH(E9,'2025_actual'!$A$59:$A$69,0),MATCH(C9,'2025_actual'!$B$58:$M$58,0)), 2026,INDEX('2026_actual'!$B$59:$M$69,MATCH(E9,'2026_actual'!$A$59:$A$69,0),MATCH(C9,'2026_actual'!$B$58:$M$58,0)) )} -> 2852200 | H9: =G9-F9 -> -38800 | I9: =IF(AND(E9="Operating Profit",F9<=0),NA(),IFERROR(H9/F9,0)) -> -0.013420962 | J9: =IF(G9<=F9,"F","U") -> F
A10: 45292 | B10: 2024 | C10: Jan | D10: Company | E10: Operating Profit | F10: {=_xlfn.SWITCH(B10, 2024,INDEX('2024_budget'!$B$59:$M$69,MATCH(E10,'2024_budget'!$A$59:$A$69,0),MATCH(C10,'2024_budget'!$B$58:$M$58,0)), 2025,INDEX('2025_budget'!$B$59:$M$69,MATCH(E10,'2025_budget'!$A$59:$A$69,0),MATCH(C10,'2025_budget'!$B$58:$M$58,0)), 2026,INDEX('2026_budget'!$B$59:$M$69,MATCH(E10,'2026_budget'!$A$59:$A$69,0),MATCH(C10,'2026_budget'!$B$58:$M$58,0)) )} -> -91000 | G10: {=_xlfn.SWITCH(B10, 2024,INDEX('2024_actual'!$B$59:$M$69,MATCH(E10,'2024_actual'!$A$59:$A$69,0),MATCH(C10,'2024_actual'!$B$58:$M$58,0)), 2025,INDEX('2025_actual'!$B$59:$M$69,MATCH(E10,'2025_actual'!$A$59:$A$69,0),MATCH(C10,'2025_actual'!$B$58:$M$58,0)), 2026,INDEX('2026_actual'!$B$59:$M$69,MATCH(E10,'2026_actual'!$A$59:$A$69,0),MATCH(C10,'2026_actual'!$B$58:$M$58,0)) )} -> -162200 | H10: =G10-F10 -> -71200 | I10: =IF(AND(E10="Operating Profit",F10<=0),NA(),IFERROR(H10/F10,0)) -> #N/A | J10: =IF(G10>=F10,"F","U") -> U
A11: 45323 | B11: 2024 | C11: Feb | D11: Company | E11: Total Revenue | F11: {=_xlfn.SWITCH(B11, 2024,INDEX('2024_budget'!$B$59:$M$69,MATCH(E11,'2024_budget'!$A$59:$A$69,0),MATCH(C11,'2024_budget'!$B$58:$M$58,0)), 2025,INDEX('2025_budget'!$B$59:$M$69,MATCH(E11,'2025_budget'!$A$59:$A$69,0),MATCH(C11,'2025_budget'!$B$58:$M$58,0)), 2026,INDEX('2026_budget'!$B$59:$M$69,MATCH(E11,'2026_budget'!$A$59:$A$69,0),MATCH(C11,'2026_budget'!$B$58:$M$58,0)) )} -> 2800000 | G11: {=_xlfn.SWITCH(B11, 2024,INDEX('2024_actual'!$B$59:$M$69,MATCH(E11,'2024_actual'!$A$59:$A$69,0),MATCH(C11,'2024_actual'!$B$58:$M$58,0)), 2025,INDEX('2025_actual'!$B$59:$M$69,MATCH(E11,'2025_actual'!$A$59:$A$69,0),MATCH(C11,'2025_actual'!$B$58:$M$58,0)), 2026,INDEX('2026_actual'!$B$59:$M$69,MATCH(E11,'2026_actual'!$A$59:$A$69,0),MATCH(C11,'2026_actual'!$B$58:$M$58,0)) )} -> 2715000 | H11: =G11-F11 -> -85000 | I11: =IF(AND(E11="Operating Profit",F11<=0),NA(),IFERROR(H11/F11,0)) -> -0.030357143 | J11: =IF(G11>=F11,"F","U") -> U
A12: 45323 | B12: 2024 | C12: Feb | D12: Sales | E12: Sales Expenses | F12: {=_xlfn.SWITCH(B12, 2024,INDEX('2024_budget'!$B$59:$M$69,MATCH(E12,'2024_budget'!$A$59:$A$69,0),MATCH(C12,'2024_budget'!$B$58:$M$58,0)), 2025,INDEX('2025_budget'!$B$59:$M$69,MATCH(E12,'2025_budget'!$A$59:$A$69,0),MATCH(C12,'2025_budget'!$B$58:$M$58,0)), 2026,INDEX('2026_budget'!$B$59:$M$69,MATCH(E12,'2026_budget'!$A$59:$A$69,0),MATCH(C12,'2026_budget'!$B$58:$M$58,0)) )} -> 655166.67 | G12: {=_xlfn.SWITCH(B12, 2024,INDEX('2024_actual'!$B$59:$M$69,MATCH(E12,'2024_actual'!$A$59:$A$69,0),MATCH(C12,'2024_actual'!$B$58:$M$58,0)), 2025,INDEX('2025_actual'!$B$59:$M$69,MATCH(E12,'2025_actual'!$A$59:$A$69,0),MATCH(C12,'2025_actual'!$B$58:$M$58,0)), 2026,INDEX('2026_actual'!$B$59:$M$69,MATCH(E12,'2026_actual'!$A$59:$A$69,0),MATCH(C12,'2026_actual'!$B$58:$M$58,0)) )} -> 629000 | H12: =G12-F12 -> -26166.667 | I12: =IF(AND(E12="Operating Profit",F12<=0),NA(),IFERROR(H12/F12,0)) -> -0.039938947 | J12: =IF(G12<=F12,"F","U") -> F
A13: 45323 | B13: 2024 | C13: Feb | D13: Marketing | E13: Marketing Expenses | F13: {=_xlfn.SWITCH(B13, 2024,INDEX('2024_budget'!$B$59:$M$69,MATCH(E13,'2024_budget'!$A$59:$A$69,0),MATCH(C13,'2024_budget'!$B$58:$M$58,0)), 2025,INDEX('2025_budget'!$B$59:$M$69,MATCH(E13,'2025_budget'!$A$59:$A$69,0),MATCH(C13,'2025_budget'!$B$58:$M$58,0)), 2026,INDEX('2026_budget'!$B$59:$M$69,MATCH(E13,'2026_budget'!$A$59:$A$69,0),MATCH(C13,'2026_budget'!$B$58:$M$58,0)) )} -> 367166.67 | G13: {=_xlfn.SWITCH(B13, 2024,INDEX('2024_actual'!$B$59:$M$69,MATCH(E13,'2024_actual'!$A$59:$A$69,0),MATCH(C13,'2024_actual'!$B$58:$M$58,0)), 2025,INDEX('2025_actual'!$B$59:$M$69,MATCH(E13,'2025_actual'!$A$59:$A$69,0),MATCH(C13,'2025_actual'!$B$58:$M$58,0)), 2026,INDEX('2026_actual'!$B$59:$M$69,MATCH(E13,'2026_actual'!$A$59:$A$69,0),MATCH(C13,'2026_actual'!$B$58:$M$58,0)) )} -> 380200 | H13: =G13-F13 -> 13033.333 | I13: =IF(AND(E13="Operating Profit",F13<=0),NA(),IFERROR(H13/F13,0)) -> 0.035497049 | J13: =IF(G13<=F13,"F","U") -> U
A14: 45323 | B14: 2024 | C14: Feb | D14: Engineering | E14: Engineering Expenses | F14: {=_xlfn.SWITCH(B14, 2024,INDEX('2024_budget'!$B$59:$M$69,MATCH(E14,'2024_budget'!$A$59:$A$69,0),MATCH(C14,'2024_budget'!$B$58:$M$58,0)), 2025,INDEX('2025_budget'!$B$59:$M$69,MATCH(E14,'2025_budget'!$A$59:$A$69,0),MATCH(C14,'2025_budget'!$B$58:$M$58,0)), 2026,INDEX('2026_budget'!$B$59:$M$69,MATCH(E14,'2026_budget'!$A$59:$A$69,0),MATCH(C14,'2026_budget'!$B$58:$M$58,0)) )} -> 1074500 | G14: {=_xlfn.SWITCH(B14, 2024,INDEX('2024_actual'!$B$59:$M$69,MATCH(E14,'2024_actual'!$A$59:$A$69,0),MATCH(C14,'2024_actual'!$B$58:$M$58,0)), 2025,INDEX('2025_actual'!$B$59:$M$69,MATCH(E14,'2025_actual'!$A$59:$A$69,0),MATCH(C14,'2025_actual'!$B$58:$M$58,0)), 2026,INDEX('2026_actual'!$B$59:$M$69,MATCH(E14,'2026_actual'!$A$59:$A$69,0),MATCH(C14,'2026_actual'!$B$58:$M$58,0)) )} -> 1077000 | H14: =G14-F14 -> 2500 | I14: =IF(AND(E14="Operating Profit",F14<=0),NA(),IFERROR(H14/F14,0)) -> 0.0023266636 | J14: =IF(G14<=F14,"F","U") -> U
A15: 45323 | B15: 2024 | C15: Feb | D15: Product | E15: Product Expenses | F15: {=_xlfn.SWITCH(B15, 2024,INDEX('2024_budget'!$B$59:$M$69,MATCH(E15,'2024_budget'!$A$59:$A$69,0),MATCH(C15,'2024_budget'!$B$58:$M$58,0)), 2025,INDEX('2025_budget'!$B$59:$M$69,MATCH(E15,'2025_budget'!$A$59:$A$69,0),MATCH(C15,'2025_budget'!$B$58:$M$58,0)), 2026,INDEX('2026_budget'!$B$59:$M$69,MATCH(E15,'2026_budget'!$A$59:$A$69,0),MATCH(C15,'2026_budget'!$B$58:$M$58,0)) )} -> 212083.33 | G15: {=_xlfn.SWITCH(B15, 2024,INDEX('2024_actual'!$B$59:$M$69,MATCH(E15,'2024_actual'!$A$59:$A$69,0),MATCH(C15,'2024_actual'!$B$58:$M$58,0)), 2025,INDEX('2025_actual'!$B$59:$M$69,MATCH(E15,'2025_actual'!$A$59:$A$69,0),MATCH(C15,'2025_actual'!$B$58:$M$58,0)), 2026,INDEX('2026_actual'!$B$59:$M$69,MATCH(E15,'2026_actual'!$A$59:$A$69,0),MATCH(C15,'2026_actual'!$B$58:$M$58,0)) )} -> 208950 | H15: =G15-F15 -> -3133.3333 | I15: =IF(AND(E15="Operating Profit",F15<=0),NA(),IFERROR(H15/F15,0)) -> -0.014774067 | J15: =IF(G15<=F15,"F","U") -> F
A16: 45323 | B16: 2024 | C16: Feb | D16: Customer Success | E16: Customer Success Expenses | F16: {=_xlfn.SWITCH(B16, 2024,INDEX('2024_budget'!$B$59:$M$69,MATCH(E16,'2024_budget'!$A$59:$A$69,0),MATCH(C16,'2024_budget'!$B$58:$M$58,0)), 2025,INDEX('2025_budget'!$B$59:$M$69,MATCH(E16,'2025_budget'!$A$59:$A$69,0),MATCH(C16,'2025_budget'!$B$58:$M$58,0)), 2026,INDEX('2026_budget'!$B$59:$M$69,MATCH(E16,'2026_budget'!$A$59:$A$69,0),MATCH(C16,'2026_budget'!$B$58:$M$58,0)) )} -> 267500 | G16: {=_xlfn.SWITCH(B16, 2024,INDEX('2024_actual'!$B$59:$M$69,MATCH(E16,'2024_actual'!$A$59:$A$69,0),MATCH(C16,'2024_actual'!$B$58:$M$58,0)), 2025,INDEX('2025_actual'!$B$59:$M$69,MATCH(E16,'2025_actual'!$A$59:$A$69,0),MATCH(C16,'2025_actual'!$B$58:$M$58,0)), 2026,INDEX('2026_actual'!$B$59:$M$69,MATCH(E16,'2026_actual'!$A$59:$A$69,0),MATCH(C16,'2026_actual'!$B$58:$M$58,0)) )} -> 261100 | H16: =G16-F16 -> -6400 | I16: =IF(AND(E16="Operating Profit",F16<=0),NA(),IFERROR(H16/F16,0)) -> -0.023925234 | J16: =IF(G16<=F16,"F","U") -> F
A17: 45323 | B17: 2024 | C17: Feb | D17: G&A | E17: G&A Expenses | F17: {=_xlfn.SWITCH(B17, 2024,INDEX('2024_budget'!$B$59:$M$69,MATCH(E17,'2024_budget'!$A$59:$A$69,0),MATCH(C17,'2024_budget'!$B$58:$M$58,0)), 2025,INDEX('2025_budget'!$B$59:$M$69,MATCH(E17,'2025_budget'!$A$59:$A$69,0),MATCH(C17,'2025_budget'!$B$58:$M$58,0)), 2026,INDEX('2026_budget'!$B$59:$M$69,MATCH(E17,'2026_budget'!$A$59:$A$69,0),MATCH(C17,'2026_budget'!$B$58:$M$58,0)) )} -> 314583.33 | G17: {=_xlfn.SWITCH(B17, 2024,INDEX('2024_actual'!$B$59:$M$69,MATCH(E17,'2024_actual'!$A$59:$A$69,0),MATCH(C17,'2024_actual'!$B$58:$M$58,0)), 2025,INDEX('2025_actual'!$B$59:$M$69,MATCH(E17,'2025_actual'!$A$59:$A$69,0),MATCH(C17,'2025_actual'!$B$58:$M$58,0)), 2026,INDEX('2026_actual'!$B$59:$M$69,MATCH(E17,'2026_actual'!$A$59:$A$69,0),MATCH(C17,'2026_actual'!$B$58:$M$58,0)) )} -> 307950 | H17: =G17-F17 -> -6633.3333 | I17: =IF(AND(E17="Operating Profit",F17<=0),NA(),IFERROR(H17/F17,0)) -> -0.021086093 | J17: =IF(G17<=F17,"F","U") -> F
A18: 45323 | B18: 2024 | C18: Feb | D18: Company | E18: Total Operating Expenses | F18: {=_xlfn.SWITCH(B18, 2024,INDEX('2024_budget'!$B$59:$M$69,MATCH(E18,'2024_budget'!$A$59:$A$69,0),MATCH(C18,'2024_budget'!$B$58:$M$58,0)), 2025,INDEX('2025_budget'!$B$59:$M$69,MATCH(E18,'2025_budget'!$A$59:$A$69,0),MATCH(C18,'2025_budget'!$B$58:$M$58,0)), 2026,INDEX('2026_budget'!$B$59:$M$69,MATCH(E18,'2026_budget'!$A$59:$A$69,0),MATCH(C18,'2026_budget'!$B$58:$M$58,0)) )} -> 2891000 | G18: {=_xlfn.SWITCH(B18, 2024,INDEX('2024_actual'!$B$59:$M$69,MATCH(E18,'2024_actual'!$A$59:$A$69,0),MATCH(C18,'2024_actual'!$B$58:$M$58,0)), 2025,INDEX('2025_actual'!$B$59:$M$69,MATCH(E18,'2025_actual'!$A$59:$A$69,0),MATCH(C18,'2025_actual'!$B$58:$M$58,0)), 2026,INDEX('2026_actual'!$B$59:$M$69,MATCH(E18,'2026_actual'!$A$59:$A$69,0),MATCH(C18,'2026_actual'!$B$58:$M$58,0)) )} -> 2864200 | H18: =G18-F18 -> -26800 | I18: =IF(AND(E18="Operating Profit",F18<=0),NA(),IFERROR(H18/F18,0)) -> -0.0092701487 | J18: =IF(G18<=F18,"F","U") -> F
A19: 45323 | B19: 2024 | C19: Feb | D19: Company | E19: Operating Profit | F19: {=_xlfn.SWITCH(B19, 2024,INDEX('2024_budget'!$B$59:$M$69,MATCH(E19,'2024_budget'!$A$59:$A$69,0),MATCH(C19,'2024_budget'!$B$58:$M$58,0)), 2025,INDEX('2025_budget'!$B$59:$M$69,MATCH(E19,'2025_budget'!$A$59:$A$69,0),MATCH(C19,'2025_budget'!$B$58:$M$58,0)), 2026,INDEX('2026_budget'!$B$59:$M$69,MATCH(E19,'2026_budget'!$A$59:$A$69,0),MATCH(C19,'2026_budget'!$B$58:$M$58,0)) )} -> -91000 | G19: {=_xlfn.SWITCH(B19, 2024,INDEX('2024_actual'!$B$59:$M$69,MATCH(E19,'2024_actual'!$A$59:$A$69,0),MATCH(C19,'2024_actual'!$B$58:$M$58,0)), 2025,INDEX('2025_actual'!$B$59:$M$69,MATCH(E19,'2025_actual'!$A$59:$A$69,0),MATCH(C19,'2025_actual'!$B$58:$M$58,0)), 2026,INDEX('2026_actual'!$B$59:$M$69,MATCH(E19,'2026_actual'!$A$59:$A$69,0),MATCH(C19,'2026_actual'!$B$58:$M$58,0)) )} -> -149200 | H19: =G19-F19 -> -58200 | I19: =IF(AND(E19="Operating Profit",F19<=0),NA(),IFERROR(H19/F19,0)) -> #N/A | J19: =IF(G19>=F19,"F","U") -> U
A20: 45352 | B20: 2024 | C20: Mar | D20: Company | E20: Total Revenue | F20: {=_xlfn.SWITCH(B20, 2024,INDEX('2024_budget'!$B$59:$M$69,MATCH(E20,'2024_budget'!$A$59:$A$69,0),MATCH(C20,'2024_budget'!$B$58:$M$58,0)), 2025,INDEX('2025_budget'!$B$59:$M$69,MATCH(E20,'2025_budget'!$A$59:$A$69,0),MATCH(C20,'2025_budget'!$B$58:$M$58,0)), 2026,INDEX('2026_budget'!$B$59:$M$69,MATCH(E20,'2026_budget'!$A$59:$A$69,0),MATCH(C20,'2026_budget'!$B$58:$M$58,0)) )} -> 3200000 | G20: {=_xlfn.SWITCH(B20, 2024,INDEX('2024_actual'!$B$59:$M$69,MATCH(E20,'2024_actual'!$A$59:$A$69,0),MATCH(C20,'2024_actual'!$B$58:$M$58,0)), 2025,INDEX('2025_actual'!$B$59:$M$69,MATCH(E20,'2025_actual'!$A$59:$A$69,0),MATCH(C20,'2025_actual'!$B$58:$M$58,0)), 2026,INDEX('2026_actual'!$B$59:$M$69,MATCH(E20,'2026_actual'!$A$59:$A$69,0),MATCH(C20,'2026_actual'!$B$58:$M$58,0)) )} -> 3025000 | H20: =G20-F20 -> -175000 | I20: =IF(AND(E20="Operating Profit",F20<=0),NA(),IFERROR(H20/F20,0)) -> -0.0546875 | J20: =IF(G20>=F20,"F","U") -> U
A21: 45352 | B21: 2024 | C21: Mar | D21: Sales | E21: Sales Expenses | F21: {=_xlfn.SWITCH(B21, 2024,INDEX('2024_budget'!$B$59:$M$69,MATCH(E21,'2024_budget'!$A$59:$A$69,0),MATCH(C21,'2024_budget'!$B$58:$M$58,0)), 2025,INDEX('2025_budget'!$B$59:$M$69,MATCH(E21,'2025_budget'!$A$59:$A$69,0),MATCH(C21,'2025_budget'!$B$58:$M$58,0)), 2026,INDEX('2026_budget'!$B$59:$M$69,MATCH(E21,'2026_budget'!$A$59:$A$69,0),MATCH(C21,'2026_budget'!$B$58:$M$58,0)) )} -> 673166.67 | G21: {=_xlfn.SWITCH(B21, 2024,INDEX('2024_actual'!$B$59:$M$69,MATCH(E21,'2024_actual'!$A$59:$A$69,0),MATCH(C21,'2024_actual'!$B$58:$M$58,0)), 2025,INDEX('2025_actual'!$B$59:$M$69,MATCH(E21,'2025_actual'!$A$59:$A$69,0),MATCH(C21,'2025_actual'!$B$58:$M$58,0)), 2026,INDEX('2026_actual'!$B$59:$M$69,MATCH(E21,'2026_actual'!$A$59:$A$69,0),MATCH(C21,'2026_actual'!$B$58:$M$58,0)) )} -> 649000 | H21: =G21-F21 -> -24166.667 | I21: =IF(AND(E21="Operating Profit",F21<=0),NA(),IFERROR(H21/F21,0)) -> -0.035899975 | J21: =IF(G21<=F21,"F","U") -> F
A22: 45352 | B22: 2024 | C22: Mar | D22: Marketing | E22: Marketing Expenses | F22: {=_xlfn.SWITCH(B22, 2024,INDEX('2024_budget'!$B$59:$M$69,MATCH(E22,'2024_budget'!$A$59:$A$69,0),MATCH(C22,'2024_budget'!$B$58:$M$58,0)), 2025,INDEX('2025_budget'!$B$59:$M$69,MATCH(E22,'2025_budget'!$A$59:$A$69,0),MATCH(C22,'2025_budget'!$B$58:$M$58,0)), 2026,INDEX('2026_budget'!$B$59:$M$69,MATCH(E22,'2026_budget'!$A$59:$A$69,0),MATCH(C22,'2026_budget'!$B$58:$M$58,0)) )} -> 391166.67 | G22: {=_xlfn.SWITCH(B22, 2024,INDEX('2024_actual'!$B$59:$M$69,MATCH(E22,'2024_actual'!$A$59:$A$69,0),MATCH(C22,'2024_actual'!$B$58:$M$58,0)), 2025,INDEX('2025_actual'!$B$59:$M$69,MATCH(E22,'2025_actual'!$A$59:$A$69,0),MATCH(C22,'2025_actual'!$B$58:$M$58,0)), 2026,INDEX('2026_actual'!$B$59:$M$69,MATCH(E22,'2026_actual'!$A$59:$A$69,0),MATCH(C22,'2026_actual'!$B$58:$M$58,0)) )} -> 391900 | H22: =G22-F22 -> 733.33333 | I22: =IF(AND(E22="Operating Profit",F22<=0),NA(),IFERROR(H22/F22,0)) -> 0.0018747337 | J22: =IF(G22<=F22,"F","U") -> U
A23: 45352 | B23: 2024 | C23: Mar | D23: Engineering | E23: Engineering Expenses | F23: {=_xlfn.SWITCH(B23, 2024,INDEX('2024_budget'!$B$59:$M$69,MATCH(E23,'2024_budget'!$A$59:$A$69,0),MATCH(C23,'2024_budget'!$B$58:$M$58,0)), 2025,INDEX('2025_budget'!$B$59:$M$69,MATCH(E23,'2025_budget'!$A$59:$A$69,0),MATCH(C23,'2025_budget'!$B$58:$M$58,0)), 2026,INDEX('2026_budget'!$B$59:$M$69,MATCH(E23,'2026_budget'!$A$59:$A$69,0),MATCH(C23,'2026_budget'!$B$58:$M$58,0)) )} -> 1090500 | G23: {=_xlfn.SWITCH(B23, 2024,INDEX('2024_actual'!$B$59:$M$69,MATCH(E23,'2024_actual'!$A$59:$A$69,0),MATCH(C23,'2024_actual'!$B$58:$M$58,0)), 2025,INDEX('2025_actual'!$B$59:$M$69,MATCH(E23,'2025_actual'!$A$59:$A$69,0),MATCH(C23,'2025_actual'!$B$58:$M$58,0)), 2026,INDEX('2026_actual'!$B$59:$M$69,MATCH(E23,'2026_actual'!$A$59:$A$69,0),MATCH(C23,'2026_actual'!$B$58:$M$58,0)) )} -> 1088000 | H23: =G23-F23 -> -2500 | I23: =IF(AND(E23="Operating Profit",F23<=0),NA(),IFERROR(H23/F23,0)) -> -0.0022925264 | J23: =IF(G23<=F23,"F","U") -> F
A24: 45352 | B24: 2024 | C24: Mar | D24: Product | E24: Product Expenses | F24: {=_xlfn.SWITCH(B24, 2024,INDEX('2024_budget'!$B$59:$M$69,MATCH(E24,'2024_budget'!$A$59:$A$69,0),MATCH(C24,'2024_budget'!$B$58:$M$58,0)), 2025,INDEX('2025_budget'!$B$59:$M$69,MATCH(E24,'2025_budget'!$A$59:$A$69,0),MATCH(C24,'2025_budget'!$B$58:$M$58,0)), 2026,INDEX('2026_budget'!$B$59:$M$69,MATCH(E24,'2026_budget'!$A$59:$A$69,0),MATCH(C24,'2026_budget'!$B$58:$M$58,0)) )} -> 212083.33 | G24: {=_xlfn.SWITCH(B24, 2024,INDEX('2024_actual'!$B$59:$M$69,MATCH(E24,'2024_actual'!$A$59:$A$69,0),MATCH(C24,'2024_actual'!$B$58:$M$58,0)), 2025,INDEX('2025_actual'!$B$59:$M$69,MATCH(E24,'2025_actual'!$A$59:$A$69,0),MATCH(C24,'2025_actual'!$B$58:$M$58,0)), 2026,INDEX('2026_actual'!$B$59:$M$69,MATCH(E24,'2026_actual'!$A$59:$A$69,0),MATCH(C24,'2026_actual'!$B$58:$M$58,0)) )} -> 210950 | H24: =G24-F24 -> -1133.3333 | I24: =IF(AND(E24="Operating Profit",F24<=0),NA(),IFERROR(H24/F24,0)) -> -0.0053438114 | J24: =IF(G24<=F24,"F","U") -> F
A25: 45352 | B25: 2024 | C25: Mar | D25: Customer Success | E25: Customer Success Expenses | F25: {=_xlfn.SWITCH(B25, 2024,INDEX('2024_budget'!$B$59:$M$69,MATCH(E25,'2024_budget'!$A$59:$A$69,0),MATCH(C25,'2024_budget'!$B$58:$M$58,0)), 2025,INDEX('2025_budget'!$B$59:$M$69,MATCH(E25,'2025_budget'!$A$59:$A$69,0),MATCH(C25,'2025_budget'!$B$58:$M$58,0)), 2026,INDEX('2026_budget'!$B$59:$M$69,MATCH(E25,'2026_budget'!$A$59:$A$69,0),MATCH(C25,'2026_budget'!$B$58:$M$58,0)) )} -> 267500 | G25: {=_xlfn.SWITCH(B25, 2024,INDEX('2024_actual'!$B$59:$M$69,MATCH(E25,'2024_actual'!$A$59:$A$69,0),MATCH(C25,'2024_actual'!$B$58:$M$58,0)), 2025,INDEX('2025_actual'!$B$59:$M$69,MATCH(E25,'2025_actual'!$A$59:$A$69,0),MATCH(C25,'2025_actual'!$B$58:$M$58,0)), 2026,INDEX('2026_actual'!$B$59:$M$69,MATCH(E25,'2026_actual'!$A$59:$A$69,0),MATCH(C25,'2026_actual'!$B$58:$M$58,0)) )} -> 263500 | H25: =G25-F25 -> -4000 | I25: =IF(AND(E25="Operating Profit",F25<=0),NA(),IFERROR(H25/F25,0)) -> -0.014953271 | J25: =IF(G25<=F25,"F","U") -> F
A26: 45352 | B26: 2024 | C26: Mar | D26: G&A | E26: G&A Expenses | F26: {=_xlfn.SWITCH(B26, 2024,INDEX('2024_budget'!$B$59:$M$69,MATCH(E26,'2024_budget'!$A$59:$A$69,0),MATCH(C26,'2024_budget'!$B$58:$M$58,0)), 2025,INDEX('2025_budget'!$B$59:$M$69,MATCH(E26,'2025_budget'!$A$59:$A$69,0),MATCH(C26,'2025_budget'!$B$58:$M$58,0)), 2026,INDEX('2026_budget'!$B$59:$M$69,MATCH(E26,'2026_budget'!$A$59:$A$69,0),MATCH(C26,'2026_budget'!$B$58:$M$58,0)) )} -> 314583.33 | G26: {=_xlfn.SWITCH(B26, 2024,INDEX('2024_actual'!$B$59:$M$69,MATCH(E26,'2024_actual'!$A$59:$A$69,0),MATCH(C26,'2024_actual'!$B$58:$M$58,0)), 2025,INDEX('2025_actual'!$B$59:$M$69,MATCH(E26,'2025_actual'!$A$59:$A$69,0),MATCH(C26,'2025_actual'!$B$58:$M$58,0)), 2026,INDEX('2026_actual'!$B$59:$M$69,MATCH(E26,'2026_actual'!$A$59:$A$69,0),MATCH(C26,'2026_actual'!$B$58:$M$58,0)) )} -> 311150 | H26: =G26-F26 -> -3433.3333 | I26: =IF(AND(E26="Operating Profit",F26<=0),NA(),IFERROR(H26/F26,0)) -> -0.010913907 | J26: =IF(G26<=F26,"F","U") -> F
A27: 45352 | B27: 2024 | C27: Mar | D27: Company | E27: Total Operating Expenses | F27: {=_xlfn.SWITCH(B27, 2024,INDEX('2024_budget'!$B$59:$M$69,MATCH(E27,'2024_budget'!$A$59:$A$69,0),MATCH(C27,'2024_budget'!$B$58:$M$58,0)), 2025,INDEX('2025_budget'!$B$59:$M$69,MATCH(E27,'2025_budget'!$A$59:$A$69,0),MATCH(C27,'2025_budget'!$B$58:$M$58,0)), 2026,INDEX('2026_budget'!$B$59:$M$69,MATCH(E27,'2026_budget'!$A$59:$A$69,0),MATCH(C27,'2026_budget'!$B$58:$M$58,0)) )} -> 2949000 | G27: {=_xlfn.SWITCH(B27, 2024,INDEX('2024_actual'!$B$59:$M$69,MATCH(E27,'2024_actual'!$A$59:$A$69,0),MATCH(C27,'2024_actual'!$B$58:$M$58,0)), 2025,INDEX('2025_actual'!$B$59:$M$69,MATCH(E27,'2025_actual'!$A$59:$A$69,0),MATCH(C27,'2025_actual'!$B$58:$M$58,0)), 2026,INDEX('2026_actual'!$B$59:$M$69,MATCH(E27,'2026_actual'!$A$59:$A$69,0),MATCH(C27,'2026_actual'!$B$58:$M$58,0)) )} -> 2914500 | H27: =G27-F27 -> -34500 | I27: =IF(AND(E27="Operating Profit",F27<=0),NA(),IFERROR(H27/F27,0)) -> -0.011698881 | J27: =IF(G27<=F27,"F","U") -> F
A28: 45352 | B28: 2024 | C28: Mar | D28: Company | E28: Operating Profit | F28: {=_xlfn.SWITCH(B28, 2024,INDEX('2024_budget'!$B$59:$M$69,MATCH(E28,'2024_budget'!$A$59:$A$69,0),MATCH(C28,'2024_budget'!$B$58:$M$58,0)), 2025,INDEX('2025_budget'!$B$59:$M$69,MATCH(E28,'2025_budget'!$A$59:$A$69,0),MATCH(C28,'2025_budget'!$B$58:$M$58,0)), 2026,INDEX('2026_budget'!$B$59:$M$69,MATCH(E28,'2026_budget'!$A$59:$A$69,0),MATCH(C28,'2026_budget'!$B$58:$M$58,0)) )} -> 251000 | G28: {=_xlfn.SWITCH(B28, 2024,INDEX('2024_actual'!$B$59:$M$69,MATCH(E28,'2024_actual'!$A$59:$A$69,0),MATCH(C28,'2024_actual'!$B$58:$M$58,0)), 2025,INDEX('2025_actual'!$B$59:$M$69,MATCH(E28,'2025_actual'!$A$59:$A$69,0),MATCH(C28,'2025_actual'!$B$58:$M$58,0)), 2026,INDEX('2026_actual'!$B$59:$M$69,MATCH(E28,'2026_actual'!$A$59:$A$69,0),MATCH(C28,'2026_actual'!$B$58:$M$58,0)) )} -> 110500 | H28: =G28-F28 -> -140500 | I28: =IF(AND(E28="Operating Profit",F28<=0),NA(),IFERROR(H28/F28,0)) -> -0.55976096 | J28: =IF(G28>=F28,"F","U") -> U
A29: 45383 | B29: 2024 | C29: Apr | D29: Company | E29: Total Revenue | F29: {=_xlfn.SWITCH(B29, 2024,INDEX('2024_budget'!$B$59:$M$69,MATCH(E29,'2024_budget'!$A$59:$A$69,0),MATCH(C29,'2024_budget'!$B$58:$M$58,0)), 2025,INDEX('2025_budget'!$B$59:$M$69,MATCH(E29,'2025_budget'!$A$59:$A$69,0),MATCH(C29,'2025_budget'!$B$58:$M$58,0)), 2026,INDEX('2026_budget'!$B$59:$M$69,MATCH(E29,'2026_budget'!$A$59:$A$69,0),MATCH(C29,'2026_budget'!$B$58:$M$58,0)) )} -> 3200000 | G29: {=_xlfn.SWITCH(B29, 2024,INDEX('2024_actual'!$B$59:$M$69,MATCH(E29,'2024_actual'!$A$59:$A$69,0),MATCH(C29,'2024_actual'!$B$58:$M$58,0)), 2025,INDEX('2025_actual'!$B$59:$M$69,MATCH(E29,'2025_actual'!$A$59:$A$69,0),MATCH(C29,'2025_actual'!$B$58:$M$58,0)), 2026,INDEX('2026_actual'!$B$59:$M$69,MATCH(E29,'2026_actual'!$A$59:$A$69,0),MATCH(C29,'2026_actual'!$B$58:$M$58,0)) )} -> 3070000 | H29: =G29-F29 -> -130000 | I29: =IF(AND(E29="Operating Profit",F29<=0),NA(),IFERROR(H29/F29,0)) -> -0.040625 | J29: =IF(G29>=F29,"F","U") -> U
A30: 45383 | B30: 2024 | C30: Apr | D30: Sales | E30: Sales Expenses | F30: {=_xlfn.SWITCH(B30, 2024,INDEX('2024_budget'!$B$59:$M$69,MATCH(E30,'2024_budget'!$A$59:$A$69,0),MATCH(C30,'2024_budget'!$B$58:$M$58,0)), 2025,INDEX('2025_budget'!$B$59:$M$69,MATCH(E30,'2025_budget'!$A$59:$A$69,0),MATCH(C30,'2025_budget'!$B$58:$M$58,0)), 2026,INDEX('2026_budget'!$B$59:$M$69,MATCH(E30,'2026_budget'!$A$59:$A$69,0),MATCH(C30,'2026_budget'!$B$58:$M$58,0)) )} -> 673166.67 | G30: {=_xlfn.SWITCH(B30, 2024,INDEX('2024_actual'!$B$59:$M$69,MATCH(E30,'2024_actual'!$A$59:$A$69,0),MATCH(C30,'2024_actual'!$B$58:$M$58,0)), 2025,INDEX('2025_actual'!$B$59:$M$69,MATCH(E30,'2025_actual'!$A$59:$A$69,0),MATCH(C30,'2025_actual'!$B$58:$M$58,0)), 2026,INDEX('2026_actual'!$B$59:$M$69,MATCH(E30,'2026_actual'!$A$59:$A$69,0),MATCH(C30,'2026_actual'!$B$58:$M$58,0)) )} -> 652000 | H30: =G30-F30 -> -21166.667 | I30: =IF(AND(E30="Operating Profit",F30<=0),NA(),IFERROR(H30/F30,0)) -> -0.031443427 | J30: =IF(G30<=F30,"F","U") -> F
A31: 45383 | B31: 2024 | C31: Apr | D31: Marketing | E31: Marketing Expenses | F31: {=_xlfn.SWITCH(B31, 2024,INDEX('2024_budget'!$B$59:$M$69,MATCH(E31,'2024_budget'!$A$59:$A$69,0),MATCH(C31,'2024_budget'!$B$58:$M$58,0)), 2025,INDEX('2025_budget'!$B$59:$M$69,MATCH(E31,'2025_budget'!$A$59:$A$69,0),MATCH(C31,'2025_budget'!$B$58:$M$58,0)), 2026,INDEX('2026_budget'!$B$59:$M$69,MATCH(E31,'2026_budget'!$A$59:$A$69,0),MATCH(C31,'2026_budget'!$B$58:$M$58,0)) )} -> 391166.67 | G31: {=_xlfn.SWITCH(B31, 2024,INDEX('2024_actual'!$B$59:$M$69,MATCH(E31,'2024_actual'!$A$59:$A$69,0),MATCH(C31,'2024_actual'!$B$58:$M$58,0)), 2025,INDEX('2025_actual'!$B$59:$M$69,MATCH(E31,'2025_actual'!$A$59:$A$69,0),MATCH(C31,'2025_actual'!$B$58:$M$58,0)), 2026,INDEX('2026_actual'!$B$59:$M$69,MATCH(E31,'2026_actual'!$A$59:$A$69,0),MATCH(C31,'2026_actual'!$B$58:$M$58,0)) )} -> 396900 | H31: =G31-F31 -> 5733.3333 | I31: =IF(AND(E31="Operating Profit",F31<=0),NA(),IFERROR(H31/F31,0)) -> 0.014657009 | J31: =IF(G31<=F31,"F","U") -> U
A32: 45383 | B32: 2024 | C32: Apr | D32: Engineering | E32: Engineering Expenses | F32: {=_xlfn.SWITCH(B32, 2024,INDEX('2024_budget'!$B$59:$M$69,MATCH(E32,'2024_budget'!$A$59:$A$69,0),MATCH(C32,'2024_budget'!$B$58:$M$58,0)), 2025,INDEX('2025_budget'!$B$59:$M$69,MATCH(E32,'2025_budget'!$A$59:$A$69,0),MATCH(C32,'2025_budget'!$B$58:$M$58,0)), 2026,INDEX('2026_budget'!$B$59:$M$69,MATCH(E32,'2026_budget'!$A$59:$A$69,0),MATCH(C32,'2026_budget'!$B$58:$M$58,0)) )} -> 1090500 | G32: {=_xlfn.SWITCH(B32, 2024,INDEX('2024_actual'!$B$59:$M$69,MATCH(E32,'2024_actual'!$A$59:$A$69,0),MATCH(C32,'2024_actual'!$B$58:$M$58,0)), 2025,INDEX('2025_actual'!$B$59:$M$69,MATCH(E32,'2025_actual'!$A$59:$A$69,0),MATCH(C32,'2025_actual'!$B$58:$M$58,0)), 2026,INDEX('2026_actual'!$B$59:$M$69,MATCH(E32,'2026_actual'!$A$59:$A$69,0),MATCH(C32,'2026_actual'!$B$58:$M$58,0)) )} -> 1091000 | H32: =G32-F32 -> 500 | I32: =IF(AND(E32="Operating Profit",F32<=0),NA(),IFERROR(H32/F32,0)) -> 0.00045850527 | J32: =IF(G32<=F32,"F","U") -> U
A33: 45383 | B33: 2024 | C33: Apr | D33: Product | E33: Product Expenses | F33: {=_xlfn.SWITCH(B33, 2024,INDEX('2024_budget'!$B$59:$M$69,MATCH(E33,'2024_budget'!$A$59:$A$69,0),MATCH(C33,'2024_budget'!$B$58:$M$58,0)), 2025,INDEX('2025_budget'!$B$59:$M$69,MATCH(E33,'2025_budget'!$A$59:$A$69,0),MATCH(C33,'2025_budget'!$B$58:$M$58,0)), 2026,INDEX('2026_budget'!$B$59:$M$69,MATCH(E33,'2026_budget'!$A$59:$A$69,0),MATCH(C33,'2026_budget'!$B$58:$M$58,0)) )} -> 212083.33 | G33: {=_xlfn.SWITCH(B33, 2024,INDEX('2024_actual'!$B$59:$M$69,MATCH(E33,'2024_actual'!$A$59:$A$69,0),MATCH(C33,'2024_actual'!$B$58:$M$58,0)), 2025,INDEX('2025_actual'!$B$59:$M$69,MATCH(E33,'2025_actual'!$A$59:$A$69,0),MATCH(C33,'2025_actual'!$B$58:$M$58,0)), 2026,INDEX('2026_actual'!$B$59:$M$69,MATCH(E33,'2026_actual'!$A$59:$A$69,0),MATCH(C33,'2026_actual'!$B$58:$M$58,0)) )} -> 210950 | H33: =G33-F33 -> -1133.3333 | I33: =IF(AND(E33="Operating Profit",F33<=0),NA(),IFERROR(H33/F33,0)) -> -0.0053438114 | J33: =IF(G33<=F33,"F","U") -> F
A34: 45383 | B34: 2024 | C34: Apr | D34: Customer Success | E34: Customer Success Expenses | F34: {=_xlfn.SWITCH(B34, 2024,INDEX('2024_budget'!$B$59:$M$69,MATCH(E34,'2024_budget'!$A$59:$A$69,0),MATCH(C34,'2024_budget'!$B$58:$M$58,0)), 2025,INDEX('2025_budget'!$B$59:$M$69,MATCH(E34,'2025_budget'!$A$59:$A$69,0),MATCH(C34,'2025_budget'!$B$58:$M$58,0)), 2026,INDEX('2026_budget'!$B$59:$M$69,MATCH(E34,'2026_budget'!$A$59:$A$69,0),MATCH(C34,'2026_budget'!$B$58:$M$58,0)) )} -> 267500 | G34: {=_xlfn.SWITCH(B34, 2024,INDEX('2024_actual'!$B$59:$M$69,MATCH(E34,'2024_actual'!$A$59:$A$69,0),MATCH(C34,'2024_actual'!$B$58:$M$58,0)), 2025,INDEX('2025_actual'!$B$59:$M$69,MATCH(E34,'2025_actual'!$A$59:$A$69,0),MATCH(C34,'2025_actual'!$B$58:$M$58,0)), 2026,INDEX('2026_actual'!$B$59:$M$69,MATCH(E34,'2026_actual'!$A$59:$A$69,0),MATCH(C34,'2026_actual'!$B$58:$M$58,0)) )} -> 264000 | H34: =G34-F34 -> -3500 | I34: =IF(AND(E34="Operating Profit",F34<=0),NA(),IFERROR(H34/F34,0)) -> -0.013084112 | J34: =IF(G34<=F34,"F","U") -> F
A35: 45383 | B35: 2024 | C35: Apr | D35: G&A | E35: G&A Expenses | F35: {=_xlfn.SWITCH(B35, 2024,INDEX('2024_budget'!$B$59:$M$69,MATCH(E35,'2024_budget'!$A$59:$A$69,0),MATCH(C35,'2024_budget'!$B$58:$M$58,0)), 2025,INDEX('2025_budget'!$B$59:$M$69,MATCH(E35,'2025_budget'!$A$59:$A$69,0),MATCH(C35,'2025_budget'!$B$58:$M$58,0)), 2026,INDEX('2026_budget'!$B$59:$M$69,MATCH(E35,'2026_budget'!$A$59:$A$69,0),MATCH(C35,'2026_budget'!$B$58:$M$58,0)) )} -> 314583.33 | G35: {=_xlfn.SWITCH(B35, 2024,INDEX('2024_actual'!$B$59:$M$69,MATCH(E35,'2024_actual'!$A$59:$A$69,0),MATCH(C35,'2024_actual'!$B$58:$M$58,0)), 2025,INDEX('2025_actual'!$B$59:$M$69,MATCH(E35,'2025_actual'!$A$59:$A$69,0),MATCH(C35,'2025_actual'!$B$58:$M$58,0)), 2026,INDEX('2026_actual'!$B$59:$M$69,MATCH(E35,'2026_actual'!$A$59:$A$69,0),MATCH(C35,'2026_actual'!$B$58:$M$58,0)) )} -> 311150 | H35: =G35-F35 -> -3433.3333 | I35: =IF(AND(E35="Operating Profit",F35<=0),NA(),IFERROR(H35/F35,0)) -> -0.010913907 | J35: =IF(G35<=F35,"F","U") -> F
A36: 45383 | B36: 2024 | C36: Apr | D36: Company | E36: Total Operating Expenses | F36: {=_xlfn.SWITCH(B36, 2024,INDEX('2024_budget'!$B$59:$M$69,MATCH(E36,'2024_budget'!$A$59:$A$69,0),MATCH(C36,'2024_budget'!$B$58:$M$58,0)), 2025,INDEX('2025_budget'!$B$59:$M$69,MATCH(E36,'2025_budget'!$A$59:$A$69,0),MATCH(C36,'2025_budget'!$B$58:$M$58,0)), 2026,INDEX('2026_budget'!$B$59:$M$69,MATCH(E36,'2026_budget'!$A$59:$A$69,0),MATCH(C36,'2026_budget'!$B$58:$M$58,0)) )} -> 2949000 | G36: {=_xlfn.SWITCH(B36, 2024,INDEX('2024_actual'!$B$59:$M$69,MATCH(E36,'2024_actual'!$A$59:$A$69,0),MATCH(C36,'2024_actual'!$B$58:$M$58,0)), 2025,INDEX('2025_actual'!$B$59:$M$69,MATCH(E36,'2025_actual'!$A$59:$A$69,0),MATCH(C36,'2025_actual'!$B$58:$M$58,0)), 2026,INDEX('2026_actual'!$B$59:$M$69,MATCH(E36,'2026_actual'!$A$59:$A$69,0),MATCH(C36,'2026_actual'!$B$58:$M$58,0)) )} -> 2926000 | H36: =G36-F36 -> -23000 | I36: =IF(AND(E36="Operating Profit",F36<=0),NA(),IFERROR(H36/F36,0)) -> -0.007799254 | J36: =IF(G36<=F36,"F","U") -> F
A37: 45383 | B37: 2024 | C37: Apr | D37: Company | E37: Operating Profit | F37: {=_xlfn.SWITCH(B37, 2024,INDEX('2024_budget'!$B$59:$M$69,MATCH(E37,'2024_budget'!$A$59:$A$69,0),MATCH(C37,'2024_budget'!$B$58:$M$58,0)), 2025,INDEX('2025_budget'!$B$59:$M$69,MATCH(E37,'2025_budget'!$A$59:$A$69,0),MATCH(C37,'2025_budget'!$B$58:$M$58,0)), 2026,INDEX('2026_budget'!$B$59:$M$69,MATCH(E37,'2026_budget'!$A$59:$A$69,0),MATCH(C37,'2026_budget'!$B$58:$M$58,0)) )} -> 251000 | G37: {=_xlfn.SWITCH(B37, 2024,INDEX('2024_actual'!$B$59:$M$69,MATCH(E37,'2024_actual'!$A$59:$A$69,0),MATCH(C37,'2024_actual'!$B$58:$M$58,0)), 2025,INDEX('2025_actual'!$B$59:$M$69,MATCH(E37,'2025_actual'!$A$59:$A$69,0),MATCH(C37,'2025_actual'!$B$58:$M$58,0)), 2026,INDEX('2026_actual'!$B$59:$M$69,MATCH(E37,'2026_actual'!$A$59:$A$69,0),MATCH(C37,'2026_actual'!$B$58:$M$58,0)) )} -> 144000 | H37: =G37-F37 -> -107000 | I37: =IF(AND(E37="Operating Profit",F37<=0),NA(),IFERROR(H37/F37,0)) -> -0.42629482 | J37: =IF(G37>=F37,"F","U") -> U
A38: 45413 | B38: 2024 | C38: May | D38: Company | E38: Total Revenue | F38: {=_xlfn.SWITCH(B38, 2024,INDEX('2024_budget'!$B$59:$M$69,MATCH(E38,'2024_budget'!$A$59:$A$69,0),MATCH(C38,'2024_budget'!$B$58:$M$58,0)), 2025,INDEX('2025_budget'!$B$59:$M$69,MATCH(E38,'2025_budget'!$A$59:$A$69,0),MATCH(C38,'2025_budget'!$B$58:$M$58,0)), 2026,INDEX('2026_budget'!$B$59:$M$69,MATCH(E38,'2026_budget'!$A$59:$A$69,0),MATCH(C38,'2026_budget'!$B$58:$M$58,0)) )} -> 3200000 | G38: {=_xlfn.SWITCH(B38, 2024,INDEX('2024_actual'!$B$59:$M$69,MATCH(E38,'2024_actual'!$A$59:$A$69,0),MATCH(C38,'2024_actual'!$B$58:$M$58,0)), 2025,INDEX('2025_actual'!$B$59:$M$69,MATCH(E38,'2025_actual'!$A$59:$A$69,0),MATCH(C38,'2025_actual'!$B$58:$M$58,0)), 2026,INDEX('2026_actual'!$B$59:$M$69,MATCH(E38,'2026_actual'!$A$59:$A$69,0),MATCH(C38,'2026_actual'!$B$58:$M$58,0)) )} -> 3105000 | H38: =G38-F38 -> -95000 | I38: =IF(AND(E38="Operating Profit",F38<=0),NA(),IFERROR(H38/F38,0)) -> -0.0296875 | J38: =IF(G38>=F38,"F","U") -> U
A39: 45413 | B39: 2024 | C39: May | D39: Sales | E39: Sales Expenses | F39: {=_xlfn.SWITCH(B39, 2024,INDEX('2024_budget'!$B$59:$M$69,MATCH(E39,'2024_budget'!$A$59:$A$69,0),MATCH(C39,'2024_budget'!$B$58:$M$58,0)), 2025,INDEX('2025_budget'!$B$59:$M$69,MATCH(E39,'2025_budget'!$A$59:$A$69,0),MATCH(C39,'2025_budget'!$B$58:$M$58,0)), 2026,INDEX('2026_budget'!$B$59:$M$69,MATCH(E39,'2026_budget'!$A$59:$A$69,0),MATCH(C39,'2026_budget'!$B$58:$M$58,0)) )} -> 673166.67 | G39: {=_xlfn.SWITCH(B39, 2024,INDEX('2024_actual'!$B$59:$M$69,MATCH(E39,'2024_actual'!$A$59:$A$69,0),MATCH(C39,'2024_actual'!$B$58:$M$58,0)), 2025,INDEX('2025_actual'!$B$59:$M$69,MATCH(E39,'2025_actual'!$A$59:$A$69,0),MATCH(C39,'2025_actual'!$B$58:$M$58,0)), 2026,INDEX('2026_actual'!$B$59:$M$69,MATCH(E39,'2026_actual'!$A$59:$A$69,0),MATCH(C39,'2026_actual'!$B$58:$M$58,0)) )} -> 653500 | H39: =G39-F39 -> -19666.667 | I39: =IF(AND(E39="Operating Profit",F39<=0),NA(),IFERROR(H39/F39,0)) -> -0.029215152 | J39: =IF(G39<=F39,"F","U") -> F
A40: 45413 | B40: 2024 | C40: May | D40: Marketing | E40: Marketing Expenses | F40: {=_xlfn.SWITCH(B40, 2024,INDEX('2024_budget'!$B$59:$M$69,MATCH(E40,'2024_budget'!$A$59:$A$69,0),MATCH(C40,'2024_budget'!$B$58:$M$58,0)), 2025,INDEX('2025_budget'!$B$59:$M$69,MATCH(E40,'2025_budget'!$A$59:$A$69,0),MATCH(C40,'2025_budget'!$B$58:$M$58,0)), 2026,INDEX('2026_budget'!$B$59:$M$69,MATCH(E40,'2026_budget'!$A$59:$A$69,0),MATCH(C40,'2026_budget'!$B$58:$M$58,0)) )} -> 391166.67 | G40: {=_xlfn.SWITCH(B40, 2024,INDEX('2024_actual'!$B$59:$M$69,MATCH(E40,'2024_actual'!$A$59:$A$69,0),MATCH(C40,'2024_actual'!$B$58:$M$58,0)), 2025,INDEX('2025_actual'!$B$59:$M$69,MATCH(E40,'2025_actual'!$A$59:$A$69,0),MATCH(C40,'2025_actual'!$B$58:$M$58,0)), 2026,INDEX('2026_actual'!$B$59:$M$69,MATCH(E40,'2026_actual'!$A$59:$A$69,0),MATCH(C40,'2026_actual'!$B$58:$M$58,0)) )} -> 403600 | H40: =G40-F40 -> 12433.333 | I40: =IF(AND(E40="Operating Profit",F40<=0),NA(),IFERROR(H40/F40,0)) -> 0.031785258 | J40: =IF(G40<=F40,"F","U") -> U
A41: 45413 | B41: 2024 | C41: May | D41: Engineering | E41: Engineering Expenses | F41: {=_xlfn.SWITCH(B41, 2024,INDEX('2024_budget'!$B$59:$M$69,MATCH(E41,'2024_budget'!$A$59:$A$69,0),MATCH(C41,'2024_budget'!$B$58:$M$58,0)), 2025,INDEX('2025_budget'!$B$59:$M$69,MATCH(E41,'2025_budget'!$A$59:$A$69,0),MATCH(C41,'2025_budget'!$B$58:$M$58,0)), 2026,INDEX('2026_budget'!$B$59:$M$69,MATCH(E41,'2026_budget'!$A$59:$A$69,0),MATCH(C41,'2026_budget'!$B$58:$M$58,0)) )} -> 1090500 | G41: {=_xlfn.SWITCH(B41, 2024,INDEX('2024_actual'!$B$59:$M$69,MATCH(E41,'2024_actual'!$A$59:$A$69,0),MATCH(C41,'2024_actual'!$B$58:$M$58,0)), 2025,INDEX('2025_actual'!$B$59:$M$69,MATCH(E41,'2025_actual'!$A$59:$A$69,0),MATCH(C41,'2025_actual'!$B$58:$M$58,0)), 2026,INDEX('2026_actual'!$B$59:$M$69,MATCH(E41,'2026_actual'!$A$59:$A$69,0),MATCH(C41,'2026_actual'!$B$58:$M$58,0)) )} -> 1099000 | H41: =G41-F41 -> 8500 | I41: =IF(AND(E41="Operating Profit",F41<=0),NA(),IFERROR(H41/F41,0)) -> 0.0077945896 | J41: =IF(G41<=F41,"F","U") -> U
A42: 45413 | B42: 2024 | C42: May | D42: Product | E42: Product Expenses | F42: {=_xlfn.SWITCH(B42, 2024,INDEX('2024_budget'!$B$59:$M$69,MATCH(E42,'2024_budget'!$A$59:$A$69,0),MATCH(C42,'2024_budget'!$B$58:$M$58,0)), 2025,INDEX('2025_budget'!$B$59:$M$69,MATCH(E42,'2025_budget'!$A$59:$A$69,0),MATCH(C42,'2025_budget'!$B$58:$M$58,0)), 2026,INDEX('2026_budget'!$B$59:$M$69,MATCH(E42,'2026_budget'!$A$59:$A$69,0),MATCH(C42,'2026_budget'!$B$58:$M$58,0)) )} -> 212083.33 | G42: {=_xlfn.SWITCH(B42, 2024,INDEX('2024_actual'!$B$59:$M$69,MATCH(E42,'2024_actual'!$A$59:$A$69,0),MATCH(C42,'2024_actual'!$B$58:$M$58,0)), 2025,INDEX('2025_actual'!$B$59:$M$69,MATCH(E42,'2025_actual'!$A$59:$A$69,0),MATCH(C42,'2025_actual'!$B$58:$M$58,0)), 2026,INDEX('2026_actual'!$B$59:$M$69,MATCH(E42,'2026_actual'!$A$59:$A$69,0),MATCH(C42,'2026_actual'!$B$58:$M$58,0)) )} -> 211950 | H42: =G42-F42 -> -133.33333 | I42: =IF(AND(E42="Operating Profit",F42<=0),NA(),IFERROR(H42/F42,0)) -> -0.00062868369 | J42: =IF(G42<=F42,"F","U") -> F
A43: 45413 | B43: 2024 | C43: May | D43: Customer Success | E43: Customer Success Expenses | F43: {=_xlfn.SWITCH(B43, 2024,INDEX('2024_budget'!$B$59:$M$69,MATCH(E43,'2024_budget'!$A$59:$A$69,0),MATCH(C43,'2024_budget'!$B$58:$M$58,0)), 2025,INDEX('2025_budget'!$B$59:$M$69,MATCH(E43,'2025_budget'!$A$59:$A$69,0),MATCH(C43,'2025_budget'!$B$58:$M$58,0)), 2026,INDEX('2026_budget'!$B$59:$M$69,MATCH(E43,'2026_budget'!$A$59:$A$69,0),MATCH(C43,'2026_budget'!$B$58:$M$58,0)) )} -> 267500 | G43: {=_xlfn.SWITCH(B43, 2024,INDEX('2024_actual'!$B$59:$M$69,MATCH(E43,'2024_actual'!$A$59:$A$69,0),MATCH(C43,'2024_actual'!$B$58:$M$58,0)), 2025,INDEX('2025_actual'!$B$59:$M$69,MATCH(E43,'2025_actual'!$A$59:$A$69,0),MATCH(C43,'2025_actual'!$B$58:$M$58,0)), 2026,INDEX('2026_actual'!$B$59:$M$69,MATCH(E43,'2026_actual'!$A$59:$A$69,0),MATCH(C43,'2026_actual'!$B$58:$M$58,0)) )} -> 265200 | H43: =G43-F43 -> -2300 | I43: =IF(AND(E43="Operating Profit",F43<=0),NA(),IFERROR(H43/F43,0)) -> -0.0085981308 | J43: =IF(G43<=F43,"F","U") -> F
A44: 45413 | B44: 2024 | C44: May | D44: G&A | E44: G&A Expenses | F44: {=_xlfn.SWITCH(B44, 2024,INDEX('2024_budget'!$B$59:$M$69,MATCH(E44,'2024_budget'!$A$59:$A$69,0),MATCH(C44,'2024_budget'!$B$58:$M$58,0)), 2025,INDEX('2025_budget'!$B$59:$M$69,MATCH(E44,'2025_budget'!$A$59:$A$69,0),MATCH(C44,'2025_budget'!$B$58:$M$58,0)), 2026,INDEX('2026_budget'!$B$59:$M$69,MATCH(E44,'2026_budget'!$A$59:$A$69,0),MATCH(C44,'2026_budget'!$B$58:$M$58,0)) )} -> 314583.33 | G44: {=_xlfn.SWITCH(B44, 2024,INDEX('2024_actual'!$B$59:$M$69,MATCH(E44,'2024_actual'!$A$59:$A$69,0),MATCH(C44,'2024_actual'!$B$58:$M$58,0)), 2025,INDEX('2025_actual'!$B$59:$M$69,MATCH(E44,'2025_actual'!$A$59:$A$69,0),MATCH(C44,'2025_actual'!$B$58:$M$58,0)), 2026,INDEX('2026_actual'!$B$59:$M$69,MATCH(E44,'2026_actual'!$A$59:$A$69,0),MATCH(C44,'2026_actual'!$B$58:$M$58,0)) )} -> 314350 | H44: =G44-F44 -> -233.33333 | I44: =IF(AND(E44="Operating Profit",F44<=0),NA(),IFERROR(H44/F44,0)) -> -0.00074172185 | J44: =IF(G44<=F44,"F","U") -> F
A45: 45413 | B45: 2024 | C45: May | D45: Company | E45: Total Operating Expenses | F45: {=_xlfn.SWITCH(B45, 2024,INDEX('2024_budget'!$B$59:$M$69,MATCH(E45,'2024_budget'!$A$59:$A$69,0),MATCH(C45,'2024_budget'!$B$58:$M$58,0)), 2025,INDEX('2025_budget'!$B$59:$M$69,MATCH(E45,'2025_budget'!$A$59:$A$69,0),MATCH(C45,'2025_budget'!$B$58:$M$58,0)), 2026,INDEX('2026_budget'!$B$59:$M$69,MATCH(E45,'2026_budget'!$A$59:$A$69,0),MATCH(C45,'2026_budget'!$B$58:$M$58,0)) )} -> 2949000 | G45: {=_xlfn.SWITCH(B45, 2024,INDEX('2024_actual'!$B$59:$M$69,MATCH(E45,'2024_actual'!$A$59:$A$69,0),MATCH(C45,'2024_actual'!$B$58:$M$58,0)), 2025,INDEX('2025_actual'!$B$59:$M$69,MATCH(E45,'2025_actual'!$A$59:$A$69,0),MATCH(C45,'2025_actual'!$B$58:$M$58,0)), 2026,INDEX('2026_actual'!$B$59:$M$69,MATCH(E45,'2026_actual'!$A$59:$A$69,0),MATCH(C45,'2026_actual'!$B$58:$M$58,0)) )} -> 2947600 | H45: =G45-F45 -> -1400 | I45: =IF(AND(E45="Operating Profit",F45<=0),NA(),IFERROR(H45/F45,0)) -> -0.0004747372 | J45: =IF(G45<=F45,"F","U") -> F
A46: 45413 | B46: 2024 | C46: May | D46: Company | E46: Operating Profit | F46: {=_xlfn.SWITCH(B46, 2024,INDEX('2024_budget'!$B$59:$M$69,MATCH(E46,'2024_budget'!$A$59:$A$69,0),MATCH(C46,'2024_budget'!$B$58:$M$58,0)), 2025,INDEX('2025_budget'!$B$59:$M$69,MATCH(E46,'2025_budget'!$A$59:$A$69,0),MATCH(C46,'2025_budget'!$B$58:$M$58,0)), 2026,INDEX('2026_budget'!$B$59:$M$69,MATCH(E46,'2026_budget'!$A$59:$A$69,0),MATCH(C46,'2026_budget'!$B$58:$M$58,0)) )} -> 251000 | G46: {=_xlfn.SWITCH(B46, 2024,INDEX('2024_actual'!$B$59:$M$69,MATCH(E46,'2024_actual'!$A$59:$A$69,0),MATCH(C46,'2024_actual'!$B$58:$M$58,0)), 2025,INDEX('2025_actual'!$B$59:$M$69,MATCH(E46,'2025_actual'!$A$59:$A$69,0),MATCH(C46,'2025_actual'!$B$58:$M$58,0)), 2026,INDEX('2026_actual'!$B$59:$M$69,MATCH(E46,'2026_actual'!$A$59:$A$69,0),MATCH(C46,'2026_actual'!$B$58:$M$58,0)) )} -> 157400 | H46: =G46-F46 -> -93600 | I46: =IF(AND(E46="Operating Profit",F46<=0),NA(),IFERROR(H46/F46,0)) -> -0.37290837 | J46: =IF(G46>=F46,"F","U") -> U
A47: 45444 | B47: 2024 | C47: Jun | D47: Company | E47: Total Revenue | F47: {=_xlfn.SWITCH(B47, 2024,INDEX('2024_budget'!$B$59:$M$69,MATCH(E47,'2024_budget'!$A$59:$A$69,0),MATCH(C47,'2024_budget'!$B$58:$M$58,0)), 2025,INDEX('2025_budget'!$B$59:$M$69,MATCH(E47,'2025_budget'!$A$59:$A$69,0),MATCH(C47,'2025_budget'!$B$58:$M$58,0)), 2026,INDEX('2026_budget'!$B$59:$M$69,MATCH(E47,'2026_budget'!$A$59:$A$69,0),MATCH(C47,'2026_budget'!$B$58:$M$58,0)) )} -> 3200000 | G47: {=_xlfn.SWITCH(B47, 2024,INDEX('2024_actual'!$B$59:$M$69,MATCH(E47,'2024_actual'!$A$59:$A$69,0),MATCH(C47,'2024_actual'!$B$58:$M$58,0)), 2025,INDEX('2025_actual'!$B$59:$M$69,MATCH(E47,'2025_actual'!$A$59:$A$69,0),MATCH(C47,'2025_actual'!$B$58:$M$58,0)), 2026,INDEX('2026_actual'!$B$59:$M$69,MATCH(E47,'2026_actual'!$A$59:$A$69,0),MATCH(C47,'2026_actual'!$B$58:$M$58,0)) )} -> 3135000 | H47: =G47-F47 -> -65000 | I47: =IF(AND(E47="Operating Profit",F47<=0),NA(),IFERROR(H47/F47,0)) -> -0.0203125 | J47: =IF(G47>=F47,"F","U") -> U
A48: 45444 | B48: 2024 | C48: Jun | D48: Sales | E48: Sales Expenses | F48: {=_xlfn.SWITCH(B48, 2024,INDEX('2024_budget'!$B$59:$M$69,MATCH(E48,'2024_budget'!$A$59:$A$69,0),MATCH(C48,'2024_budget'!$B$58:$M$58,0)), 2025,INDEX('2025_budget'!$B$59:$M$69,MATCH(E48,'2025_budget'!$A$59:$A$69,0),MATCH(C48,'2025_budget'!$B$58:$M$58,0)), 2026,INDEX('2026_budget'!$B$59:$M$69,MATCH(E48,'2026_budget'!$A$59:$A$69,0),MATCH(C48,'2026_budget'!$B$58:$M$58,0)) )} -> 673166.67 | G48: {=_xlfn.SWITCH(B48, 2024,INDEX('2024_actual'!$B$59:$M$69,MATCH(E48,'2024_actual'!$A$59:$A$69,0),MATCH(C48,'2024_actual'!$B$58:$M$58,0)), 2025,INDEX('2025_actual'!$B$59:$M$69,MATCH(E48,'2025_actual'!$A$59:$A$69,0),MATCH(C48,'2025_actual'!$B$58:$M$58,0)), 2026,INDEX('2026_actual'!$B$59:$M$69,MATCH(E48,'2026_actual'!$A$59:$A$69,0),MATCH(C48,'2026_actual'!$B$58:$M$58,0)) )} -> 662000 | H48: =G48-F48 -> -11166.667 | I48: =IF(AND(E48="Operating Profit",F48<=0),NA(),IFERROR(H48/F48,0)) -> -0.016588264 | J48: =IF(G48<=F48,"F","U") -> F
A49: 45444 | B49: 2024 | C49: Jun | D49: Marketing | E49: Marketing Expenses | F49: {=_xlfn.SWITCH(B49, 2024,INDEX('2024_budget'!$B$59:$M$69,MATCH(E49,'2024_budget'!$A$59:$A$69,0),MATCH(C49,'2024_budget'!$B$58:$M$58,0)), 2025,INDEX('2025_budget'!$B$59:$M$69,MATCH(E49,'2025_budget'!$A$59:$A$69,0),MATCH(C49,'2025_budget'!$B$58:$M$58,0)), 2026,INDEX('2026_budget'!$B$59:$M$69,MATCH(E49,'2026_budget'!$A$59:$A$69,0),MATCH(C49,'2026_budget'!$B$58:$M$58,0)) )} -> 391166.67 | G49: {=_xlfn.SWITCH(B49, 2024,INDEX('2024_actual'!$B$59:$M$69,MATCH(E49,'2024_actual'!$A$59:$A$69,0),MATCH(C49,'2024_actual'!$B$58:$M$58,0)), 2025,INDEX('2025_actual'!$B$59:$M$69,MATCH(E49,'2025_actual'!$A$59:$A$69,0),MATCH(C49,'2025_actual'!$B$58:$M$58,0)), 2026,INDEX('2026_actual'!$B$59:$M$69,MATCH(E49,'2026_actual'!$A$59:$A$69,0),MATCH(C49,'2026_actual'!$B$58:$M$58,0)) )} -> 408600 | H49: =G49-F49 -> 17433.333 | I49: =IF(AND(E49="Operating Profit",F49<=0),NA(),IFERROR(H49/F49,0)) -> 0.044567533 | J49: =IF(G49<=F49,"F","U") -> U
A50: 45444 | B50: 2024 | C50: Jun | D50: Engineering | E50: Engineering Expenses | F50: {=_xlfn.SWITCH(B50, 2024,INDEX('2024_budget'!$B$59:$M$69,MATCH(E50,'2024_budget'!$A$59:$A$69,0),MATCH(C50,'2024_budget'!$B$58:$M$58,0)), 2025,INDEX('2025_budget'!$B$59:$M$69,MATCH(E50,'2025_budget'!$A$59:$A$69,0),MATCH(C50,'2025_budget'!$B$58:$M$58,0)), 2026,INDEX('2026_budget'!$B$59:$M$69,MATCH(E50,'2026_budget'!$A$59:$A$69,0),MATCH(C50,'2026_budget'!$B$58:$M$58,0)) )} -> 1090500 | G50: {=_xlfn.SWITCH(B50, 2024,INDEX('2024_actual'!$B$59:$M$69,MATCH(E50,'2024_actual'!$A$59:$A$69,0),MATCH(C50,'2024_actual'!$B$58:$M$58,0)), 2025,INDEX('2025_actual'!$B$59:$M$69,MATCH(E50,'2025_actual'!$A$59:$A$69,0),MATCH(C50,'2025_actual'!$B$58:$M$58,0)), 2026,INDEX('2026_actual'!$B$59:$M$69,MATCH(E50,'2026_actual'!$A$59:$A$69,0),MATCH(C50,'2026_actual'!$B$58:$M$58,0)) )} -> 1101000 | H50: =G50-F50 -> 10500 | I50: =IF(AND(E50="Operating Profit",F50<=0),NA(),IFERROR(H50/F50,0)) -> 0.0096286107 | J50: =IF(G50<=F50,"F","U") -> U
A51: 45444 | B51: 2024 | C51: Jun | D51: Product | E51: Product Expenses | F51: {=_xlfn.SWITCH(B51, 2024,INDEX('2024_budget'!$B$59:$M$69,MATCH(E51,'2024_budget'!$A$59:$A$69,0),MATCH(C51,'2024_budget'!$B$58:$M$58,0)), 2025,INDEX('2025_budget'!$B$59:$M$69,MATCH(E51,'2025_budget'!$A$59:$A$69,0),MATCH(C51,'2025_budget'!$B$58:$M$58,0)), 2026,INDEX('2026_budget'!$B$59:$M$69,MATCH(E51,'2026_budget'!$A$59:$A$69,0),MATCH(C51,'2026_budget'!$B$58:$M$58,0)) )} -> 212083.33 | G51: {=_xlfn.SWITCH(B51, 2024,INDEX('2024_actual'!$B$59:$M$69,MATCH(E51,'2024_actual'!$A$59:$A$69,0),MATCH(C51,'2024_actual'!$B$58:$M$58,0)), 2025,INDEX('2025_actual'!$B$59:$M$69,MATCH(E51,'2025_actual'!$A$59:$A$69,0),MATCH(C51,'2025_actual'!$B$58:$M$58,0)), 2026,INDEX('2026_actual'!$B$59:$M$69,MATCH(E51,'2026_actual'!$A$59:$A$69,0),MATCH(C51,'2026_actual'!$B$58:$M$58,0)) )} -> 211950 | H51: =G51-F51 -> -133.33333 | I51: =IF(AND(E51="Operating Profit",F51<=0),NA(),IFERROR(H51/F51,0)) -> -0.00062868369 | J51: =IF(G51<=F51,"F","U") -> F
A52: 45444 | B52: 2024 | C52: Jun | D52: Customer Success | E52: Customer Success Expenses | F52: {=_xlfn.SWITCH(B52, 2024,INDEX('2024_budget'!$B$59:$M$69,MATCH(E52,'2024_budget'!$A$59:$A$69,0),MATCH(C52,'2024_budget'!$B$58:$M$58,0)), 2025,INDEX('2025_budget'!$B$59:$M$69,MATCH(E52,'2025_budget'!$A$59:$A$69,0),MATCH(C52,'2025_budget'!$B$58:$M$58,0)), 2026,INDEX('2026_budget'!$B$59:$M$69,MATCH(E52,'2026_budget'!$A$59:$A$69,0),MATCH(C52,'2026_budget'!$B$58:$M$58,0)) )} -> 267500 | G52: {=_xlfn.SWITCH(B52, 2024,INDEX('2024_actual'!$B$59:$M$69,MATCH(E52,'2024_actual'!$A$59:$A$69,0),MATCH(C52,'2024_actual'!$B$58:$M$58,0)), 2025,INDEX('2025_actual'!$B$59:$M$69,MATCH(E52,'2025_actual'!$A$59:$A$69,0),MATCH(C52,'2025_actual'!$B$58:$M$58,0)), 2026,INDEX('2026_actual'!$B$59:$M$69,MATCH(E52,'2026_actual'!$A$59:$A$69,0),MATCH(C52,'2026_actual'!$B$58:$M$58,0)) )} -> 265200 | H52: =G52-F52 -> -2300 | I52: =IF(AND(E52="Operating Profit",F52<=0),NA(),IFERROR(H52/F52,0)) -> -0.0085981308 | J52: =IF(G52<=F52,"F","U") -> F
A53: 45444 | B53: 2024 | C53: Jun | D53: G&A | E53: G&A Expenses | F53: {=_xlfn.SWITCH(B53, 2024,INDEX('2024_budget'!$B$59:$M$69,MATCH(E53,'2024_budget'!$A$59:$A$69,0),MATCH(C53,'2024_budget'!$B$58:$M$58,0)), 2025,INDEX('2025_budget'!$B$59:$M$69,MATCH(E53,'2025_budget'!$A$59:$A$69,0),MATCH(C53,'2025_budget'!$B$58:$M$58,0)), 2026,INDEX('2026_budget'!$B$59:$M$69,MATCH(E53,'2026_budget'!$A$59:$A$69,0),MATCH(C53,'2026_budget'!$B$58:$M$58,0)) )} -> 314583.33 | G53: {=_xlfn.SWITCH(B53, 2024,INDEX('2024_actual'!$B$59:$M$69,MATCH(E53,'2024_actual'!$A$59:$A$69,0),MATCH(C53,'2024_actual'!$B$58:$M$58,0)), 2025,INDEX('2025_actual'!$B$59:$M$69,MATCH(E53,'2025_actual'!$A$59:$A$69,0),MATCH(C53,'2025_actual'!$B$58:$M$58,0)), 2026,INDEX('2026_actual'!$B$59:$M$69,MATCH(E53,'2026_actual'!$A$59:$A$69,0),MATCH(C53,'2026_actual'!$B$58:$M$58,0)) )} -> 314350 | H53: =G53-F53 -> -233.33333 | I53: =IF(AND(E53="Operating Profit",F53<=0),NA(),IFERROR(H53/F53,0)) -> -0.00074172185 | J53: =IF(G53<=F53,"F","U") -> F
A54: 45444 | B54: 2024 | C54: Jun | D54: Company | E54: Total Operating Expenses | F54: {=_xlfn.SWITCH(B54, 2024,INDEX('2024_budget'!$B$59:$M$69,MATCH(E54,'2024_budget'!$A$59:$A$69,0),MATCH(C54,'2024_budget'!$B$58:$M$58,0)), 2025,INDEX('2025_budget'!$B$59:$M$69,MATCH(E54,'2025_budget'!$A$59:$A$69,0),MATCH(C54,'2025_budget'!$B$58:$M$58,0)), 2026,INDEX('2026_budget'!$B$59:$M$69,MATCH(E54,'2026_budget'!$A$59:$A$69,0),MATCH(C54,'2026_budget'!$B$58:$M$58,0)) )} -> 2949000 | G54: {=_xlfn.SWITCH(B54, 2024,INDEX('2024_actual'!$B$59:$M$69,MATCH(E54,'2024_actual'!$A$59:$A$69,0),MATCH(C54,'2024_actual'!$B$58:$M$58,0)), 2025,INDEX('2025_actual'!$B$59:$M$69,MATCH(E54,'2025_actual'!$A$59:$A$69,0),MATCH(C54,'2025_actual'!$B$58:$M$58,0)), 2026,INDEX('2026_actual'!$B$59:$M$69,MATCH(E54,'2026_actual'!$A$59:$A$69,0),MATCH(C54,'2026_actual'!$B$58:$M$58,0)) )} -> 2963100 | H54: =G54-F54 -> 14100 | I54: =IF(AND(E54="Operating Profit",F54<=0),NA(),IFERROR(H54/F54,0)) -> 0.0047812818 | J54: =IF(G54<=F54,"F","U") -> U
A55: 45444 | B55: 2024 | C55: Jun | D55: Company | E55: Operating Profit | F55: {=_xlfn.SWITCH(B55, 2024,INDEX('2024_budget'!$B$59:$M$69,MATCH(E55,'2024_budget'!$A$59:$A$69,0),MATCH(C55,'2024_budget'!$B$58:$M$58,0)), 2025,INDEX('2025_budget'!$B$59:$M$69,MATCH(E55,'2025_budget'!$A$59:$A$69,0),MATCH(C55,'2025_budget'!$B$58:$M$58,0)), 2026,INDEX('2026_budget'!$B$59:$M$69,MATCH(E55,'2026_budget'!$A$59:$A$69,0),MATCH(C55,'2026_budget'!$B$58:$M$58,0)) )} -> 251000 | G55: {=_xlfn.SWITCH(B55, 2024,INDEX('2024_actual'!$B$59:$M$69,MATCH(E55,'2024_actual'!$A$59:$A$69,0),MATCH(C55,'2024_actual'!$B$58:$M$58,0)), 2025,INDEX('2025_actual'!$B$59:$M$69,MATCH(E55,'2025_actual'!$A$59:$A$69,0),MATCH(C55,'2025_actual'!$B$58:$M$58,0)), 2026,INDEX('2026_actual'!$B$59:$M$69,MATCH(E55,'2026_actual'!$A$59:$A$69,0),MATCH(C55,'2026_actual'!$B$58:$M$58,0)) )} -> 171900 | H55: =G55-F55 -> -79100 | I55: =IF(AND(E55="Operating Profit",F55<=0),NA(),IFERROR(H55/F55,0)) -> -0.31513944 | J55: =IF(G55>=F55,"F","U") -> U
A56: 45474 | B56: 2024 | C56: Jul | D56: Company | E56: Total Revenue | F56: {=_xlfn.SWITCH(B56, 2024,INDEX('2024_budget'!$B$59:$M$69,MATCH(E56,'2024_budget'!$A$59:$A$69,0),MATCH(C56,'2024_budget'!$B$58:$M$58,0)), 2025,INDEX('2025_budget'!$B$59:$M$69,MATCH(E56,'2025_budget'!$A$59:$A$69,0),MATCH(C56,'2025_budget'!$B$58:$M$58,0)), 2026,INDEX('2026_budget'!$B$59:$M$69,MATCH(E56,'2026_budget'!$A$59:$A$69,0),MATCH(C56,'2026_budget'!$B$58:$M$58,0)) )} -> 3200000 | G56: {=_xlfn.SWITCH(B56, 2024,INDEX('2024_actual'!$B$59:$M$69,MATCH(E56,'2024_actual'!$A$59:$A$69,0),MATCH(C56,'2024_actual'!$B$58:$M$58,0)), 2025,INDEX('2025_actual'!$B$59:$M$69,MATCH(E56,'2025_actual'!$A$59:$A$69,0),MATCH(C56,'2025_actual'!$B$58:$M$58,0)), 2026,INDEX('2026_actual'!$B$59:$M$69,MATCH(E56,'2026_actual'!$A$59:$A$69,0),MATCH(C56,'2026_actual'!$B$58:$M$58,0)) )} -> 3160000 | H56: =G56-F56 -> -40000 | I56: =IF(AND(E56="Operating Profit",F56<=0),NA(),IFERROR(H56/F56,0)) -> -0.0125 | J56: =IF(G56>=F56,"F","U") -> U
A57: 45474 | B57: 2024 | C57: Jul | D57: Sales | E57: Sales Expenses | F57: {=_xlfn.SWITCH(B57, 2024,INDEX('2024_budget'!$B$59:$M$69,MATCH(E57,'2024_budget'!$A$59:$A$69,0),MATCH(C57,'2024_budget'!$B$58:$M$58,0)), 2025,INDEX('2025_budget'!$B$59:$M$69,MATCH(E57,'2025_budget'!$A$59:$A$69,0),MATCH(C57,'2025_budget'!$B$58:$M$58,0)), 2026,INDEX('2026_budget'!$B$59:$M$69,MATCH(E57,'2026_budget'!$A$59:$A$69,0),MATCH(C57,'2026_budget'!$B$58:$M$58,0)) )} -> 673166.67 | G57: {=_xlfn.SWITCH(B57, 2024,INDEX('2024_actual'!$B$59:$M$69,MATCH(E57,'2024_actual'!$A$59:$A$69,0),MATCH(C57,'2024_actual'!$B$58:$M$58,0)), 2025,INDEX('2025_actual'!$B$59:$M$69,MATCH(E57,'2025_actual'!$A$59:$A$69,0),MATCH(C57,'2025_actual'!$B$58:$M$58,0)), 2026,INDEX('2026_actual'!$B$59:$M$69,MATCH(E57,'2026_actual'!$A$59:$A$69,0),MATCH(C57,'2026_actual'!$B$58:$M$58,0)) )} -> 663000 | H57: =G57-F57 -> -10166.667 | I57: =IF(AND(E57="Operating Profit",F57<=0),NA(),IFERROR(H57/F57,0)) -> -0.015102748 | J57: =IF(G57<=F57,"F","U") -> F
A58: 45474 | B58: 2024 | C58: Jul | D58: Marketing | E58: Marketing Expenses | F58: {=_xlfn.SWITCH(B58, 2024,INDEX('2024_budget'!$B$59:$M$69,MATCH(E58,'2024_budget'!$A$59:$A$69,0),MATCH(C58,'2024_budget'!$B$58:$M$58,0)), 2025,INDEX('2025_budget'!$B$59:$M$69,MATCH(E58,'2025_budget'!$A$59:$A$69,0),MATCH(C58,'2025_budget'!$B$58:$M$58,0)), 2026,INDEX('2026_budget'!$B$59:$M$69,MATCH(E58,'2026_budget'!$A$59:$A$69,0),MATCH(C58,'2026_budget'!$B$58:$M$58,0)) )} -> 391166.67 | G58: {=_xlfn.SWITCH(B58, 2024,INDEX('2024_actual'!$B$59:$M$69,MATCH(E58,'2024_actual'!$A$59:$A$69,0),MATCH(C58,'2024_actual'!$B$58:$M$58,0)), 2025,INDEX('2025_actual'!$B$59:$M$69,MATCH(E58,'2025_actual'!$A$59:$A$69,0),MATCH(C58,'2025_actual'!$B$58:$M$58,0)), 2026,INDEX('2026_actual'!$B$59:$M$69,MATCH(E58,'2026_actual'!$A$59:$A$69,0),MATCH(C58,'2026_actual'!$B$58:$M$58,0)) )} -> 414800 | H58: =G58-F58 -> 23633.333 | I58: =IF(AND(E58="Operating Profit",F58<=0),NA(),IFERROR(H58/F58,0)) -> 0.060417554 | J58: =IF(G58<=F58,"F","U") -> U
A59: 45474 | B59: 2024 | C59: Jul | D59: Engineering | E59: Engineering Expenses | F59: {=_xlfn.SWITCH(B59, 2024,INDEX('2024_budget'!$B$59:$M$69,MATCH(E59,'2024_budget'!$A$59:$A$69,0),MATCH(C59,'2024_budget'!$B$58:$M$58,0)), 2025,INDEX('2025_budget'!$B$59:$M$69,MATCH(E59,'2025_budget'!$A$59:$A$69,0),MATCH(C59,'2025_budget'!$B$58:$M$58,0)), 2026,INDEX('2026_budget'!$B$59:$M$69,MATCH(E59,'2026_budget'!$A$59:$A$69,0),MATCH(C59,'2026_budget'!$B$58:$M$58,0)) )} -> 1090500 | G59: {=_xlfn.SWITCH(B59, 2024,INDEX('2024_actual'!$B$59:$M$69,MATCH(E59,'2024_actual'!$A$59:$A$69,0),MATCH(C59,'2024_actual'!$B$58:$M$58,0)), 2025,INDEX('2025_actual'!$B$59:$M$69,MATCH(E59,'2025_actual'!$A$59:$A$69,0),MATCH(C59,'2025_actual'!$B$58:$M$58,0)), 2026,INDEX('2026_actual'!$B$59:$M$69,MATCH(E59,'2026_actual'!$A$59:$A$69,0),MATCH(C59,'2026_actual'!$B$58:$M$58,0)) )} -> 1110000 | H59: =G59-F59 -> 19500 | I59: =IF(AND(E59="Operating Profit",F59<=0),NA(),IFERROR(H59/F59,0)) -> 0.017881706 | J59: =IF(G59<=F59,"F","U") -> U
A60: 45474 | B60: 2024 | C60: Jul | D60: Product | E60: Product Expenses | F60: {=_xlfn.SWITCH(B60, 2024,INDEX('2024_budget'!$B$59:$M$69,MATCH(E60,'2024_budget'!$A$59:$A$69,0),MATCH(C60,'2024_budget'!$B$58:$M$58,0)), 2025,INDEX('2025_budget'!$B$59:$M$69,MATCH(E60,'2025_budget'!$A$59:$A$69,0),MATCH(C60,'2025_budget'!$B$58:$M$58,0)), 2026,INDEX('2026_budget'!$B$59:$M$69,MATCH(E60,'2026_budget'!$A$59:$A$69,0),MATCH(C60,'2026_budget'!$B$58:$M$58,0)) )} -> 212083.33 | G60: {=_xlfn.SWITCH(B60, 2024,INDEX('2024_actual'!$B$59:$M$69,MATCH(E60,'2024_actual'!$A$59:$A$69,0),MATCH(C60,'2024_actual'!$B$58:$M$58,0)), 2025,INDEX('2025_actual'!$B$59:$M$69,MATCH(E60,'2025_actual'!$A$59:$A$69,0),MATCH(C60,'2025_actual'!$B$58:$M$58,0)), 2026,INDEX('2026_actual'!$B$59:$M$69,MATCH(E60,'2026_actual'!$A$59:$A$69,0),MATCH(C60,'2026_actual'!$B$58:$M$58,0)) )} -> 212950 | H60: =G60-F60 -> 866.66667 | I60: =IF(AND(E60="Operating Profit",F60<=0),NA(),IFERROR(H60/F60,0)) -> 0.004086444 | J60: =IF(G60<=F60,"F","U") -> U
A61: 45474 | B61: 2024 | C61: Jul | D61: Customer Success | E61: Customer Success Expenses | F61: {=_xlfn.SWITCH(B61, 2024,INDEX('2024_budget'!$B$59:$M$69,MATCH(E61,'2024_budget'!$A$59:$A$69,0),MATCH(C61,'2024_budget'!$B$58:$M$58,0)), 2025,INDEX('2025_budget'!$B$59:$M$69,MATCH(E61,'2025_budget'!$A$59:$A$69,0),MATCH(C61,'2025_budget'!$B$58:$M$58,0)), 2026,INDEX('2026_budget'!$B$59:$M$69,MATCH(E61,'2026_budget'!$A$59:$A$69,0),MATCH(C61,'2026_budget'!$B$58:$M$58,0)) )} -> 267500 | G61: {=_xlfn.SWITCH(B61, 2024,INDEX('2024_actual'!$B$59:$M$69,MATCH(E61,'2024_actual'!$A$59:$A$69,0),MATCH(C61,'2024_actual'!$B$58:$M$58,0)), 2025,INDEX('2025_actual'!$B$59:$M$69,MATCH(E61,'2025_actual'!$A$59:$A$69,0),MATCH(C61,'2025_actual'!$B$58:$M$58,0)), 2026,INDEX('2026_actual'!$B$59:$M$69,MATCH(E61,'2026_actual'!$A$59:$A$69,0),MATCH(C61,'2026_actual'!$B$58:$M$58,0)) )} -> 266900 | H61: =G61-F61 -> -600 | I61: =IF(AND(E61="Operating Profit",F61<=0),NA(),IFERROR(H61/F61,0)) -> -0.0022429907 | J61: =IF(G61<=F61,"F","U") -> F
A62: 45474 | B62: 2024 | C62: Jul | D62: G&A | E62: G&A Expenses | F62: {=_xlfn.SWITCH(B62, 2024,INDEX('2024_budget'!$B$59:$M$69,MATCH(E62,'2024_budget'!$A$59:$A$69,0),MATCH(C62,'2024_budget'!$B$58:$M$58,0)), 2025,INDEX('2025_budget'!$B$59:$M$69,MATCH(E62,'2025_budget'!$A$59:$A$69,0),MATCH(C62,'2025_budget'!$B$58:$M$58,0)), 2026,INDEX('2026_budget'!$B$59:$M$69,MATCH(E62,'2026_budget'!$A$59:$A$69,0),MATCH(C62,'2026_budget'!$B$58:$M$58,0)) )} -> 314583.33 | G62: {=_xlfn.SWITCH(B62, 2024,INDEX('2024_actual'!$B$59:$M$69,MATCH(E62,'2024_actual'!$A$59:$A$69,0),MATCH(C62,'2024_actual'!$B$58:$M$58,0)), 2025,INDEX('2025_actual'!$B$59:$M$69,MATCH(E62,'2025_actual'!$A$59:$A$69,0),MATCH(C62,'2025_actual'!$B$58:$M$58,0)), 2026,INDEX('2026_actual'!$B$59:$M$69,MATCH(E62,'2026_actual'!$A$59:$A$69,0),MATCH(C62,'2026_actual'!$B$58:$M$58,0)) )} -> 316550 | H62: =G62-F62 -> 1966.6667 | I62: =IF(AND(E62="Operating Profit",F62<=0),NA(),IFERROR(H62/F62,0)) -> 0.0062516556 | J62: =IF(G62<=F62,"F","U") -> U
A63: 45474 | B63: 2024 | C63: Jul | D63: Company | E63: Total Operating Expenses | F63: {=_xlfn.SWITCH(B63, 2024,INDEX('2024_budget'!$B$59:$M$69,MATCH(E63,'2024_budget'!$A$59:$A$69,0),MATCH(C63,'2024_budget'!$B$58:$M$58,0)), 2025,INDEX('2025_budget'!$B$59:$M$69,MATCH(E63,'2025_budget'!$A$59:$A$69,0),MATCH(C63,'2025_budget'!$B$58:$M$58,0)), 2026,INDEX('2026_budget'!$B$59:$M$69,MATCH(E63,'2026_budget'!$A$59:$A$69,0),MATCH(C63,'2026_budget'!$B$58:$M$58,0)) )} -> 2949000 | G63: {=_xlfn.SWITCH(B63, 2024,INDEX('2024_actual'!$B$59:$M$69,MATCH(E63,'2024_actual'!$A$59:$A$69,0),MATCH(C63,'2024_actual'!$B$58:$M$58,0)), 2025,INDEX('2025_actual'!$B$59:$M$69,MATCH(E63,'2025_actual'!$A$59:$A$69,0),MATCH(C63,'2025_actual'!$B$58:$M$58,0)), 2026,INDEX('2026_actual'!$B$59:$M$69,MATCH(E63,'2026_actual'!$A$59:$A$69,0),MATCH(C63,'2026_actual'!$B$58:$M$58,0)) )} -> 2984200 | H63: =G63-F63 -> 35200 | I63: =IF(AND(E63="Operating Profit",F63<=0),NA(),IFERROR(H63/F63,0)) -> 0.01193625 | J63: =IF(G63<=F63,"F","U") -> U
A64: 45474 | B64: 2024 | C64: Jul | D64: Company | E64: Operating Profit | F64: {=_xlfn.SWITCH(B64, 2024,INDEX('2024_budget'!$B$59:$M$69,MATCH(E64,'2024_budget'!$A$59:$A$69,0),MATCH(C64,'2024_budget'!$B$58:$M$58,0)), 2025,INDEX('2025_budget'!$B$59:$M$69,MATCH(E64,'2025_budget'!$A$59:$A$69,0),MATCH(C64,'2025_budget'!$B$58:$M$58,0)), 2026,INDEX('2026_budget'!$B$59:$M$69,MATCH(E64,'2026_budget'!$A$59:$A$69,0),MATCH(C64,'2026_budget'!$B$58:$M$58,0)) )} -> 251000 | G64: {=_xlfn.SWITCH(B64, 2024,INDEX('2024_actual'!$B$59:$M$69,MATCH(E64,'2024_actual'!$A$59:$A$69,0),MATCH(C64,'2024_actual'!$B$58:$M$58,0)), 2025,INDEX('2025_actual'!$B$59:$M$69,MATCH(E64,'2025_actual'!$A$59:$A$69,0),MATCH(C64,'2025_actual'!$B$58:$M$58,0)), 2026,INDEX('2026_actual'!$B$59:$M$69,MATCH(E64,'2026_actual'!$A$59:$A$69,0),MATCH(C64,'2026_actual'!$B$58:$M$58,0)) )} -> 175800 | H64: =G64-F64 -> -75200 | I64: =IF(AND(E64="Operating Profit",F64<=0),NA(),IFERROR(H64/F64,0)) -> -0.29960159 | J64: =IF(G64>=F64,"F","U") -> U
A65: 45505 | B65: 2024 | C65: Aug | D65: Company | E65: Total Revenue | F65: {=_xlfn.SWITCH(B65, 2024,INDEX('2024_budget'!$B$59:$M$69,MATCH(E65,'2024_budget'!$A$59:$A$69,0),MATCH(C65,'2024_budget'!$B$58:$M$58,0)), 2025,INDEX('2025_budget'!$B$59:$M$69,MATCH(E65,'2025_budget'!$A$59:$A$69,0),MATCH(C65,'2025_budget'!$B$58:$M$58,0)), 2026,INDEX('2026_budget'!$B$59:$M$69,MATCH(E65,'2026_budget'!$A$59:$A$69,0),MATCH(C65,'2026_budget'!$B$58:$M$58,0)) )} -> 3200000 | G65: {=_xlfn.SWITCH(B65, 2024,INDEX('2024_actual'!$B$59:$M$69,MATCH(E65,'2024_actual'!$A$59:$A$69,0),MATCH(C65,'2024_actual'!$B$58:$M$58,0)), 2025,INDEX('2025_actual'!$B$59:$M$69,MATCH(E65,'2025_actual'!$A$59:$A$69,0),MATCH(C65,'2025_actual'!$B$58:$M$58,0)), 2026,INDEX('2026_actual'!$B$59:$M$69,MATCH(E65,'2026_actual'!$A$59:$A$69,0),MATCH(C65,'2026_actual'!$B$58:$M$58,0)) )} -> 3195000 | H65: =G65-F65 -> -5000 | I65: =IF(AND(E65="Operating Profit",F65<=0),NA(),IFERROR(H65/F65,0)) -> -0.0015625 | J65: =IF(G65>=F65,"F","U") -> U
A66: 45505 | B66: 2024 | C66: Aug | D66: Sales | E66: Sales Expenses | F66: {=_xlfn.SWITCH(B66, 2024,INDEX('2024_budget'!$B$59:$M$69,MATCH(E66,'2024_budget'!$A$59:$A$69,0),MATCH(C66,'2024_budget'!$B$58:$M$58,0)), 2025,INDEX('2025_budget'!$B$59:$M$69,MATCH(E66,'2025_budget'!$A$59:$A$69,0),MATCH(C66,'2025_budget'!$B$58:$M$58,0)), 2026,INDEX('2026_budget'!$B$59:$M$69,MATCH(E66,'2026_budget'!$A$59:$A$69,0),MATCH(C66,'2026_budget'!$B$58:$M$58,0)) )} -> 673166.67 | G66: {=_xlfn.SWITCH(B66, 2024,INDEX('2024_actual'!$B$59:$M$69,MATCH(E66,'2024_actual'!$A$59:$A$69,0),MATCH(C66,'2024_actual'!$B$58:$M$58,0)), 2025,INDEX('2025_actual'!$B$59:$M$69,MATCH(E66,'2025_actual'!$A$59:$A$69,0),MATCH(C66,'2025_actual'!$B$58:$M$58,0)), 2026,INDEX('2026_actual'!$B$59:$M$69,MATCH(E66,'2026_actual'!$A$59:$A$69,0),MATCH(C66,'2026_actual'!$B$58:$M$58,0)) )} -> 664500 | H66: =G66-F66 -> -8666.6667 | I66: =IF(AND(E66="Operating Profit",F66<=0),NA(),IFERROR(H66/F66,0)) -> -0.012874474 | J66: =IF(G66<=F66,"F","U") -> F
A67: 45505 | B67: 2024 | C67: Aug | D67: Marketing | E67: Marketing Expenses | F67: {=_xlfn.SWITCH(B67, 2024,INDEX('2024_budget'!$B$59:$M$69,MATCH(E67,'2024_budget'!$A$59:$A$69,0),MATCH(C67,'2024_budget'!$B$58:$M$58,0)), 2025,INDEX('2025_budget'!$B$59:$M$69,MATCH(E67,'2025_budget'!$A$59:$A$69,0),MATCH(C67,'2025_budget'!$B$58:$M$58,0)), 2026,INDEX('2026_budget'!$B$59:$M$69,MATCH(E67,'2026_budget'!$A$59:$A$69,0),MATCH(C67,'2026_budget'!$B$58:$M$58,0)) )} -> 391166.67 | G67: {=_xlfn.SWITCH(B67, 2024,INDEX('2024_actual'!$B$59:$M$69,MATCH(E67,'2024_actual'!$A$59:$A$69,0),MATCH(C67,'2024_actual'!$B$58:$M$58,0)), 2025,INDEX('2025_actual'!$B$59:$M$69,MATCH(E67,'2025_actual'!$A$59:$A$69,0),MATCH(C67,'2025_actual'!$B$58:$M$58,0)), 2026,INDEX('2026_actual'!$B$59:$M$69,MATCH(E67,'2026_actual'!$A$59:$A$69,0),MATCH(C67,'2026_actual'!$B$58:$M$58,0)) )} -> 420300 | H67: =G67-F67 -> 29133.333 | I67: =IF(AND(E67="Operating Profit",F67<=0),NA(),IFERROR(H67/F67,0)) -> 0.074478057 | J67: =IF(G67<=F67,"F","U") -> U
A68: 45505 | B68: 2024 | C68: Aug | D68: Engineering | E68: Engineering Expenses | F68: {=_xlfn.SWITCH(B68, 2024,INDEX('2024_budget'!$B$59:$M$69,MATCH(E68,'2024_budget'!$A$59:$A$69,0),MATCH(C68,'2024_budget'!$B$58:$M$58,0)), 2025,INDEX('2025_budget'!$B$59:$M$69,MATCH(E68,'2025_budget'!$A$59:$A$69,0),MATCH(C68,'2025_budget'!$B$58:$M$58,0)), 2026,INDEX('2026_budget'!$B$59:$M$69,MATCH(E68,'2026_budget'!$A$59:$A$69,0),MATCH(C68,'2026_budget'!$B$58:$M$58,0)) )} -> 1090500 | G68: {=_xlfn.SWITCH(B68, 2024,INDEX('2024_actual'!$B$59:$M$69,MATCH(E68,'2024_actual'!$A$59:$A$69,0),MATCH(C68,'2024_actual'!$B$58:$M$58,0)), 2025,INDEX('2025_actual'!$B$59:$M$69,MATCH(E68,'2025_actual'!$A$59:$A$69,0),MATCH(C68,'2025_actual'!$B$58:$M$58,0)), 2026,INDEX('2026_actual'!$B$59:$M$69,MATCH(E68,'2026_actual'!$A$59:$A$69,0),MATCH(C68,'2026_actual'!$B$58:$M$58,0)) )} -> 1113000 | H68: =G68-F68 -> 22500 | I68: =IF(AND(E68="Operating Profit",F68<=0),NA(),IFERROR(H68/F68,0)) -> 0.020632737 | J68: =IF(G68<=F68,"F","U") -> U
A69: 45505 | B69: 2024 | C69: Aug | D69: Product | E69: Product Expenses | F69: {=_xlfn.SWITCH(B69, 2024,INDEX('2024_budget'!$B$59:$M$69,MATCH(E69,'2024_budget'!$A$59:$A$69,0),MATCH(C69,'2024_budget'!$B$58:$M$58,0)), 2025,INDEX('2025_budget'!$B$59:$M$69,MATCH(E69,'2025_budget'!$A$59:$A$69,0),MATCH(C69,'2025_budget'!$B$58:$M$58,0)), 2026,INDEX('2026_budget'!$B$59:$M$69,MATCH(E69,'2026_budget'!$A$59:$A$69,0),MATCH(C69,'2026_budget'!$B$58:$M$58,0)) )} -> 212083.33 | G69: {=_xlfn.SWITCH(B69, 2024,INDEX('2024_actual'!$B$59:$M$69,MATCH(E69,'2024_actual'!$A$59:$A$69,0),MATCH(C69,'2024_actual'!$B$58:$M$58,0)), 2025,INDEX('2025_actual'!$B$59:$M$69,MATCH(E69,'2025_actual'!$A$59:$A$69,0),MATCH(C69,'2025_actual'!$B$58:$M$58,0)), 2026,INDEX('2026_actual'!$B$59:$M$69,MATCH(E69,'2026_actual'!$A$59:$A$69,0),MATCH(C69,'2026_actual'!$B$58:$M$58,0)) )} -> 212950 | H69: =G69-F69 -> 866.66667 | I69: =IF(AND(E69="Operating Profit",F69<=0),NA(),IFERROR(H69/F69,0)) -> 0.004086444 | J69: =IF(G69<=F69,"F","U") -> U
A70: 45505 | B70: 2024 | C70: Aug | D70: Customer Success | E70: Customer Success Expenses | F70: {=_xlfn.SWITCH(B70, 2024,INDEX('2024_budget'!$B$59:$M$69,MATCH(E70,'2024_budget'!$A$59:$A$69,0),MATCH(C70,'2024_budget'!$B$58:$M$58,0)), 2025,INDEX('2025_budget'!$B$59:$M$69,MATCH(E70,'2025_budget'!$A$59:$A$69,0),MATCH(C70,'2025_budget'!$B$58:$M$58,0)), 2026,INDEX('2026_budget'!$B$59:$M$69,MATCH(E70,'2026_budget'!$A$59:$A$69,0),MATCH(C70,'2026_budget'!$B$58:$M$58,0)) )} -> 267500 | G70: {=_xlfn.SWITCH(B70, 2024,INDEX('2024_actual'!$B$59:$M$69,MATCH(E70,'2024_actual'!$A$59:$A$69,0),MATCH(C70,'2024_actual'!$B$58:$M$58,0)), 2025,INDEX('2025_actual'!$B$59:$M$69,MATCH(E70,'2025_actual'!$A$59:$A$69,0),MATCH(C70,'2025_actual'!$B$58:$M$58,0)), 2026,INDEX('2026_actual'!$B$59:$M$69,MATCH(E70,'2026_actual'!$A$59:$A$69,0),MATCH(C70,'2026_actual'!$B$58:$M$58,0)) )} -> 266900 | H70: =G70-F70 -> -600 | I70: =IF(AND(E70="Operating Profit",F70<=0),NA(),IFERROR(H70/F70,0)) -> -0.0022429907 | J70: =IF(G70<=F70,"F","U") -> F
A71: 45505 | B71: 2024 | C71: Aug | D71: G&A | E71: G&A Expenses | F71: {=_xlfn.SWITCH(B71, 2024,INDEX('2024_budget'!$B$59:$M$69,MATCH(E71,'2024_budget'!$A$59:$A$69,0),MATCH(C71,'2024_budget'!$B$58:$M$58,0)), 2025,INDEX('2025_budget'!$B$59:$M$69,MATCH(E71,'2025_budget'!$A$59:$A$69,0),MATCH(C71,'2025_budget'!$B$58:$M$58,0)), 2026,INDEX('2026_budget'!$B$59:$M$69,MATCH(E71,'2026_budget'!$A$59:$A$69,0),MATCH(C71,'2026_budget'!$B$58:$M$58,0)) )} -> 314583.33 | G71: {=_xlfn.SWITCH(B71, 2024,INDEX('2024_actual'!$B$59:$M$69,MATCH(E71,'2024_actual'!$A$59:$A$69,0),MATCH(C71,'2024_actual'!$B$58:$M$58,0)), 2025,INDEX('2025_actual'!$B$59:$M$69,MATCH(E71,'2025_actual'!$A$59:$A$69,0),MATCH(C71,'2025_actual'!$B$58:$M$58,0)), 2026,INDEX('2026_actual'!$B$59:$M$69,MATCH(E71,'2026_actual'!$A$59:$A$69,0),MATCH(C71,'2026_actual'!$B$58:$M$58,0)) )} -> 316550 | H71: =G71-F71 -> 1966.6667 | I71: =IF(AND(E71="Operating Profit",F71<=0),NA(),IFERROR(H71/F71,0)) -> 0.0062516556 | J71: =IF(G71<=F71,"F","U") -> U
A72: 45505 | B72: 2024 | C72: Aug | D72: Company | E72: Total Operating Expenses | F72: {=_xlfn.SWITCH(B72, 2024,INDEX('2024_budget'!$B$59:$M$69,MATCH(E72,'2024_budget'!$A$59:$A$69,0),MATCH(C72,'2024_budget'!$B$58:$M$58,0)), 2025,INDEX('2025_budget'!$B$59:$M$69,MATCH(E72,'2025_budget'!$A$59:$A$69,0),MATCH(C72,'2025_budget'!$B$58:$M$58,0)), 2026,INDEX('2026_budget'!$B$59:$M$69,MATCH(E72,'2026_budget'!$A$59:$A$69,0),MATCH(C72,'2026_budget'!$B$58:$M$58,0)) )} -> 2949000 | G72: {=_xlfn.SWITCH(B72, 2024,INDEX('2024_actual'!$B$59:$M$69,MATCH(E72,'2024_actual'!$A$59:$A$69,0),MATCH(C72,'2024_actual'!$B$58:$M$58,0)), 2025,INDEX('2025_actual'!$B$59:$M$69,MATCH(E72,'2025_actual'!$A$59:$A$69,0),MATCH(C72,'2025_actual'!$B$58:$M$58,0)), 2026,INDEX('2026_actual'!$B$59:$M$69,MATCH(E72,'2026_actual'!$A$59:$A$69,0),MATCH(C72,'2026_actual'!$B$58:$M$58,0)) )} -> 2994200 | H72: =G72-F72 -> 45200 | I72: =IF(AND(E72="Operating Profit",F72<=0),NA(),IFERROR(H72/F72,0)) -> 0.01532723 | J72: =IF(G72<=F72,"F","U") -> U
A73: 45505 | B73: 2024 | C73: Aug | D73: Company | E73: Operating Profit | F73: {=_xlfn.SWITCH(B73, 2024,INDEX('2024_budget'!$B$59:$M$69,MATCH(E73,'2024_budget'!$A$59:$A$69,0),MATCH(C73,'2024_budget'!$B$58:$M$58,0)), 2025,INDEX('2025_budget'!$B$59:$M$69,MATCH(E73,'2025_budget'!$A$59:$A$69,0),MATCH(C73,'2025_budget'!$B$58:$M$58,0)), 2026,INDEX('2026_budget'!$B$59:$M$69,MATCH(E73,'2026_budget'!$A$59:$A$69,0),MATCH(C73,'2026_budget'!$B$58:$M$58,0)) )} -> 251000 | G73: {=_xlfn.SWITCH(B73, 2024,INDEX('2024_actual'!$B$59:$M$69,MATCH(E73,'2024_actual'!$A$59:$A$69,0),MATCH(C73,'2024_actual'!$B$58:$M$58,0)), 2025,INDEX('2025_actual'!$B$59:$M$69,MATCH(E73,'2025_actual'!$A$59:$A$69,0),MATCH(C73,'2025_actual'!$B$58:$M$58,0)), 2026,INDEX('2026_actual'!$B$59:$M$69,MATCH(E73,'2026_actual'!$A$59:$A$69,0),MATCH(C73,'2026_actual'!$B$58:$M$58,0)) )} -> 200800 | H73: =G73-F73 -> -50200 | I73: =IF(AND(E73="Operating Profit",F73<=0),NA(),IFERROR(H73/F73,0)) -> -0.2 | J73: =IF(G73>=F73,"F","U") -> U
A74: 45536 | B74: 2024 | C74: Sep | D74: Company | E74: Total Revenue | F74: {=_xlfn.SWITCH(B74, 2024,INDEX('2024_budget'!$B$59:$M$69,MATCH(E74,'2024_budget'!$A$59:$A$69,0),MATCH(C74,'2024_budget'!$B$58:$M$58,0)), 2025,INDEX('2025_budget'!$B$59:$M$69,MATCH(E74,'2025_budget'!$A$59:$A$69,0),MATCH(C74,'2025_budget'!$B$58:$M$58,0)), 2026,INDEX('2026_budget'!$B$59:$M$69,MATCH(E74,'2026_budget'!$A$59:$A$69,0),MATCH(C74,'2026_budget'!$B$58:$M$58,0)) )} -> 3600000 | G74: {=_xlfn.SWITCH(B74, 2024,INDEX('2024_actual'!$B$59:$M$69,MATCH(E74,'2024_actual'!$A$59:$A$69,0),MATCH(C74,'2024_actual'!$B$58:$M$58,0)), 2025,INDEX('2025_actual'!$B$59:$M$69,MATCH(E74,'2025_actual'!$A$59:$A$69,0),MATCH(C74,'2025_actual'!$B$58:$M$58,0)), 2026,INDEX('2026_actual'!$B$59:$M$69,MATCH(E74,'2026_actual'!$A$59:$A$69,0),MATCH(C74,'2026_actual'!$B$58:$M$58,0)) )} -> 3540000 | H74: =G74-F74 -> -60000 | I74: =IF(AND(E74="Operating Profit",F74<=0),NA(),IFERROR(H74/F74,0)) -> -0.016666667 | J74: =IF(G74>=F74,"F","U") -> U
A75: 45536 | B75: 2024 | C75: Sep | D75: Sales | E75: Sales Expenses | F75: {=_xlfn.SWITCH(B75, 2024,INDEX('2024_budget'!$B$59:$M$69,MATCH(E75,'2024_budget'!$A$59:$A$69,0),MATCH(C75,'2024_budget'!$B$58:$M$58,0)), 2025,INDEX('2025_budget'!$B$59:$M$69,MATCH(E75,'2025_budget'!$A$59:$A$69,0),MATCH(C75,'2025_budget'!$B$58:$M$58,0)), 2026,INDEX('2026_budget'!$B$59:$M$69,MATCH(E75,'2026_budget'!$A$59:$A$69,0),MATCH(C75,'2026_budget'!$B$58:$M$58,0)) )} -> 691166.67 | G75: {=_xlfn.SWITCH(B75, 2024,INDEX('2024_actual'!$B$59:$M$69,MATCH(E75,'2024_actual'!$A$59:$A$69,0),MATCH(C75,'2024_actual'!$B$58:$M$58,0)), 2025,INDEX('2025_actual'!$B$59:$M$69,MATCH(E75,'2025_actual'!$A$59:$A$69,0),MATCH(C75,'2025_actual'!$B$58:$M$58,0)), 2026,INDEX('2026_actual'!$B$59:$M$69,MATCH(E75,'2026_actual'!$A$59:$A$69,0),MATCH(C75,'2026_actual'!$B$58:$M$58,0)) )} -> 687000 | H75: =G75-F75 -> -4166.6667 | I75: =IF(AND(E75="Operating Profit",F75<=0),NA(),IFERROR(H75/F75,0)) -> -0.0060284543 | J75: =IF(G75<=F75,"F","U") -> F
A76: 45536 | B76: 2024 | C76: Sep | D76: Marketing | E76: Marketing Expenses | F76: {=_xlfn.SWITCH(B76, 2024,INDEX('2024_budget'!$B$59:$M$69,MATCH(E76,'2024_budget'!$A$59:$A$69,0),MATCH(C76,'2024_budget'!$B$58:$M$58,0)), 2025,INDEX('2025_budget'!$B$59:$M$69,MATCH(E76,'2025_budget'!$A$59:$A$69,0),MATCH(C76,'2025_budget'!$B$58:$M$58,0)), 2026,INDEX('2026_budget'!$B$59:$M$69,MATCH(E76,'2026_budget'!$A$59:$A$69,0),MATCH(C76,'2026_budget'!$B$58:$M$58,0)) )} -> 415166.67 | G76: {=_xlfn.SWITCH(B76, 2024,INDEX('2024_actual'!$B$59:$M$69,MATCH(E76,'2024_actual'!$A$59:$A$69,0),MATCH(C76,'2024_actual'!$B$58:$M$58,0)), 2025,INDEX('2025_actual'!$B$59:$M$69,MATCH(E76,'2025_actual'!$A$59:$A$69,0),MATCH(C76,'2025_actual'!$B$58:$M$58,0)), 2026,INDEX('2026_actual'!$B$59:$M$69,MATCH(E76,'2026_actual'!$A$59:$A$69,0),MATCH(C76,'2026_actual'!$B$58:$M$58,0)) )} -> 431500 | H76: =G76-F76 -> 16333.333 | I76: =IF(AND(E76="Operating Profit",F76<=0),NA(),IFERROR(H76/F76,0)) -> 0.03934163 | J76: =IF(G76<=F76,"F","U") -> U
A77: 45536 | B77: 2024 | C77: Sep | D77: Engineering | E77: Engineering Expenses | F77: {=_xlfn.SWITCH(B77, 2024,INDEX('2024_budget'!$B$59:$M$69,MATCH(E77,'2024_budget'!$A$59:$A$69,0),MATCH(C77,'2024_budget'!$B$58:$M$58,0)), 2025,INDEX('2025_budget'!$B$59:$M$69,MATCH(E77,'2025_budget'!$A$59:$A$69,0),MATCH(C77,'2025_budget'!$B$58:$M$58,0)), 2026,INDEX('2026_budget'!$B$59:$M$69,MATCH(E77,'2026_budget'!$A$59:$A$69,0),MATCH(C77,'2026_budget'!$B$58:$M$58,0)) )} -> 1106500 | G77: {=_xlfn.SWITCH(B77, 2024,INDEX('2024_actual'!$B$59:$M$69,MATCH(E77,'2024_actual'!$A$59:$A$69,0),MATCH(C77,'2024_actual'!$B$58:$M$58,0)), 2025,INDEX('2025_actual'!$B$59:$M$69,MATCH(E77,'2025_actual'!$A$59:$A$69,0),MATCH(C77,'2025_actual'!$B$58:$M$58,0)), 2026,INDEX('2026_actual'!$B$59:$M$69,MATCH(E77,'2026_actual'!$A$59:$A$69,0),MATCH(C77,'2026_actual'!$B$58:$M$58,0)) )} -> 1126000 | H77: =G77-F77 -> 19500 | I77: =IF(AND(E77="Operating Profit",F77<=0),NA(),IFERROR(H77/F77,0)) -> 0.017623136 | J77: =IF(G77<=F77,"F","U") -> U
A78: 45536 | B78: 2024 | C78: Sep | D78: Product | E78: Product Expenses | F78: {=_xlfn.SWITCH(B78, 2024,INDEX('2024_budget'!$B$59:$M$69,MATCH(E78,'2024_budget'!$A$59:$A$69,0),MATCH(C78,'2024_budget'!$B$58:$M$58,0)), 2025,INDEX('2025_budget'!$B$59:$M$69,MATCH(E78,'2025_budget'!$A$59:$A$69,0),MATCH(C78,'2025_budget'!$B$58:$M$58,0)), 2026,INDEX('2026_budget'!$B$59:$M$69,MATCH(E78,'2026_budget'!$A$59:$A$69,0),MATCH(C78,'2026_budget'!$B$58:$M$58,0)) )} -> 212083.33 | G78: {=_xlfn.SWITCH(B78, 2024,INDEX('2024_actual'!$B$59:$M$69,MATCH(E78,'2024_actual'!$A$59:$A$69,0),MATCH(C78,'2024_actual'!$B$58:$M$58,0)), 2025,INDEX('2025_actual'!$B$59:$M$69,MATCH(E78,'2025_actual'!$A$59:$A$69,0),MATCH(C78,'2025_actual'!$B$58:$M$58,0)), 2026,INDEX('2026_actual'!$B$59:$M$69,MATCH(E78,'2026_actual'!$A$59:$A$69,0),MATCH(C78,'2026_actual'!$B$58:$M$58,0)) )} -> 216150 | H78: =G78-F78 -> 4066.6667 | I78: =IF(AND(E78="Operating Profit",F78<=0),NA(),IFERROR(H78/F78,0)) -> 0.019174853 | J78: =IF(G78<=F78,"F","U") -> U
A79: 45536 | B79: 2024 | C79: Sep | D79: Customer Success | E79: Customer Success Expenses | F79: {=_xlfn.SWITCH(B79, 2024,INDEX('2024_budget'!$B$59:$M$69,MATCH(E79,'2024_budget'!$A$59:$A$69,0),MATCH(C79,'2024_budget'!$B$58:$M$58,0)), 2025,INDEX('2025_budget'!$B$59:$M$69,MATCH(E79,'2025_budget'!$A$59:$A$69,0),MATCH(C79,'2025_budget'!$B$58:$M$58,0)), 2026,INDEX('2026_budget'!$B$59:$M$69,MATCH(E79,'2026_budget'!$A$59:$A$69,0),MATCH(C79,'2026_budget'!$B$58:$M$58,0)) )} -> 267500 | G79: {=_xlfn.SWITCH(B79, 2024,INDEX('2024_actual'!$B$59:$M$69,MATCH(E79,'2024_actual'!$A$59:$A$69,0),MATCH(C79,'2024_actual'!$B$58:$M$58,0)), 2025,INDEX('2025_actual'!$B$59:$M$69,MATCH(E79,'2025_actual'!$A$59:$A$69,0),MATCH(C79,'2025_actual'!$B$58:$M$58,0)), 2026,INDEX('2026_actual'!$B$59:$M$69,MATCH(E79,'2026_actual'!$A$59:$A$69,0),MATCH(C79,'2026_actual'!$B$58:$M$58,0)) )} -> 268100 | H79: =G79-F79 -> 600 | I79: =IF(AND(E79="Operating Profit",F79<=0),NA(),IFERROR(H79/F79,0)) -> 0.0022429907 | J79: =IF(G79<=F79,"F","U") -> U
A80: 45536 | B80: 2024 | C80: Sep | D80: G&A | E80: G&A Expenses | F80: {=_xlfn.SWITCH(B80, 2024,INDEX('2024_budget'!$B$59:$M$69,MATCH(E80,'2024_budget'!$A$59:$A$69,0),MATCH(C80,'2024_budget'!$B$58:$M$58,0)), 2025,INDEX('2025_budget'!$B$59:$M$69,MATCH(E80,'2025_budget'!$A$59:$A$69,0),MATCH(C80,'2025_budget'!$B$58:$M$58,0)), 2026,INDEX('2026_budget'!$B$59:$M$69,MATCH(E80,'2026_budget'!$A$59:$A$69,0),MATCH(C80,'2026_budget'!$B$58:$M$58,0)) )} -> 314583.33 | G80: {=_xlfn.SWITCH(B80, 2024,INDEX('2024_actual'!$B$59:$M$69,MATCH(E80,'2024_actual'!$A$59:$A$69,0),MATCH(C80,'2024_actual'!$B$58:$M$58,0)), 2025,INDEX('2025_actual'!$B$59:$M$69,MATCH(E80,'2025_actual'!$A$59:$A$69,0),MATCH(C80,'2025_actual'!$B$58:$M$58,0)), 2026,INDEX('2026_actual'!$B$59:$M$69,MATCH(E80,'2026_actual'!$A$59:$A$69,0),MATCH(C80,'2026_actual'!$B$58:$M$58,0)) )} -> 320250 | H80: =G80-F80 -> 5666.6667 | I80: =IF(AND(E80="Operating Profit",F80<=0),NA(),IFERROR(H80/F80,0)) -> 0.018013245 | J80: =IF(G80<=F80,"F","U") -> U
