Workbook

Sheet assumptions
A1: MFR Analytics –– Capital Investment Analysis
A3: Project Assumptions
A4: Assumption | B4: Base Case
A5: Initial Investment | B5: 7500000
A6: Project Life | B6: 5 years
A7: Discount Rate | B7: 0.1
A8: Year 1 Revenue | B8: 3500000
A9: Annual Revenue Growth | B9: 0.2
A10: Gross Margin | B10: 0.7
A11: Annual Fixed Operating Costs | B11: 1000000
A12: Annual Fixed Cost Growth | B12: 0.05
A13: Tax Rate | B13: 0.25
A14: Terminal Value | B14: 1000000
A17: Decision Criteria
A18: Minimum Required IRR | B18: 0.1
A19: Maximum Payback Period | B19: 5 years
A20: NPV Requirement | B20: Positive

Sheet financial_projection
A1: 5-Year Financial Projection
A3: Metric | B3: Year 1 | C3: Year 2 | D3: Year 3 | E3: Year 4 | F3: Year 5
A4: Revenue | B4: =assumptions!$B$8 -> 3500000 | C4: =B4*(1+assumptions!$B$9) -> 4200000 | D4: =C4*(1+assumptions!$B$9) -> 5040000 | E4: =D4*(1+assumptions!$B$9) -> 6048000 | F4: =E4*(1+assumptions!$B$9) -> 7257600
A6: Cost of Revenue | B6: =B4*(1-assumptions!$B$10) -> 1050000 | C6: =C4*(1-assumptions!$B$10) -> 1260000 | D6: =D4*(1-assumptions!$B$10) -> 1512000 | E6: =E4*(1-assumptions!$B$10) -> 1814400 | F6: =F4*(1-assumptions!$B$10) -> 2177280
A7: Gross Profit | B7: =B4-B6 -> 2450000 | C7: =C4-C6 -> 2940000 | D7: =D4-D6 -> 3528000 | E7: =E4-E6 -> 4233600 | F7: =F4-F6 -> 5080320
A8: Gross Margin | B8: =B7/B4 -> 0.7 | C8: =C7/C4 -> 0.7 | D8: =D7/D4 -> 0.7 | E8: =E7/E4 -> 0.7 | F8: =F7/F4 -> 0.7
A10: Fixed Operating Costs | B10: =assumptions!$B$11 -> 1000000 | C10: =B10*(1+assumptions!$B$12) -> 1050000 | D10: =C10*(1+assumptions!$B$12) -> 1102500 | E10: =D10*(1+assumptions!$B$12) -> 1157625 | F10: =E10*(1+assumptions!$B$12) -> 1215506.2
A11: Operating Profit | B11: =B7-B10 -> 1450000 | C11: =C7-C10 -> 1890000 | D11: =D7-D10 -> 2425500 | E11: =E7-E10 -> 3075975 | F11: =F7-F10 -> 3864813.8
A12: Operating Margin | B12: =B11/B4 -> 0.41428571 | C12: =C11/C4 -> 0.45 | D12: =D11/D4 -> 0.48125 | E12: =E11/E4 -> 0.50859375 | F12: =F11/F4 -> 0.53251953
A14: Taxes | B14: =MAX(0,B11*assumptions!$B$13) -> 362500 | C14: =MAX(0,C11*assumptions!$B$13) -> 472500 | D14: =MAX(0,D11*assumptions!$B$13) -> 606375 | E14: =MAX(0,E11*assumptions!$B$13) -> 768993.75 | F14: =MAX(0,F11*assumptions!$B$13) -> 966203.44
A15: After-Tax Operating Profit | B15: =B11-B14 -> 1087500 | C15: =C11-C14 -> 1417500 | D15: =D11-D14 -> 1819125 | E15: =E11-E14 -> 2306981.2 | F15: =F11-F14 -> 2898610.3
A18: Metric | B18: Year 0 | C18: Year 1 | D18: Year 2 | E18: Year 3 | F18: Year 4 | G18: Year 5
A19: Initial Investment | B19: =-assumptions!$B$5 -> -7500000 | C19: 0 | D19: 0 | E19: 0 | F19: 0 | G19: 0
A20: After-Tax Operating Profit | B20: 0 | C20: =B15 -> 1087500 | D20: =C15 -> 1417500 | E20: =D15 -> 1819125 | F20: =E15 -> 2306981.2 | G20: =F15 -> 2898610.3
A21: Terminal Value | B21: =0 -> 0 | C21: =0 -> 0 | D21: =0 -> 0 | E21: =0 -> 0 | F21: =0 -> 0 | G21: =assumptions!$B$14 -> 1000000
A22: Project Cash Flow | B22: =SUM(B19:B21) -> -7500000 | C22: =SUM(C19:C21) -> 1087500 | D22: =SUM(D19:D21) -> 1417500 | E22: =SUM(E19:E21) -> 1819125 | F22: =SUM(F19:F21) -> 2306981.2 | G22: =SUM(G19:G21) -> 3898610.3

Sheet investment_analysis
A1: Metric | B1: Result
A2: Initial Investment | B2: =ABS(financial_projection!B19) -> 7500000
A3: NPV | B3: =NPV(assumptions!$B$7,financial_projection!C22:G22)+financial_projection!B22 -> 23289.012
A4: IRR | B4: =IRR(financial_projection!B22:G22) -> 0.10099372
A5: ROI | B5: =(SUM(financial_projection!C22:G22)-ABS(financial_projection!B22))/ABS(financial_projection!B22) -> 0.40396221
A6: Payback Period (years) | B6: =4+ABS(F12)/G11 -> 4.2228727
A7: Decision | B7: Conditional Approval
B10: Year 0 | C10: Year 1 | D10: Year 2 | E10: Year 3 | F10: Year 4 | G10: Year 5
A11: Project Cash Flow | B11: =financial_projection!B22 -> -7500000 | C11: =financial_projection!C22 -> 1087500 | D11: =financial_projection!D22 -> 1417500 | E11: =financial_projection!E22 -> 1819125 | F11: =financial_projection!F22 -> 2306981.2 | G11: =financial_projection!G22 -> 3898610.3
A12: Cumulative Cash Flow | B12: =B11 -> -7500000 | C12: =B12+C11 -> -6412500 | D12: =C12+D11 -> -4995000 | E12: =D12+E11 -> -3175875 | F12: =E12+F11 -> -868893.75 | G12: =F12+G11 -> 3029716.6

Sheet scenario_analysis
A1: Metric | B1: Downside | C1: Base | D1: Upside
A2: Annual Revenue Growth | B2: 0.1 | C2: =assumptions!B9 -> 0.2 | D2: 0.3
A3: Gross Margin | B3: 0.65 | C3: =assumptions!B10 -> 0.7 | D3: 0.75
A4: Discount Rate | B4: 0.1 | C4: =assumptions!B7 -> 0.1 | D4: 0.1
A5: Initial Investment | B5: =7500000 -> 7500000 | C5: =assumptions!B5 -> 7500000 | D5: =7500000 -> 7500000
A8: Metric | B8: Downside | C8: Base | D8: Upside
A9: NPV | B9: =NPV($B$4,C23:G23)-$B$5 -> -2236340.3 | C9: =investment_analysis!B3 -> 23289.012 | D9: =NPV($D$4,C34:G34)+B34 -> 2858377.4
A10: IRR | B10: =IRR(B23:G23) -> -0.0087571478 | C10: =investment_analysis!B4 -> 0.10099372 | D10: =IRR(B34:G34) -> 0.20729579
A11: ROI | B11: =(SUM(C23:G23)-ABS(B23))/ABS(B23) -> -0.030319542 | C11: =investment_analysis!B5 -> 0.40396221 | D11: =(SUM(C34:G34)-ABS(B34))/ABS(B34) -> 0.95458396
A12: Payback Period (years) | B12: > 5 | C12: =investment_analysis!B6 -> 4.2228727 | D12: =3+ABS(E35)/F34 -> 3.5811368
A14: Downside
A15: Metric | B15: Year 0 | C15: Year 1 | D15: Year 2 | E15: Year 3 | F15: Year 4 | G15: Year 5
A16: Revenue | B16: 0 | C16: =assumptions!B8 -> 3500000 | D16: =C16*(1+$B$2) -> 3850000 | E16: =D16*(1+$B$2) -> 4235000 | F16: =E16*(1+$B$2) -> 4658500 | G16: =F16*(1+$B$2) -> 5124350
A17: Gross Profit | B17: 0 | C17: =C16*$B$3 -> 2275000 | D17: =D16*$B$3 -> 2502500 | E17: =E16*$B$3 -> 2752750 | F17: =F16*$B$3 -> 3028025 | G17: =G16*$B$3 -> 3330827.5
A18: Fixed Operating Costs | B18: 0 | C18: =assumptions!$B$11 -> 1000000 | D18: =C18*(1+assumptions!$B$12) -> 1050000 | E18: =D18*(1+assumptions!$B$12) -> 1102500 | F18: =E18*(1+assumptions!$B$12) -> 1157625 | G18: =F18*(1+assumptions!$B$12) -> 1215506.2
A19: Operating Profit | B19: 0 | C19: =C17-C18 -> 1275000 | D19: =D17-D18 -> 1452500 | E19: =E17-E18 -> 1650250 | F19: =F17-F18 -> 1870400 | G19: =G17-G18 -> 2115321.3
A20: Taxes | B20: 0 | C20: =MAX(0,C19*assumptions!$B$13) -> 318750 | D20: =MAX(0,D19*assumptions!$B$13) -> 363125 | E20: =MAX(0,E19*assumptions!$B$13) -> 412562.5 | F20: =MAX(0,F19*assumptions!$B$13) -> 467600 | G20: =MAX(0,G19*assumptions!$B$13) -> 528830.31
A21: After-Tax Operating Profit | B21: 0 | C21: =C19-C20 -> 956250 | D21: =D19-D20 -> 1089375 | E21: =E19-E20 -> 1237687.5 | F21: =F19-F20 -> 1402800 | G21: =G19-G20 -> 1586490.9
A22: Terminal Value | B22: 0 | C22: 0 | D22: 0 | E22: 0 | F22: 0 | G22: =assumptions!$B$14 -> 1000000
A23: Project Cash Flow | B23: =-$B$5 -> -7500000 | C23: =C21+C22 -> 956250 | D23: =D21+D22 -> 1089375 | E23: =E21+E22 -> 1237687.5 | F23: =F21+F22 -> 1402800 | G23: =G21+G22 -> 2586490.9
A25: Upside
A26: Metric | B26: Year 0 | C26: Year 1 | D26: Year 2 | E26: Year 3 | F26: Year 4 | G26: Year 5
A27: Revenue | B27: 0 | C27: =assumptions!B8 -> 3500000 | D27: =C27*(1+$D$2) -> 4550000 | E27: =D27*(1+$D$2) -> 5915000 | F27: =E27*(1+$D$2) -> 7689500 | G27: =F27*(1+$D$2) -> 9996350
A28: Gross Profit | B28: 0 | C28: =C27*$D$3 -> 2625000 | D28: =D27*$D$3 -> 3412500 | E28: =E27*$D$3 -> 4436250 | F28: =F27*$D$3 -> 5767125 | G28: =G27*$D$3 -> 7497262.5
A29: Fixed Operating Costs | B29: 0 | C29: =assumptions!$B$11 -> 1000000 | D29: =C29*(1+assumptions!$B$12) -> 1050000 | E29: =D29*(1+assumptions!$B$12) -> 1102500 | F29: =E29*(1+assumptions!$B$12) -> 1157625 | G29: =F29*(1+assumptions!$B$12) -> 1215506.2
A30: Operating Profit | B30: 0 | C30: =C28-C29 -> 1625000 | D30: =D28-D29 -> 2362500 | E30: =E28-E29 -> 3333750 | F30: =F28-F29 -> 4609500 | G30: =G28-G29 -> 6281756.2
A31: Taxes | B31: 0 | C31: =MAX(0,C30*assumptions!$B$13) -> 406250 | D31: =MAX(0,D30*assumptions!$B$13) -> 590625 | E31: =MAX(0,E30*assumptions!$B$13) -> 833437.5 | F31: =MAX(0,F30*assumptions!$B$13) -> 1152375 | G31: =MAX(0,G30*assumptions!$B$13) -> 1570439.1
A32: After-Tax Operating Profit | B32: 0 | C32: =C30-C31 -> 1218750 | D32: =D30-D31 -> 1771875 | E32: =E30-E31 -> 2500312.5 | F32: =F30-F31 -> 3457125 | G32: =G30-G31 -> 4711317.2
A33: Terminal Value | B33: 0 | C33: 0 | D33: 0 | E33: 0 | F33: 0 | G33: =assumptions!$B$14 -> 1000000
A34: Project Cash Flow | B34: =-$B$5 -> -7500000 | C34: =C32+C33 -> 1218750 | D34: =D32+D33 -> 1771875 | E34: =E32+E33 -> 2500312.5 | F34: =F32+F33 -> 3457125 | G34: =G32+G33 -> 5711317.2
A35: Cumulative Cash Flow | B35: =B34 -> -7500000 | C35: =B35+C34 -> -6281250 | D35: =C35+D34 -> -4509375 | E35: =D35+E34 -> -2009062.5 | F35: =E35+F34 -> 1448062.5 | G35: =F35+G34 -> 7159379.7

Sheet executive_summary
A1: Capital Investment Executive Summary
A3: Investment Recommendation
A4: Decision | B4: Conditional Approval
A5: Initial Investment | B5: =assumptions!B5 -> 7500000
A6: Project Life | B6: =assumptions!B6 -> 5 years
A9: Metric | B9: Base Case
A10: NPV | B10: =investment_analysis!B3 -> 23289.012
A11: IRR | B11: =investment_analysis!B4 -> 0.10099372
A12: ROI | B12: =investment_analysis!B5 -> 0.40396221
A13: Payback Period (years) | B13: =investment_analysis!B6 -> 4.2228727
A16: Management Recommendation
A17: Conditionally approve the $7.5M investment. The base case generates a positive NPV, a 10.1% IRR, and a 4.22-year payback period, meeting the project's minimum investment criteria. However, downside performance indicates material sensitivity to revenue growth and gross margin assumptions.
A20: Scenario Comparison
A21: Metric | B21: Downside | C21: Base | D21: Upside
A22: NPV | B22: =scenario_analysis!B9 -> -2236340.3 | C22: =investment_analysis!B3 -> 23289.012 | D22: =scenario_analysis!D9 -> 2858377.4
A23: IRR | B23: =scenario_analysis!B10 -> -0.0087571478 | C23: =investment_analysis!B4 -> 0.10099372 | D23: =scenario_analysis!D10 -> 0.20729579
A24: ROI | B24: =scenario_analysis!B11 -> -0.030319542 | C24: =investment_analysis!B5 -> 0.40396221 | D24: =scenario_analysis!D11 -> 0.95458396
A25: Payback Period (years) | B25: =scenario_analysis!B12 -> > 5 | C25: =investment_analysis!B6 -> 4.2228727 | D25: =scenario_analysis!D12 -> 3.5811368
A28: Management Insights
A29: 1. Base Case Meets Investment Hurdles The base case generates a positive NPV of $23K and a 10.1% IRR, narrowly exceeding the 10% required return, with payback occurring in 4.22 years.
A30: 2. Downside Risk Is Material Under lower revenue growth and gross margin assumptions, NPV declines to approximately -$2.24M, IRR falls to -0.9%, and the investment does not pay back within the five-year project life.
A31: 3. Upside Provides Significant Value Creation With 30% revenue growth and a 75% gross margin, NPV increases to approximately $2.86M, IRR reaches 20.7%, and payback improves to 3.58 years.
A32: Key Takeaway: The investment is financially viable under the base case but has limited margin for underperformance. Management should proceed conditionally and closely validate revenue growth and gross margin assumptions before committing the full $7.5M investment.
