Workbook

Sheet raw_financials
A1: Netflix Historical Financials
A3: Income Statement ($ millions) | B3: 2023 | C3: 2024 | D3: 2025
A4: Revenue | B4: 33723.297 | C4: 39000.966 | D4: 45183.036
A5: Cost of Revenues | B5: 19715.368 | C5: 21038.464 | D5: 23275.329
A6: Sales & Marketing | B6: 2657.883 | C6: 2917.554 | D6: 3301.306
A7: Technology & Development | B7: 2675.758 | C7: 2925.295 | D7: 3391.39
A8: General & Administrative | B8: 1720.285 | C8: 1702.039 | D8: 1888.408
A9: Operating Income | B9: 6954.003 | C9: 10417.614 | D9: 13326.603
A10: Interest Expense | B10: -699.826 | C10: -718.733 | D10: -776.51
A11: Interest & Other Income (Expense) | B11: -48.772 | C11: 266.776 | D11: 172.459
A12: Income Before Taxes | B12: 6205.405 | C12: 9965.657 | D12: 12722.552
A13: Income Tax Expense | B13: 797.415 | C13: 1254.026 | D13: 1741.351
A14: Net Income | B14: 5407.99 | C14: 8711.631 | D14: 10981.201
... A19: Purchases of Property & Equipment | B19: -348.552 | C19: -439.538 | D19: -688.22
A20: Free Cash Flow | B20: =B18+B19 -> 6925.749 | C20: =C18+C19 -> 6921.826 | D20: =D18+D19 -> 9461.053
A21: Additions to Content Assets | B21: -12554.7 | C21: -16223.62 | D21: -17096.62
A22: Amortization of Content Assets | B22: 14197.44 | C22: 15301.52 | D22: 16422.17
A24: Balance Sheet ($ millions) | B24: 2024 | C24: 2025
A25: Cash & Cash Equivalents | B25: 7804.733 | C25: 9033.681
A26: Short-Term Investments | B26: 1779.006 | C26: 28.678
A27: Other Current Assets | B27: 3516.64 | C27: 3957.832
A28: Total Current Assets | B28: 13100.379 | C28: 13020.191
A29: Content Assets, Net | B29: 32452.462 | C29: 32778.392
A30: Property & Equipment, Net | B30: 1593.756 | C30: 2004.35
A31: Other Non-Current Assets | B31: 6483.777 | C31: 7794.06
A32: Total Assets | B32: 53630.374 | C32: 55596.993
A33: Current Content Liabilities | B33: 4393.681 | C33: 4084.854
A34: Accounts Payable | B34: 899.909 | C34: 900.612
A35: Accrued Expenses & Other Liabilities | B35: 2156.544 | C35: 3220.869
... A44: Total Liabilities & Equity | B44: 53630.374 | C44: 55596.993

Sheet historical_analysis
A1: Netflix Historical Analysis
A3: Metric | B3: 2023 | C3: 2024 | D3: 2025
A4: Revenue Growth | C4: =raw_financials!C4/raw_financials!B4-1 -> 0.1564992 | D4: =raw_financials!D4/raw_financials!C4-1 -> 0.15851069
A5: Gross Profit | B5: =raw_financials!B4-raw_financials!B5 -> 14007.929 | C5: =raw_financials!C4-raw_financials!C5 -> 17962.502 | D5: =raw_financials!D4-raw_financials!D5 -> 21907.707
A6: Gross Margin | B6: =(raw_financials!B4-raw_financials!B5) / raw_financials!B4 -> 0.4153784 | C6: =(raw_financials!C4-raw_financials!C5) / raw_financials!C4 -> 0.46056557 | D6: =(raw_financials!D4-raw_financials!D5) / raw_financials!D4 -> 0.48486576
A7: Operating Margin | B7: =raw_financials!B9/raw_financials!B4 -> 0.20620768 | C7: =raw_financials!C9/raw_financials!C4 -> 0.26711169 | D7: =raw_financials!D9/raw_financials!D4 -> 0.29494705
A8: Net Margin | B8: =raw_financials!B14/raw_financials!B4 -> 0.16036362 | C8: =raw_financials!C14/raw_financials!C4 -> 0.22336962 | D8: =raw_financials!D14/raw_financials!D4 -> 0.24303814
A9: Free Cash Flow | B9: =raw_financials!B20 -> 6925.749 | C9: =raw_financials!C20 -> 6921.826 | D9: =raw_financials!D20 -> 9461.053
A10: FCF Margin | B10: =B9/raw_financials!B4 -> 0.20536987 | C10: =C9/raw_financials!C4 -> 0.17747832 | D10: =D9/raw_financials!D4 -> 0.20939392
A13: Expense Analysis | B13: 2023 | C13: 2024 | D13: 2025
A14: Cost of Revenues % | B14: =raw_financials!B5/raw_financials!B4 -> 0.5846216 | C14: =raw_financials!C5/raw_financials!C4 -> 0.53943443 | D14: =raw_financials!D5/raw_financials!D4 -> 0.51513424
A15: Sales & Marketing % | B15: =raw_financials!B6/raw_financials!B4 -> 0.078814447 | C15: =raw_financials!C6/raw_financials!C4 -> 0.074807224 | D15: =raw_financials!D6/raw_financials!D4 -> 0.073065165
A16: Technology & Development % | B16: =raw_financials!B7/raw_financials!B4 -> 0.079344496 | C16: =raw_financials!C7/raw_financials!C4 -> 0.075005706 | D16: =raw_financials!D7/raw_financials!D4 -> 0.075058923
A17: G&A % | B17: =raw_financials!B8/raw_financials!B4 -> 0.051011768 | C17: =raw_financials!C8/raw_financials!C4 -> 0.043640945 | D17: =raw_financials!D8/raw_financials!D4 -> 0.041794624
A18: Total Operating Expenses % | B18: =SUM(B14:B17) -> 0.79379232 | C18: =SUM(C14:C17) -> 0.73288831 | D18: =SUM(D14:D17) -> 0.70505295
A21: Balance Sheet & Liquidity Analysis | B21: 2023 | C21: 2024 | D21: 2025
A22: Cash & Short-Term Investments | C22: =raw_financials!B25+raw_financials!B26 -> 9583.739 | D22: =raw_financials!C25+raw_financials!C26 -> 9062.359
A23: Total Debt | C23: =raw_financials!B37+raw_financials!B40 -> 15582.804 | D23: =raw_financials!C37+raw_financials!C40 -> 14462.836
A24: Net Debt | C24: =C23-C22 -> 5999.065 | D24: =D23-D22 -> 5400.477
A25: Current Ratio | C25: =raw_financials!B28/raw_financials!B38 -> 1.2180281 | D25: =raw_financials!C28/raw_financials!C38 -> 1.1857093
A26: Debt / Assets | C26: =C23/raw_financials!B32 -> 0.2905593 | D26: =D23/raw_financials!C32 -> 0.26013702
A27: Content Assets / Total Assets | C27: =raw_financials!B29/raw_financials!B32 -> 0.60511348 | D27: =raw_financials!C29/raw_financials!C32 -> 0.58957131
A30: Cash Flow & Content Analysis | B30: 2023 | C30: 2024 | D30: 2025
A31: Operating Cash Flow | B31: =raw_financials!B18 -> 7274.301 | C31: =raw_financials!C18 -> 7361.364 | D31: =raw_financials!D18 -> 10149.273
A32: Operating Cash Flow Growth | C32: =C31/B31-1 -> 0.011968573 | D32: =D31/C31-1 -> 0.3787218
A33: Capital Expenditures | B33: =-raw_financials!B19 -> 348.552 | C33: =-raw_financials!C19 -> 439.538 | D33: =-raw_financials!D19 -> 688.22
A34: Free Cash Flow | B34: =raw_financials!B20 -> 6925.749 | C34: =raw_financials!C20 -> 6921.826 | D34: =raw_financials!D20 -> 9461.053
A35: FCF Growth | C35: =C34/B34-1 -> -0.00056643693 | D35: =D34/C34-1 -> 0.36684352
A36: FCF / Net Income | B36: =B34/raw_financials!B14 -> 1.2806512 | C36: =C34/raw_financials!C14 -> 0.79454995 | D36: =D34/raw_financials!D14 -> 0.86156815
A37: Additions to Content Assets | B37: 12554.7 | C37: 16223.62 | D37: 17096.62
A38: Amortization of Content Assets | B38: 14197.44 | C38: 15301.52 | D38: 16422.17

Sheet revenue_drivers
A1: Netflix Revenue Driver Analysis
A2: Regional Revenue ($ millions) | B2: 2023 | C2: 2024 | D2: 2025
A3: UCAN | B3: 14873.78 | C3: 17359.37 | D3: 19957.15
A4: EMEA | B4: 10556.49 | C4: 12387.04 | D4: 14514.65
A5: LATAM | B5: 4446.46 | C5: 4839.82 | D5: 5357.52
A6: APAC | B6: 3763.73 | C6: 4414.75 | D6: 5353.72
A7: Total Streaming Revenue | B7: 33640.46 | C7: 39000.97 | D7: 45183.04
A10: Regional Revenue Growth | B10: 2023 | C10: 2024 | D10: 2025
A11: UCAN Growth | C11: =C3/B3-1 -> 0.16711219 | D11: =D3/C3-1 -> 0.14964714
A12: EMEA Growth | C12: =C4/B4-1 -> 0.17340518 | D12: =D4/C4-1 -> 0.17176097
A13: LATAM Growth | C13: =C5/B5-1 -> 0.088465881 | D13: =D5/C5-1 -> 0.10696679
A14: APAC Growth | C14: =C6/B6-1 -> 0.17297203 | D14: =D6/C6-1 -> 0.21268928
A15: Total Streaming Revenue Growth | C15: =C7/B7-1 -> 0.15934711 | D15: =D7/C7-1 -> 0.15851067
A18: Revenue Driver | B18: 2025 Evidence | C18: Forecast Implication
A19: Membership Growth | B19: Netflix identified membership growth as a revenue driver | C19: Supports continued revenue growth
A20: Pricing | B20: Netflix identified price increases as a revenue driver | C20: Higher pricing can increase revenue per member
A21: Advertising | B21: Netflix identified increased advertising revenue as a growth driver | C21: Provides an additional revenue growth opportunity
A22: International Growth | B22: APAC +21.3%, EMEA +17.2%, UCAN +15.0%, LATAM +10.7% | C22: International markets, particularly APAC/EMEA, support future growth
A23: Foreign Exchange | B23: FX partially offset reported revenue growth | C23: Creates potential volatility in reported revenue

Sheet forecast_assumptions
A1: Netflix Forecast Assumptions | B1: 2026E | C1: 2027E | D1: 2028E
A2: Revenue Growth | B2: 0.133 | C2: 0.115 | D2: 0.1
A3: Cost of Revenues % of Revenue | B3: 0.495 | C3: 0.485 | D3: 0.475
A4: Sales & Marketing % of Revenue | B4: 0.073 | C4: 0.072 | D4: 0.071
A5: Technology & Development % of Revenue | B5: 0.075 | C5: 0.075 | D5: 0.075
A6: G&A % of Revenue | B6: 0.042 | C6: 0.041 | D6: 0.04
A7: Interest Expense ($M) | B7: 800 | C7: 800 | D7: 800
A8: Tax Rate | B8: 0.13 | C8: 0.13 | D8: 0.13
A9: CapEx % of Revenue | B9: 0.015 | C9: 0.015 | D9: 0.015
A10: FCF Margin | B10: 0.244 | C10: 0.25 | D10: 0.255
A11: Other Income (Expense) | B11: 0 | C11: 0 | D11: 0
A14: Management Guidance / Model Check | B14: 2026E
A15: Revenue Guidance Midpoint ($B) | B15: 51.2
A16: Operating Margin Guidance | B16: 0.315
A17: Free Cash Flow Guidance ($B) | B17: 12.5

Sheet forecast
A1: Netflix Financial Forecast ($ millions) | B1: 2023A | C1: 2024A | D1: 2025A | E1: 2026E | F1: 2027E | G1: 2028E
A2: Revenue | B2: =raw_financials!B4 -> 33723.297 | C2: =raw_financials!C4 -> 39000.966 | D2: =raw_financials!D4 -> 45183.036 | E2: =D2*(1+forecast_assumptions!B2) -> 51192.38 | F2: =E2*(1+forecast_assumptions!C2) -> 57079.503 | G2: =F2*(1+forecast_assumptions!D2) -> 62787.454
A3: Revenue Growth | C3: =historical_analysis!C4 -> 0.1564992 | D3: =historical_analysis!D4 -> 0.15851069 | E3: =forecast_assumptions!B2 -> 0.133 | F3: =forecast_assumptions!C2 -> 0.115 | G3: =forecast_assumptions!D2 -> 0.1
A4: Cost of Revenues | B4: =raw_financials!B5 -> 19715.368 | C4: =raw_financials!C5 -> 21038.464 | D4: =raw_financials!D5 -> 23275.329 | E4: =E2*forecast_assumptions!B3 -> 25340.228 | F4: =F2*forecast_assumptions!C3 -> 27683.559 | G4: =G2*forecast_assumptions!D3 -> 29824.041
A5: Gross Profit | B5: =historical_analysis!B5 -> 14007.929 | C5: =historical_analysis!C5 -> 17962.502 | D5: =historical_analysis!D5 -> 21907.707 | E5: =E2-E4 -> 25852.152 | F5: =F2-F4 -> 29395.944 | G5: =G2-G4 -> 32963.413
A6: Gross Margin | B6: =historical_analysis!B6 -> 0.4153784 | C6: =historical_analysis!C6 -> 0.46056557 | D6: =historical_analysis!D6 -> 0.48486576 | E6: =E5/E2 -> 0.505 | F6: =F5/F2 -> 0.515 | G6: =G5/G2 -> 0.525
A7: Sales & Marketing | B7: =raw_financials!B6 -> 2657.883 | C7: =raw_financials!C6 -> 2917.554 | D7: =raw_financials!D6 -> 3301.306 | E7: =E$2*forecast_assumptions!B4 -> 3737.0437 | F7: =F$2*forecast_assumptions!C4 -> 4109.7242 | G7: =G$2*forecast_assumptions!D4 -> 4457.9092
A8: Technology & Development | B8: =raw_financials!B7 -> 2675.758 | C8: =raw_financials!C7 -> 2925.295 | D8: =raw_financials!D7 -> 3391.39 | E8: =E$2*forecast_assumptions!B5 -> 3839.4285 | F8: =F$2*forecast_assumptions!C5 -> 4280.9628 | G8: =G$2*forecast_assumptions!D5 -> 4709.059
A9: General & Administrative | B9: =raw_financials!B8 -> 1720.285 | C9: =raw_financials!C8 -> 1702.039 | D9: =raw_financials!D8 -> 1888.408 | E9: =E$2*forecast_assumptions!B6 -> 2150.08 | F9: =F$2*forecast_assumptions!C6 -> 2340.2596 | G9: =G$2*forecast_assumptions!D6 -> 2511.4982
A10: Operating Income | B10: =raw_financials!B9 -> 6954.003 | C10: =raw_financials!C9 -> 10417.614 | D10: =raw_financials!D9 -> 13326.603 | E10: =E5-E7-E8-E9 -> 16125.6 | F10: =F5-F7-F8-F9 -> 18664.998 | G10: =G5-G7-G8-G9 -> 21284.947
A11: Operating Margin | B11: =historical_analysis!B7 -> 0.20620768 | C11: =historical_analysis!C7 -> 0.26711169 | D11: =historical_analysis!D7 -> 0.29494705 | E11: =E10/E2 -> 0.315 | F11: =F10/F2 -> 0.327 | G11: =G10/G2 -> 0.339
A12: Interest Expense | B12: =raw_financials!B10 -> -699.826 | C12: =raw_financials!C10 -> -718.733 | D12: =raw_financials!D10 -> -776.51 | E12: =-forecast_assumptions!B7 -> -800 | F12: =-forecast_assumptions!C7 -> -800 | G12: =-forecast_assumptions!D7 -> -800
A13: Other Income (Expense) | B13: =raw_financials!B11 -> -48.772 | C13: =raw_financials!C11 -> 266.776 | D13: =raw_financials!D11 -> 172.459 | E13: =forecast_assumptions!B11 -> 0 | F13: =forecast_assumptions!C11 -> 0 | G13: =forecast_assumptions!D11 -> 0
A14: Income Before Taxes | B14: =raw_financials!B12 -> 6205.405 | C14: =raw_financials!C12 -> 9965.657 | D14: =raw_financials!D12 -> 12722.552 | E14: =E10+E12+E13 -> 15325.6 | F14: =F10+F12+F13 -> 17864.998 | G14: =G10+G12+G13 -> 20484.947
A15: Income Tax Expense | B15: =raw_financials!B13 -> 797.415 | C15: =raw_financials!C13 -> 1254.026 | D15: =raw_financials!D13 -> 1741.351 | E15: =E14*forecast_assumptions!B8 -> 1992.328 | F15: =F14*forecast_assumptions!C8 -> 2322.4497 | G15: =G14*forecast_assumptions!D8 -> 2663.0431
A16: Net Income | B16: =raw_financials!B14 -> 5407.99 | C16: =raw_financials!C14 -> 8711.631 | D16: =raw_financials!D14 -> 10981.201 | E16: =E14-E15 -> 13333.272 | F16: =F14-F15 -> 15542.548 | G16: =G14-G15 -> 17821.904
A17: Net Margin | B17: =historical_analysis!B8 -> 0.16036362 | C17: =historical_analysis!C8 -> 0.22336962 | D17: =historical_analysis!D8 -> 0.24303814 | E17: =E16/E2 -> 0.26045423 | F17: =F16/F2 -> 0.27229648 | G17: =G16/G2 -> 0.28384498
A20: Cash Flow Forecast ($ millions) | B20: 2023A | C20: 2024A | D20: 2025A | E20: 2026E | F20: 2027E | G20: 2028E
A21: Operating Cash Flow | B21: =historical_analysis!B31 -> 7274.301 | C21: =historical_analysis!C31 -> 7361.364 | D21: =historical_analysis!D31 -> 10149.273 | E21: =SUM(E22:E23) -> 13267.886 | F21: =SUM(F22:F23) -> 15126.068 | G21: =SUM(G22:G23) -> 16952.613
A22: Capital Expenditures | B22: =historical_analysis!B33 -> 348.552 | C22: =historical_analysis!C33 -> 439.538 | D22: =historical_analysis!D33 -> 688.22 | E22: =E2*forecast_assumptions!C9 -> 767.8857 | F22: =F2*forecast_assumptions!C9 -> 856.19255 | G22: =forecast_assumptions!D9*G2 -> 941.81181
A23: Free Cash Flow | B23: =historical_analysis!B34 -> 6925.749 | C23: =historical_analysis!C34 -> 6921.826 | D23: =historical_analysis!D34 -> 9461.053 | E23: =forecast_assumptions!B17*1000 -> 12500 | F23: =F2*forecast_assumptions!C10 -> 14269.876 | G23: =G2*forecast_assumptions!D10 -> 16010.801
A24: FCF Margin | B24: =historical_analysis!B10 -> 0.20536987 | C24: =historical_analysis!C10 -> 0.17747832 | D24: =historical_analysis!D10 -> 0.20939392 | E24: =E23/E2 -> 0.24417697 | F24: =F23/F2 -> 0.25 | G24: =G23/G2 -> 0.255

Sheet scenarios
A1: Netflix Scenario Analysis | B1: Bear Case | C1: Base Case | D1: Bull Case
A2: 2027E Revenue Growth | B2: 0.09 | C2: =forecast_assumptions!C2 -> 0.115 | D2: 0.14
A3: 2027E Operating Margin | B3: 0.31 | C3: =forecast!F11 -> 0.327 | D3: 0.34
A4: 2027E FCF Margin | B4: 0.235 | C4: =forecast_assumptions!C10 -> 0.25 | D4: 0.265
A6: 2028E Revenue Growth | B6: 0.07 | C6: =forecast_assumptions!D2 -> 0.1 | D6: 0.13
A7: 2028E Operating Margin | B7: 0.305 | C7: =forecast!G11 -> 0.339 | D7: 0.355
A8: 2028E FCF Margin | B8: 0.23 | C8: =forecast_assumptions!D10 -> 0.255 | D8: 0.275
A11: 2027E Scenario Outputs ($ millions) | B11: Bear Case | C11: Base Case | D11: Bull Case
A12: Revenue | B12: =forecast!$E$2*(1+B2) -> 55799.694 | C12: =forecast!$E$2*(1+C2) -> 57079.503 | D12: =forecast!$E$2*(1+D2) -> 58359.313
A13: Operating Income | B13: =B12*B3 -> 17297.905 | C13: =C12*C3 -> 18664.998 | D13: =D12*D3 -> 19842.166
A14: Free Cash Flow | B14: =B12*B4 -> 13112.928 | C14: =C12*C4 -> 14269.876 | D14: =D12*D4 -> 15465.218
A17: 2028E Scenario Outputs ($ millions) | B17: Bear Case | C17: Base Case | D17: Bull Case
A18: Revenue | B18: =B12*(1+B6) -> 59705.673 | C18: =C12*(1+C6) -> 62787.454 | D18: =D12*(1+D6) -> 65946.024
A19: Operating Income | B19: =B18*B7 -> 18210.23 | C19: =C18*C7 -> 21284.947 | D19: =D18*D7 -> 23410.838
A20: Free Cash Flow | B20: =B18*B8 -> 13732.305 | C20: =C18*C8 -> 16010.801 | D20: =D18*D8 -> 18135.157

Sheet dashboard_data
A1: Revenue
A2: Year | B2: Actual | C2: Forecast
A3: 2023A | B3: =forecast!B$2 -> 33723.297
A4: 2024A | B4: =forecast!C2 -> 39000.966
A5: 2025A | B5: =forecast!$D2 -> 45183.036 | C5: =forecast!$D2 -> 45183.036
A6: 2026E | C6: =forecast!E2 -> 51192.38
A7: 2027E | C7: =forecast!F2 -> 57079.503
A8: 2028E | C8: =forecast!G2 -> 62787.454
A11: Operating Margin
A12: Year | B12: Actual | C12: Forecast
A13: 2023A | B13: =forecast!B11 -> 0.20620768
A14: 2024A | B14: =forecast!C11 -> 0.26711169
A15: 2025A | B15: =forecast!$D$11 -> 0.29494705 | C15: =forecast!$D$11 -> 0.29494705
A16: 2026E | C16: =forecast!E11 -> 0.315
A17: 2027E | C17: =forecast!F11 -> 0.327
A18: 2028E | C18: =forecast!G11 -> 0.339
A21: FCF
A22: Year | B22: Actual | C22: Forecast
A23: 2023A | B23: =forecast!B23 -> 6925.749
A24: 2024A | B24: =forecast!C23 -> 6921.826
A25: 2025A | B25: =forecast!$D$23 -> 9461.053 | C25: =forecast!$D$23 -> 9461.053
A26: 2026E | C26: =forecast!E23 -> 12500
A27: 2027E | C27: =forecast!F23 -> 14269.876
A28: 2028E | C28: =forecast!G23 -> 16010.801
A31: Cases In Billions ($B)
A32: 2028 Scenario | B32: Bear Case | C32: Base Case | D32: Bull Case
A33: Revenue | B33: =scenarios!B18 -> 59705.673 | C33: =scenarios!C18 -> 62787.454 | D33: =scenarios!D18 -> 65946.024
A34: Operating Income | B34: =scenarios!B19 -> 18210.23 | C34: =scenarios!C19 -> 21284.947 | D34: =scenarios!D19 -> 23410.838
A35: Free Cash Flow | B35: =scenarios!B20 -> 13732.305 | C35: =scenarios!C20 -> 16010.801 | D35: =scenarios!D20 -> 18135.157

Sheet dashboard
A1: NETFLIX FINANCIAL PERFORMANCE & FORECAST
A2: Historical Performance (2023-2025) | Forecast (2026-2028)
A5: Key Metric | B5: 2025A | C5: 2028E | E5: Key Takeaways
A6: Revenue ($B) | B6: =forecast!D2/1000 -> 45.183036 | C6: =forecast!G2/1000 -> 62.787454
A7: Operating Margin | B7: =forecast!D11 -> 0.29494705 | C7: =forecast!G11 -> 0.339 | E7: Base-case revenue reaches $62.8B by 2028, supported by pricing, advertising, membership, and international growth.
A8: Net Margin | B8: =forecast!D17 -> 0.24303814 | C8: =forecast!G17 -> 0.28384498 | E8: Operating margin expands from 29.5% in 2025 to 33.9% in 2028, reflecting continued operating leverage.
A9: Free Cash Flow ($B) | B9: =forecast!D23/1000 -> 9.461053 | C9: =forecast!G23/1000 -> 16.010801 | E9: Free cash flow increases from $9.5B to $16.0B, with 2028 scenario outcomes ranging from $13.7B to $18.1B.
A10: FCF Margin | B10: =forecast!D24 -> 0.20939392 | C10: =forecast!G24 -> 0.255
O51: S
